Workbook

Sheet Presentation
E5: 45657 | F5: 46022 | G5: 46387 | H5: 46752 | I5: 47118 | J5: 47483 | K5: 47848 | L5: 48213 | O5: 45657 | P5: 46022 | Q5: 46387 | R5: 46752 | S5: 47118 | T5: 47483 | U5: 47848 | V5: 48213 | Z5: =P5 -> 46022 | AA5: =Q5 -> 46387 | AB5: =R5 -> 46752 | AC5: =S5 -> 47118 | AD5: =T5 -> 47483 | AE5: =U5 -> 47848 | AF5: =V5 -> 48213
D6: ='Valuation (Base)'!D5 -> Revenue | E6: ='Valuation (Base)'!F5 -> 3820845.7 | F6: ='Valuation (Base)'!G5 -> 3800977.3 | G6: ='Valuation (Base)'!H5 -> 3978863.1 | H6: ='Valuation (Base)'!I5 -> 4240672.3 | I6: ='Valuation (Base)'!J5 -> 4373829.4 | J6: ='Valuation (Base)'!K5 -> 4592520.9 | K6: ='Valuation (Base)'!L5 -> 4765934.4 | L6: ='Valuation (Base)'!M5 -> 4986845 | N6: Revenue | O6: ='Valuation (Downside)'!F5 -> 3820845.7 | P6: ='Valuation (Downside)'!G5 -> 3629803.5 | Q6: ='Valuation (Downside)'!H5 -> 3520909.4 | R6: ='Valuation (Downside)'!I5 -> 3520909.4 | S6: ='Valuation (Downside)'!J5 -> 3591327.5 | T6: ='Valuation (Downside)'!K5 -> 3699067.4 | U6: ='Valuation (Downside)'!L5 -> 3838744.2 | V6: ='Valuation (Downside)'!M5 -> 4016677.6 | X6: =_xlfn.CONCAT("Δ ",N6) -> Δ Revenue | Z6: =P6-F6 -> -171173.89 | AA6: =Q6-G6 -> -457953.73 | AB6: =R6-H6 -> -719762.92 | AC6: =S6-I6 -> -782501.85 | AD6: =T6-J6 -> -893453.49 | AE6: =U6-K6 -> -927190.29 | AF6: =V6-L6 -> -970167.42
D7: ='Valuation (Base)'!D72 -> EBITDA | E7: ='Valuation (Base)'!F72 -> 478336.62 | F7: ='Valuation (Base)'!G72 -> 484191.38 | G7: ='Valuation (Base)'!H72 -> 506656.92 | H7: ='Valuation (Base)'!I72 -> 555267.69 | I7: ='Valuation (Base)'!J72 -> 564646.36 | J7: ='Valuation (Base)'!K72 -> 584684.72 | K7: ='Valuation (Base)'!L72 -> 612013.34 | L7: ='Valuation (Base)'!M72 -> 641406.79 | N7: EBITDA | O7: ='Valuation (Downside)'!F66 -> 478336.62 | P7: ='Valuation (Downside)'!G66 -> 371641.13 | Q7: ='Valuation (Downside)'!H66 -> 377924.23 | R7: ='Valuation (Downside)'!I66 -> 415251.12 | S7: ='Valuation (Downside)'!J66 -> 434897.44 | T7: ='Valuation (Downside)'!K66 -> 470937.04 | U7: ='Valuation (Downside)'!L66 -> 492949 | V7: ='Valuation (Downside)'!M66 -> 516624.1 | X7: =_xlfn.CONCAT("Δ ",N7) -> Δ EBITDA | Z7: =P7-F7 -> -112550.25 | AA7: =Q7-G7 -> -128732.69 | AB7: =R7-H7 -> -140016.57 | AC7: =S7-I7 -> -129748.92 | AD7: =T7-J7 -> -113747.68 | AE7: =U7-K7 -> -119064.34 | AF7: =V7-L7 -> -124782.7
D8: ='Valuation (Base)'!D9 -> EBIT | E8: ='Valuation (Base)'!F9 -> 396112.25 | F8: ='Valuation (Base)'!G9 -> 406509.1 | G8: ='Valuation (Base)'!H9 -> 426294.94 | H8: ='Valuation (Base)'!I9 -> 470491.83 | I8: ='Valuation (Base)'!J9 -> 476396.03 | J8: ='Valuation (Base)'!K9 -> 490700.95 | K8: ='Valuation (Base)'!L9 -> 515486.74 | L8: ='Valuation (Base)'!M9 -> 540589.51 | N8: EBIT | O8: ='Valuation (Downside)'!F9 -> 396112.25 | P8: ='Valuation (Downside)'!G9 -> 297457.21 | Q8: ='Valuation (Downside)'!H9 -> 306811.64 | R8: ='Valuation (Downside)'!I9 -> 344864.14 | S8: ='Valuation (Downside)'!J9 -> 362435.57 | T8: ='Valuation (Downside)'!K9 -> 395237.37 | U8: ='Valuation (Downside)'!L9 -> 415201.2 | V8: ='Valuation (Downside)'!M9 -> 435420.34 | X8: =_xlfn.CONCAT("Δ ",N8) -> Δ EBIT | Z8: =P8-F8 -> -109051.89 | AA8: =Q8-G8 -> -119483.3 | AB8: =R8-H8 -> -125627.69 | AC8: =S8-I8 -> -113960.46 | AD8: =T8-J8 -> -95463.578 | AE8: =U8-K8 -> -100285.54 | AF8: =V8-L8 -> -105169.16
D9: ='Valuation (Base)'!D13 -> Net Income | E9: ='Valuation (Base)'!F13 -> 266918.14 | F9: ='Valuation (Base)'!G13 -> 277602.98 | G9: ='Valuation (Base)'!H13 -> 291954.03 | H9: ='Valuation (Base)'!I13 -> 323881.59 | I9: ='Valuation (Base)'!J13 -> 327513.49 | J9: ='Valuation (Base)'!K13 -> 337670.52 | K9: ='Valuation (Base)'!L13 -> 356290.05 | L9: ='Valuation (Base)'!M13 -> 374377.5 | N9: Net Income | O9: ='Valuation (Downside)'!F13 -> 266918.14 | P9: ='Valuation (Downside)'!G13 -> 195976.97 | Q9: ='Valuation (Downside)'!H13 -> 203601.86 | R9: ='Valuation (Downside)'!I13 -> 231974.86 | S9: ='Valuation (Downside)'!J13 -> 244651.28 | T9: ='Valuation (Downside)'!K13 -> 269173.34 | U9: ='Valuation (Downside)'!L13 -> 284155.85 | V9: ='Valuation (Downside)'!M13 -> 298777.87 | X9: =_xlfn.CONCAT("Δ ",N9) -> Δ Net Income | Z9: =P9-F9 -> -81626.008 | AA9: =Q9-G9 -> -88352.166 | AB9: =R9-H9 -> -91906.733 | AC9: =S9-I9 -> -82862.21 | AD9: =T9-J9 -> -68497.179 | AE9: =U9-K9 -> -72134.2 | AF9: =V9-L9 -> -75599.628
D10: Free Cash Flow | E10: ='Valuation (Base)'!F17 -> 257155.98 | F10: ='Valuation (Base)'!G17 -> 329315.33 | G10: ='Valuation (Base)'!H17 -> 275755.63 | H10: ='Valuation (Base)'!I17 -> 281751.36 | I10: ='Valuation (Base)'!J17 -> 320125.97 | J10: ='Valuation (Base)'!K17 -> 306573.89 | K10: ='Valuation (Base)'!L17 -> 342268.46 | L10: ='Valuation (Base)'!M17 -> 350798.57 | N10: Free Cash Flow | O10: ='Valuation (Downside)'!F17 -> 257155.98 | P10: ='Valuation (Downside)'!G17 -> 186827.5 | Q10: ='Valuation (Downside)'!H17 -> 264325.8 | R10: ='Valuation (Downside)'!I17 -> 278154.25 | S10: ='Valuation (Downside)'!J17 -> 251876.13 | T10: ='Valuation (Downside)'!K17 -> 270291.95 | U10: ='Valuation (Downside)'!L17 -> 271274.86 | V10: ='Valuation (Downside)'!M17 -> 279078.56 | X10: =_xlfn.CONCAT("Δ ",N10) -> Δ Free Cash Flow | Z10: =P10-F10 -> -142487.83 | AA10: =Q10-G10 -> -11429.838 | AB10: =R10-H10 -> -3597.1139 | AC10: =S10-I10 -> -68249.838 | AD10: =T10-J10 -> -36281.94 | AE10: =U10-K10 -> -70993.599 | AF10: =V10-L10 -> -71720.001
D11: Equity Value | E11: ='Valuation (Base)'!M32 -> 4045942.7 | N11: Equity Value | O11: ='Valuation (Downside)'!M32 -> 3198602.3
D12: ='Valuation (Base)'!D41 -> Market Capitalization | E12: ='Valuation (Base)'!F41 -> 4129223.7 | N12: Market Capitalization | O12: ='Valuation (Downside)'!F41 -> 3203017.7
E14: 45657 | F14: 46022 | G14: 46387 | H14: 46752 | I14: 47118 | J14: 47483 | K14: 47848 | L14: 48213 | O14: 45657 | P14: 46022 | Q14: 46387 | R14: 46752 | S14: 47118 | T14: 47483 | U14: 47848 | V14: 48213 | Z14: =Z5 -> 46022 | AA14: =AA5 -> 46387 | AB14: =AB5 -> 46752 | AC14: =AC5 -> 47118 | AD14: =AD5 -> 47483 | AE14: =AE5 -> 47848 | AF14: =AF5 -> 48213
D15: ='Valuation (Base)'!D60 -> Debt-to-EBITDA | E15: ='Valuation (Base)'!F60 -> 1.1006361 | F15: ='Valuation (Base)'!G60 -> 1.0608635 | G15: ='Valuation (Base)'!H60 -> 1.0425161 | H15: ='Valuation (Base)'!I60 -> 0.97422874 | I15: ='Valuation (Base)'!J60 -> 0.98333907 | J15: ='Valuation (Base)'!K60 -> 0.9690077 | K15: ='Valuation (Base)'!L60 -> 0.93750013 | L15: ='Valuation (Base)'!M60 -> 0.91895858 | N15: =D15 -> Debt-to-EBITDA | O15: ='Valuation (Downside)'!F60 -> 1.1013854 | P15: ='Valuation (Downside)'!G60 -> 1.4102273 | Q15: ='Valuation (Downside)'!H60 -> 1.3807549 | R15: ='Valuation (Downside)'!I60 -> 1.2231208 | S15: ='Valuation (Downside)'!J60 -> 1.1733228 | T15: ='Valuation (Downside)'!K60 -> 1.0800245 | U15: ='Valuation (Downside)'!L60 -> 1.0594675 | V15: ='Valuation (Downside)'!M60 -> 1.0192473 | X15: Revenue | Z15: ='3-Statement (Downside)'!L10 -> -0.05 | AA15: ='3-Statement (Downside)'!M10 -> -0.03 | AB15: ='3-Statement (Downside)'!N10 -> 0 | AC15: ='3-Statement (Downside)'!O10 -> 0.02 | AD15: ='3-Statement (Downside)'!P10 -> 0.03 | AE15: ='3-Statement (Downside)'!Q10 -> 0.03776 | AF15: ='3-Statement (Downside)'!R10 -> 0.046352
D16: ='Valuation (Base)'!D64 -> Interest Coverage | E16: ='Valuation (Base)'!F64 -> 21.080314 | F16: ='Valuation (Base)'!G64 -> 21.681084 | G16: ='Valuation (Base)'!H64 -> 22.867734 | H16: ='Valuation (Base)'!I64 -> 25.571601 | I16: ='Valuation (Base)'!J64 -> 26.223442 | J16: ='Valuation (Base)'!K64 -> 27.369635 | K16: ='Valuation (Base)'!L64 -> 29.112104 | L16: ='Valuation (Base)'!M64 -> 30.877567 | N16: =D16 -> Interest Coverage | O16: ='Valuation (Downside)'!F64 -> 21.080314 | P16: ='Valuation (Downside)'!G64 -> 15.866339 | Q16: ='Valuation (Downside)'!H64 -> 16.504497 | R16: ='Valuation (Downside)'!I64 -> 18.71121 | S16: ='Valuation (Downside)'!J64 -> 19.770568 | T16: ='Valuation (Downside)'!K64 -> 21.771987 | U16: ='Valuation (Downside)'!L64 -> 23.071017 | V16: ='Valuation (Downside)'!M64 -> 24.509994 | X16: Δ COGS % Revenue | Z16: ='3-Statement (Downside)'!L12 -> 0.01 | AA16: ='3-Statement (Downside)'!M12 -> 0.008 | AB16: ='3-Statement (Downside)'!N12 -> 0.005 | AC16: ='3-Statement (Downside)'!O12 -> 0.003 | AD16: ='3-Statement (Downside)'!P12 -> 0 | AE16: ='3-Statement (Downside)'!Q12 -> 0 | AF16: ='3-Statement (Downside)'!R12 -> 0
D17: ='Valuation (Base)'!D70 -> Debt Service Coverage Ratio | E17: ='Valuation (Base)'!F70 -> 22.8102 | F17: ='Valuation (Base)'!G70 -> 23.158661 | G17: ='Valuation (Base)'!H70 -> 24.383723 | H17: ='Valuation (Base)'!I70 -> 27.066998 | I17: ='Valuation (Base)'!J70 -> 27.868054 | J17: ='Valuation (Base)'!K70 -> 29.230517 | K17: ='Valuation (Base)'!L70 -> 30.971858 | L17: ='Valuation (Base)'!M70 -> 32.824424 | N17: =D17 -> Debt Service Coverage Ratio | O17: ='Valuation (Downside)'!F70 -> 22.8102 | P17: ='Valuation (Downside)'!G70 -> 17.776956 | Q17: ='Valuation (Downside)'!H70 -> 18.234041 | R17: ='Valuation (Downside)'!I70 -> 20.210358 | S17: ='Valuation (Downside)'!J70 -> 21.290638 | T17: ='Valuation (Downside)'!K70 -> 23.282176 | U17: ='Valuation (Downside)'!L70 -> 24.585977 | V17: ='Valuation (Downside)'!M70 -> 26.094722 | X17: Δ OpEx % Revenue | Z17: ='3-Statement (Downside)'!L14 -> 0.015 | AA17: ='3-Statement (Downside)'!M14 -> 0.012 | AB17: ='3-Statement (Downside)'!N14 -> 0.008 | AC17: ='3-Statement (Downside)'!O14 -> 0.005 | AD17: ='3-Statement (Downside)'!P14 -> 0 | AE17: ='3-Statement (Downside)'!Q14 -> 0 | AF17: ='3-Statement (Downside)'!R14 -> 0
D18: ='Valuation (Base)'!D76 -> Fixed Charge Coverage Ratio | E18: ='Valuation (Base)'!F76 -> 11.895128 | F18: ='Valuation (Base)'!G76 -> 13.513415 | G18: ='Valuation (Base)'!H76 -> 13.787291 | H18: ='Valuation (Base)'!I76 -> 14.394623 | I18: ='Valuation (Base)'!J76 -> 14.26465 | J18: ='Valuation (Base)'!K76 -> 14.365361 | K18: ='Valuation (Base)'!L76 -> 15.039268 | L18: ='Valuation (Base)'!M76 -> 15.324398 | N18: =D18 -> Fixed Charge Coverage Ratio | O18: ='Valuation (Downside)'!F76 -> 11.895128 | P18: ='Valuation (Downside)'!G76 -> 10.833384 | Q18: ='Valuation (Downside)'!H76 -> 11.171563 | R18: ='Valuation (Downside)'!I76 -> 12.051782 | S18: ='Valuation (Downside)'!J76 -> 12.335028 | T18: ='Valuation (Downside)'!K76 -> 13.091308 | U18: ='Valuation (Downside)'!L76 -> 13.689609 | V18: ='Valuation (Downside)'!M76 -> 14.00353 | X18: Δ NWC % Revenue | Z18: ='3-Statement (Downside)'!L23 -> 0.024 | AA18: ='3-Statement (Downside)'!M23 -> 0.018 | AB18: ='3-Statement (Downside)'!N23 -> 0.006 | AC18: ='3-Statement (Downside)'!O23 -> 0.003 | AD18: ='3-Statement (Downside)'!P23 -> 0 | AE18: ='3-Statement (Downside)'!Q23 -> 0 | AF18: ='3-Statement (Downside)'!R23 -> 0
D19: ='Valuation (Base)'!D80 -> Current Ratio | E19: ='Valuation (Base)'!F80 -> 2.1056234 | F19: ='Valuation (Base)'!G80 -> 2.0872094 | G19: ='Valuation (Base)'!H80 -> 2.1184821 | H19: ='Valuation (Base)'!I80 -> 2.1661126 | I19: ='Valuation (Base)'!J80 -> 2.1833194 | J19: ='Valuation (Base)'!K80 -> 2.215593 | K19: ='Valuation (Base)'!L80 -> 2.2399978 | L19: ='Valuation (Base)'!M80 -> 2.2678933 | N19: =D19 -> Current Ratio | O19: ='Valuation (Downside)'!F80 -> 2.1056234 | P19: ='Valuation (Downside)'!G80 -> 2.1584917 | Q19: ='Valuation (Downside)'!H80 -> 2.1720491 | R19: ='Valuation (Downside)'!I80 -> 2.1840386 | S19: ='Valuation (Downside)'!J80 -> 2.1923235 | T19: ='Valuation (Downside)'!K80 -> 2.215593 | U19: ='Valuation (Downside)'!L80 -> 2.2399978 | V19: ='Valuation (Downside)'!M80 -> 2.2678933 | X19: Δ CapEx % Revenue | Z19: ='3-Statement (Downside)'!L25 -> -0.003 | AA19: ='3-Statement (Downside)'!M25 -> -0.002 | AB19: ='3-Statement (Downside)'!N25 -> -0.001 | AC19: ='3-Statement (Downside)'!O25 -> -0.001 | AD19: ='3-Statement (Downside)'!P25 -> 0 | AE19: ='3-Statement (Downside)'!Q25 -> 0 | AF19: ='3-Statement (Downside)'!R25 -> 0
D20: ='Valuation (Base)'!D86 -> Quick Ratio | E20: ='Valuation (Base)'!F86 -> 0.77170049 | F20: ='Valuation (Base)'!G86 -> 0.7656641 | G20: ='Valuation (Base)'!H86 -> 0.77591577 | H20: ='Valuation (Base)'!I86 -> 0.79152985 | I20: ='Valuation (Base)'!J86 -> 0.7971705 | J20: ='Valuation (Base)'!K86 -> 0.8077503 | K20: ='Valuation (Base)'!L86 -> 0.8157506 | L20: ='Valuation (Base)'!M86 -> 0.8248952 | N20: =D20 -> Quick Ratio | O20: ='Valuation (Downside)'!F86 -> 0.77170049 | P20: ='Valuation (Downside)'!G86 -> 0.78903157 | Q20: ='Valuation (Downside)'!H86 -> 0.79347593 | R20: ='Valuation (Downside)'!I86 -> 0.79740626 | S20: ='Valuation (Downside)'!J86 -> 0.80012218 | T20: ='Valuation (Downside)'!K86 -> 0.8077503 | U20: ='Valuation (Downside)'!L86 -> 0.8157506 | V20: ='Valuation (Downside)'!M86 -> 0.8248952 | X20: Δ Other % Revenue | Z20: ='3-Statement (Downside)'!L28 -> -0.004 | AA20: ='3-Statement (Downside)'!M28 -> -0.004 | AB20: ='3-Statement (Downside)'!N28 -> -0.003 | AC20: ='3-Statement (Downside)'!O28 -> -0.002 | AD20: ='3-Statement (Downside)'!P28 -> 0 | AE20: ='3-Statement (Downside)'!Q28 -> 0 | AF20: ='3-Statement (Downside)'!R28 -> 0

Sheet Valuation (Base)
D3: VALUATION
E4: ='3-Statement (Base)'!J2 -> Q4-24 | F4: ='3-Statement (Base)'!K2 -> 45657 | G4: ='3-Statement (Base)'!L2 -> 46022 | H4: ='3-Statement (Base)'!M2 -> 46387 | I4: ='3-Statement (Base)'!N2 -> 46752 | J4: ='3-Statement (Base)'!O2 -> 47118 | K4: ='3-Statement (Base)'!P2 -> 47483 | L4: ='3-Statement (Base)'!Q2 -> 47848 | M4: ='3-Statement (Base)'!R2 -> 48213
D5: Revenue | E5: ='3-Statement (Base)'!J43 -> 952178.75 | F5: ='3-Statement (Base)'!K43 -> 3820845.7 | G5: ='3-Statement (Base)'!L43 -> 3800977.3 | H5: ='3-Statement (Base)'!M43 -> 3978863.1 | I5: ='3-Statement (Base)'!N43 -> 4240672.3 | J5: ='3-Statement (Base)'!O43 -> 4373829.4 | K5: ='3-Statement (Base)'!P43 -> 4592520.9 | L5: ='3-Statement (Base)'!Q43 -> 4765934.4 | M5: ='3-Statement (Base)'!R43 -> 4986845
D6: Cost of Goods Sold | E6: ='3-Statement (Base)'!J46 -> -559738.78 | F6: ='3-Statement (Base)'!K46 -> -2246230.8 | G6: ='3-Statement (Base)'!L46 -> -2222863.2 | H6: ='3-Statement (Base)'!M46 -> -2331350.5 | I6: ='3-Statement (Base)'!N46 -> -2482296.6 | J6: ='3-Statement (Base)'!O46 -> -2566738 | K6: ='3-Statement (Base)'!P46 -> -2691979.9 | L6: ='3-Statement (Base)'!Q46 -> -2791987.3 | M6: ='3-Statement (Base)'!R46 -> -2922406.9
D7: Operating Expenses | E7: ='3-Statement (Base)'!J47 -> -289178.76 | F7: ='3-Statement (Base)'!K47 -> -1160037.8 | G7: ='3-Statement (Base)'!L47 -> -1137677.8 | H7: ='3-Statement (Base)'!M47 -> -1185928.2 | I7: ='3-Statement (Base)'!N47 -> -1256691.8 | J7: ='3-Statement (Base)'!O47 -> -1298569.4 | K7: ='3-Statement (Base)'!P47 -> -1372442.2 | L7: ='3-Statement (Base)'!Q47 -> -1419724 | M7: ='3-Statement (Base)'!R47 -> -1484112.8
D8: Restructuring Costs | E8: ='3-Statement (Base)'!J49 -> -6677.9508 | F8: ='3-Statement (Base)'!K49 -> -18464.951 | G8: ='3-Statement (Base)'!L49 -> -33927.258 | H8: ='3-Statement (Base)'!M49 -> -35289.429 | I8: ='3-Statement (Base)'!N49 -> -31192.044 | J8: ='3-Statement (Base)'!O49 -> -32125.93 | K8: ='3-Statement (Base)'!P49 -> -37397.865 | L8: ='3-Statement (Base)'!Q49 -> -38736.417 | M8: ='3-Statement (Base)'!R49 -> -39735.867
D9: EBIT | E9: =SUM(E5:E8) -> 96583.254 | F9: =SUM(F5:F8) -> 396112.25 | G9: =SUM(G5:G8) -> 406509.1 | H9: =SUM(H5:H8) -> 426294.94 | I9: =SUM(I5:I8) -> 470491.83 | J9: =SUM(J5:J8) -> 476396.03 | K9: =SUM(K5:K8) -> 490700.95 | L9: =SUM(L5:L8) -> 515486.74 | M9: =SUM(M5:M8) -> 540589.51
D10: Net Interest | E10: ='3-Statement (Base)'!J55 -> -4723.6238 | F10: ='3-Statement (Base)'!K55 -> -18790.624 | G10: ='3-Statement (Base)'!L55 -> -18749.482 | H10: ='3-Statement (Base)'!M55 -> -18641.766 | I10: ='3-Statement (Base)'!N55 -> -18398.998 | J10: ='3-Statement (Base)'!O55 -> -18166.8 | K10: ='3-Statement (Base)'!P55 -> -17928.663 | L10: ='3-Statement (Base)'!Q55 -> -17706.956 | M10: ='3-Statement (Base)'!R55 -> -17507.516
D11: Other Income (Expense) | E11: ='3-Statement (Base)'!J54 -> -6260.0937 | F11: ='3-Statement (Base)'!K54 -> -25113.094 | G11: ='3-Statement (Base)'!L54 -> -19944.303 | H11: ='3-Statement (Base)'!M54 -> -20980.147 | I11: ='3-Statement (Base)'!N54 -> -23055.523 | J11: ='3-Statement (Base)'!O54 -> -24400.953 | K11: ='3-Statement (Base)'!P54 -> -25817.608 | L11: ='3-Statement (Base)'!Q54 -> -25886.011 | M11: ='3-Statement (Base)'!R54 -> -27269.709
D12: Taxes | E12: ='3-Statement (Base)'!J58 -> -20686.393 | F12: ='3-Statement (Base)'!K58 -> -85290.393 | G12: ='3-Statement (Base)'!L58 -> -90212.334 | H12: ='3-Statement (Base)'!M58 -> -94719 | I12: ='3-Statement (Base)'!N58 -> -105155.72 | J12: ='3-Statement (Base)'!O58 -> -106314.79 | K12: ='3-Statement (Base)'!P58 -> -109284.16 | L12: ='3-Statement (Base)'!Q58 -> -115603.72 | M12: ='3-Statement (Base)'!R58 -> -121434.78
D13: Net Income | E13: =SUM(E9:E12) -> 64913.144 | F13: =SUM(F9:F12) -> 266918.14 | G13: =SUM(G9:G12) -> 277602.98 | H13: =SUM(H9:H12) -> 291954.03 | I13: =SUM(I9:I12) -> 323881.59 | J13: =SUM(J9:J12) -> 327513.49 | K13: =SUM(K9:K12) -> 337670.52 | L13: =SUM(L9:L12) -> 356290.05 | M13: =SUM(M9:M12) -> 374377.5
D15: Cash Flow from Operations | E15: ='3-Statement (Base)'!J98 -> 51395.363 | F15: ='3-Statement (Base)'!K98 -> 354828.36 | G15: ='3-Statement (Base)'!L98 -> 402710.6 | H15: ='3-Statement (Base)'!M98 -> 356238.35 | I15: ='3-Statement (Base)'!N98 -> 370630.43 | J15: ='3-Statement (Base)'!O98 -> 415587.95 | K15: ='3-Statement (Base)'!P98 -> 405666.36 | L15: ='3-Statement (Base)'!Q98 -> 441303.16 | M15: ='3-Statement (Base)'!R98 -> 455889.97
D16: Capital Expenditures | E16: ='3-Statement (Base)'!J101 -> -24318.379 | F16: ='3-Statement (Base)'!K101 -> -97672.379 | G16: ='3-Statement (Base)'!L101 -> -73395.274 | H16: ='3-Statement (Base)'!M101 -> -80482.712 | I16: ='3-Statement (Base)'!N101 -> -88879.07 | J16: ='3-Statement (Base)'!O101 -> -95461.983 | K16: ='3-Statement (Base)'!P101 -> -99092.467 | L16: ='3-Statement (Base)'!Q101 -> -99034.698 | M16: ='3-Statement (Base)'!R101 -> -105091.41
D17: Free Cash Flow | E17: =SUM(E15:E16) -> 27076.985 | F17: =SUM(F15:F16) -> 257155.98 | G17: =SUM(G15:G16) -> 329315.33 | H17: =SUM(H15:H16) -> 275755.63 | I17: =SUM(I15:I16) -> 281751.36 | J17: =SUM(J15:J16) -> 320125.97 | K17: =SUM(K15:K16) -> 306573.89 | L17: =SUM(L15:L16) -> 342268.46 | M17: =SUM(M15:M16) -> 350798.57
D19: Free Cash Flow | G19: =G17 -> 329315.33 | H19: =H17 -> 275755.63 | I19: =I17 -> 281751.36 | J19: =J17 -> 320125.97 | K19: =K17 -> 306573.89 | L19: =L17 -> 342268.46 | M19: =M17 -> 350798.57
D20: Growth Rate | M20: 0.03
D21: WACC (Given) | M21: 0.093
D22: Terminal Value | M22: =(M19*(1+M20))/(M21-M20) -> 5735278.1
D23: Discounted Terminal Value | M23: =M22/((1+M21)^COUNT(G19:M19)) -> 3077608.3
D24: Present Value of Cash Flows | M24: =NPV(M21,G19:M19) -> 1557723.5
D25: Enterprise Value | M25: =M24+M23 -> 4635331.9
D27: Enterprise Value | M27: =M25 -> 4635331.9
D28: Total Debt | M28: =-M48 -> -589426.28
D29: Cash & Cash Equivalents | M29: ='3-Statement (Base)'!R68 -> 25000
D30: Net Debt | M30: =M28+M29 -> -564426.28
D31: Minority Interest | M31: =-'3-Statement (Base)'!R84 -> -24962.83
D32: Implied Equity Value | M32: =M27+M30+M31 -> 4045942.7
D34: Implied Equity Value | M34: =M32 -> 4045942.7
D35: Weighted-Average Shares Outstanding | M35: 55900
D36: Per-Share Value | M36: =M34/M35 -> 72.378224
D38: Net Income | F38: =F13 -> 266918.14
D39: Shares | F39: =$M$35 -> 55900
D40: EPS | F40: =F38/F39 -> 4.7749221
D41: Market Capitalization | F41: =F38*F42 -> 4129223.7
D42: 3-Year Average PE Ratio | F42: 15.47
D43: Per-Share Value | F43: =F41/F39 -> 73.868044
D44: Average Per-Share Value | F44: =AVERAGE(F43,M36) -> 73.123134
D46: SUMMARY OUTPUTS
E47: =E4 -> Q4-24 | F47: =F4 -> 45657 | G47: =G4 -> 46022 | H47: =H4 -> 46387 | I47: =I4 -> 46752 | J47: =J4 -> 47118 | K47: =K4 -> 47483 | L47: =L4 -> 47848 | M47: =M4 -> 48213
D48: Total Debt | E48: ='3-Statement (Base)'!J76+'3-Statement (Base)'!J77+'3-Statement (Base)'!J78 -> 526474.58 | F48: ='3-Statement (Base)'!K76+'3-Statement (Base)'!K77+'3-Statement (Base)'!K78 -> 526474.58 | G48: ='3-Statement (Base)'!L76+'3-Statement (Base)'!L77+'3-Statement (Base)'!L78 -> 513660.94 | H48: ='3-Statement (Base)'!M76+'3-Statement (Base)'!M77+'3-Statement (Base)'!M78 -> 528197.99 | I48: ='3-Statement (Base)'!N76+'3-Statement (Base)'!N77+'3-Statement (Base)'!N78 -> 540957.74 | J48: ='3-Statement (Base)'!O76+'3-Statement (Base)'!O77+'3-Statement (Base)'!O78 -> 555238.82 | K48: ='3-Statement (Base)'!P76+'3-Statement (Base)'!P77+'3-Statement (Base)'!P78 -> 566564 | L48: ='3-Statement (Base)'!Q76+'3-Statement (Base)'!Q77+'3-Statement (Base)'!Q78 -> 573762.59 | M48: ='3-Statement (Base)'!R76+'3-Statement (Base)'!R77+'3-Statement (Base)'!R78 -> 589426.28
D49: Total Capitalization | E49: =E48+E52 -> 1934967.6 | F49: =F48+F52 -> 1934967.6 | G49: =G48+G52 -> 1899458.3 | H49: =H48+H52 -> 1935507.8 | I49: =I48+I52 -> 1997973.9 | J49: =J48+J52 -> 2023947.3 | K49: =K48+K52 -> 2074593 | L49: =L48+L52 -> 2110087.4 | M49: =M48+M52 -> 2156376.8
D50: Debt-to-Capital | E50: =E48/E49 -> 0.27208444 | F50: =F48/F49 -> 0.27208444 | G50: =G48/G49 -> 0.27042497 | H50: =H48/H49 -> 0.27289892 | I50: =I48/I49 -> 0.27075316 | J50: =J48/J49 -> 0.27433463 | K50: =K48/K49 -> 0.27309645 | L50: =L48/L49 -> 0.27191413 | M50: =M48/M49 -> 0.27334105
D52: Total Equity | E52: ='3-Statement (Base)'!J83-'3-Statement (Base)'!J84 -> 1408493 | F52: ='3-Statement (Base)'!K83-'3-Statement (Base)'!K84 -> 1408493 | G52: ='3-Statement (Base)'!L83-'3-Statement (Base)'!L84 -> 1385797.3 | H52: ='3-Statement (Base)'!M83-'3-Statement (Base)'!M84 -> 1407309.8 | I52: ='3-Statement (Base)'!N83-'3-Statement (Base)'!N84 -> 1457016.2 | J52: ='3-Statement (Base)'!O83-'3-Statement (Base)'!O84 -> 1468708.5 | K52: ='3-Statement (Base)'!P83-'3-Statement (Base)'!P84 -> 1508029 | L52: ='3-Statement (Base)'!Q83-'3-Statement (Base)'!Q84 -> 1536324.8 | M52: ='3-Statement (Base)'!R83-'3-Statement (Base)'!R84 -> 1566950.5
D53: Total Capitalization | E53: =E48+E52 -> 1934967.6 | F53: =F48+F52 -> 1934967.6 | G53: =G48+G52 -> 1899458.3 | H53: =H48+H52 -> 1935507.8 | I53: =I48+I52 -> 1997973.9 | J53: =J48+J52 -> 2023947.3 | K53: =K48+K52 -> 2074593 | L53: =L48+L52 -> 2110087.4 | M53: =M48+M52 -> 2156376.8
D54: Equity-to-Capital | E54: =E52/E53 -> 0.72791556 | F54: =F52/F53 -> 0.72791556 | G54: =G52/G53 -> 0.72957503 | H54: =H52/H53 -> 0.72710108 | I54: =I52/I53 -> 0.72924684 | J54: =J52/J53 -> 0.72566537 | K54: =K52/K53 -> 0.72690355 | L54: =L52/L53 -> 0.72808587 | M54: =M52/M53 -> 0.72665895
D56: Total Debt | E56: =E48 -> 526474.58 | F56: =F48 -> 526474.58 | G56: =G48 -> 513660.94 | H56: =H48 -> 528197.99 | I56: =I48 -> 540957.74 | J56: =J48 -> 555238.82 | K56: =K48 -> 566564 | L56: =L48 -> 573762.59 | M56: =M48 -> 589426.28
D57: EBIT | E57: =E9 -> 96583.254 | F57: =F9 -> 396112.25 | G57: =G9 -> 406509.1 | H57: =H9 -> 426294.94 | I57: =I9 -> 470491.83 | J57: =J9 -> 476396.03 | K57: =K9 -> 490700.95 | L57: =L9 -> 515486.74 | M57: =M9 -> 540589.51
D58: Depreciation & Amortization | E58: ='3-Statement (Base)'!J94 -> 20499.369 | F58: ='3-Statement (Base)'!K94 -> 82224.369 | G58: ='3-Statement (Base)'!L94 -> 77682.279 | H58: ='3-Statement (Base)'!M94 -> 80361.977 | I58: ='3-Statement (Base)'!N94 -> 84775.859 | J58: ='3-Statement (Base)'!O94 -> 88250.329 | K58: ='3-Statement (Base)'!P94 -> 93983.779 | L58: ='3-Statement (Base)'!Q94 -> 96526.604 | M58: ='3-Statement (Base)'!R94 -> 100817.29
D59: Annualized EBITDA | E59: =(E57+E58)*4 -> 468330.49 | F59: =(F57+F58) -> 478336.62 | G59: =(G57+G58) -> 484191.38 | H59: =(H57+H58) -> 506656.92 | I59: =(I57+I58) -> 555267.69 | J59: =(J57+J58) -> 564646.36 | K59: =(K57+K58) -> 584684.72 | L59: =(L57+L58) -> 612013.34 | M59: =(M57+M58) -> 641406.79
D60: Debt-to-EBITDA | E60: =E56/E59 -> 1.1241518 | F60: =F56/F59 -> 1.1006361 | G60: =G56/G59 -> 1.0608635 | H60: =H56/H59 -> 1.0425161 | I60: =I56/I59 -> 0.97422874 | J60: =J56/J59 -> 0.98333907 | K60: =K56/K59 -> 0.9690077 | L60: =L56/L59 -> 0.93750013 | M60: =M56/M59 -> 0.91895858
D62: EBIT | E62: =E57 -> 96583.254 | F62: =F57 -> 396112.25 | G62: =G57 -> 406509.1 | H62: =H57 -> 426294.94 | I62: =I57 -> 470491.83 | J62: =J57 -> 476396.03 | K62: =K57 -> 490700.95 | L62: =L57 -> 515486.74 | M62: =M57 -> 540589.51
D63: Interest Expense | E63: =-'3-Statement (Base)'!J55 -> 4723.6238 | F63: =-'3-Statement (Base)'!K55 -> 18790.624 | G63: =-'3-Statement (Base)'!L55 -> 18749.482 | H63: =-'3-Statement (Base)'!M55 -> 18641.766 | I63: =-'3-Statement (Base)'!N55 -> 18398.998 | J63: =-'3-Statement (Base)'!O55 -> 18166.8 | K63: =-'3-Statement (Base)'!P55 -> 17928.663 | L63: =-'3-Statement (Base)'!Q55 -> 17706.956 | M63: =-'3-Statement (Base)'!R55 -> 17507.516
D64: Interest Coverage | E64: =E62/E63 -> 20.446856 | F64: =F62/F63 -> 21.080314 | G64: =G62/G63 -> 21.681084 | H64: =H62/H63 -> 22.867734 | I64: =I62/I63 -> 25.571601 | J64: =J62/J63 -> 26.223442 | K64: =K62/K63 -> 27.369635 | L64: =L62/L63 -> 29.112104 | M64: =M62/M63 -> 30.877567
D66: EBITDA | E66: =E59/4 -> 117082.62 | F66: =F59 -> 478336.62 | G66: =G59 -> 484191.38 | H66: =H59 -> 506656.92 | I66: =I59 -> 555267.69 | J66: =J59 -> 564646.36 | K66: =K59 -> 584684.72 | L66: =L59 -> 612013.34 | M66: =M59 -> 641406.79
D67: Interest Expense | E67: =E63 -> 4723.6238 | F67: =F63 -> 18790.624 | G67: =G63 -> 18749.482 | H67: =H63 -> 18641.766 | I67: =I63 -> 18398.998 | J67: =J63 -> 18166.8 | K67: =K63 -> 17928.663 | L67: =L63 -> 17706.956 | M67: =M63 -> 17507.516
D68: Estimated Principal Payment (1%) | E68: ='3-Statement (Base)'!J78*0.01 -> 2179.6708 | F68: ='3-Statement (Base)'!K78*0.01 -> 2179.6708 | G68: ='3-Statement (Base)'!L78*0.01 -> 2158.0899 | H68: ='3-Statement (Base)'!M78*0.01 -> 2136.7227 | I68: ='3-Statement (Base)'!N78*0.01 -> 2115.567 | J68: ='3-Statement (Base)'!O78*0.01 -> 2094.6208 | K68: ='3-Statement (Base)'!P78*0.01 -> 2073.882 | L68: ='3-Statement (Base)'!Q78*0.01 -> 2053.3485 | M68: ='3-Statement (Base)'!R78*0.01 -> 2033.0183
D69: Total Debt Service | E69: =(E67+E68) -> 6903.2946 | F69: =(F67+F68) -> 20970.295 | G69: =(G67+G68) -> 20907.572 | H69: =(H67+H68) -> 20778.489 | I69: =(I67+I68) -> 20514.565 | J69: =(J67+J68) -> 20261.421 | K69: =(K67+K68) -> 20002.545 | L69: =(L67+L68) -> 19760.304 | M69: =(M67+M68) -> 19540.535
D70: Debt Service Coverage Ratio | E70: =E66/E69 -> 16.960398 | F70: =F66/F69 -> 22.8102 | G70: =G66/G69 -> 23.158661 | H70: =H66/H69 -> 24.383723 | I70: =I66/I69 -> 27.066998 | J70: =J66/J69 -> 27.868054 | K70: =K66/K69 -> 29.230517 | L70: =L66/L69 -> 30.971858 | M70: =M66/M69 -> 32.824424
D72: EBITDA | E72: =E66 -> 117082.62 | F72: =F66 -> 478336.62 | G72: =G66 -> 484191.38 | H72: =H66 -> 506656.92 | I72: =I66 -> 555267.69 | J72: =J66 -> 564646.36 | K72: =K66 -> 584684.72 | L72: =L66 -> 612013.34 | M72: =M66 -> 641406.79
D73: Interest Expense | E73: =E63 -> 4723.6238 | F73: =F63 -> 18790.624 | G73: =G63 -> 18749.482 | H73: =H63 -> 18641.766 | I73: =I63 -> 18398.998 | J73: =J63 -> 18166.8 | K73: =K63 -> 17928.663 | L73: =L63 -> 17706.956 | M73: =M63 -> 17507.516
D74: Other Expense | E74: =-'3-Statement (Base)'!J54 -> 6260.0937 | F74: =-'3-Statement (Base)'!K54 -> 25113.094 | G74: =-'3-Statement (Base)'!L54 -> 19944.303 | H74: =-'3-Statement (Base)'!M54 -> 20980.147 | I74: =-'3-Statement (Base)'!N54 -> 23055.523 | J74: =-'3-Statement (Base)'!O54 -> 24400.953 | K74: =-'3-Statement (Base)'!P54 -> 25817.608 | L74: =-'3-Statement (Base)'!Q54 -> 25886.011 | M74: =-'3-Statement (Base)'!R54 -> 27269.709
D75: Fixed Charges | E75: =SUM(E73:E74) -> 10983.717 | F75: =SUM(F73:F74) -> 43903.717 | G75: =SUM(G73:G74) -> 38693.785 | H75: =SUM(H73:H74) -> 39621.913 | I75: =SUM(I73:I74) -> 41454.521 | J75: =SUM(J73:J74) -> 42567.753 | K75: =SUM(K73:K74) -> 43746.271 | L75: =SUM(L73:L74) -> 43592.967 | M75: =SUM(M73:M74) -> 44777.225
D76: Fixed Charge Coverage Ratio | E76: =(E72+E75)/E75 -> 11.659654 | F76: =(F72+F75)/F75 -> 11.895128 | G76: =(G72+G75)/G75 -> 13.513415 | H76: =(H72+H75)/H75 -> 13.787291 | I76: =(I72+I75)/I75 -> 14.394623 | J76: =(J72+J75)/J75 -> 14.26465 | K76: =(K72+K75)/K75 -> 14.365361 | L76: =(L72+L75)/L75 -> 15.039268 | M76: =(M72+M75)/M75 -> 15.324398
D78: Current Assets | E78: ='Balance Sheet NWC (Base)'!J11 -> 1262501.9 | F78: ='Balance Sheet NWC (Base)'!K11 -> 1262501.9 | G78: ='Balance Sheet NWC (Base)'!L11 -> 1229713.9 | H78: ='Balance Sheet NWC (Base)'!M11 -> 1286094.5 | I78: ='Balance Sheet NWC (Base)'!N11 -> 1378875 | J78: ='Balance Sheet NWC (Base)'!O11 -> 1414647.8 | K78: ='Balance Sheet NWC (Base)'!P11 -> 1485309.5 | L78: ='Balance Sheet NWC (Base)'!Q11 -> 1542082.6 | M78: ='Balance Sheet NWC (Base)'!R11 -> 1610837.3
D79: Current Liabilities | E79: ='Balance Sheet NWC (Base)'!J24 -> 599585.82 | F79: ='Balance Sheet NWC (Base)'!K24 -> 599585.82 | G79: ='Balance Sheet NWC (Base)'!L24 -> 589166.5 | H79: ='Balance Sheet NWC (Base)'!M24 -> 607083.01 | I79: ='Balance Sheet NWC (Base)'!N24 -> 636566.62 | J79: ='Balance Sheet NWC (Base)'!O24 -> 647934.44 | K79: ='Balance Sheet NWC (Base)'!P24 -> 670389.16 | L79: ='Balance Sheet NWC (Base)'!Q24 -> 688430.39 | M79: ='Balance Sheet NWC (Base)'!R24 -> 710279.11
D80: Current Ratio | E80: =E78/E79 -> 2.1056234 | F80: =F78/F79 -> 2.1056234 | G80: =G78/G79 -> 2.0872094 | H80: =H78/H79 -> 2.1184821 | I80: =I78/I79 -> 2.1661126 | J80: =J78/J79 -> 2.1833194 | K80: =K78/K79 -> 2.215593 | L80: =L78/L79 -> 2.2399978 | M80: =M78/M79 -> 2.2678933
D82: Current Assets | E82: =E78 -> 1262501.9 | F82: =F78 -> 1262501.9 | G82: =G78 -> 1229713.9 | H82: =H78 -> 1286094.5 | I82: =I78 -> 1378875 | J82: =J78 -> 1414647.8 | K82: =K78 -> 1485309.5 | L82: =L78 -> 1542082.6 | M82: =M78 -> 1610837.3
D83: Inventory & Other | E83: =-'Balance Sheet NWC (Base)'!J9-'Balance Sheet NWC (Base)'!J10 -> -799801.25 | F83: =-'Balance Sheet NWC (Base)'!K9-'Balance Sheet NWC (Base)'!K10 -> -799801.25 | G83: =-'Balance Sheet NWC (Base)'!L9-'Balance Sheet NWC (Base)'!L10 -> -778610.22 | H83: =-'Balance Sheet NWC (Base)'!M9-'Balance Sheet NWC (Base)'!M10 -> -815049.18 | I83: =-'Balance Sheet NWC (Base)'!N9-'Balance Sheet NWC (Base)'!N10 -> -875013.53 | J83: =-'Balance Sheet NWC (Base)'!O9-'Balance Sheet NWC (Base)'!O10 -> -898133.62 | K83: =-'Balance Sheet NWC (Base)'!P9-'Balance Sheet NWC (Base)'!P10 -> -943802.48 | L83: =-'Balance Sheet NWC (Base)'!Q9-'Balance Sheet NWC (Base)'!Q10 -> -980495.08 | M83: =-'Balance Sheet NWC (Base)'!R9-'Balance Sheet NWC (Base)'!R10 -> -1024931.4
D84: Net Current Assets | E84: =E82+E83 -> 462700.67 | F84: =F82+F83 -> 462700.67 | G84: =G82+G83 -> 451103.63 | H84: =H82+H83 -> 471045.28 | I84: =I82+I83 -> 503861.48 | J84: =J82+J83 -> 516514.22 | K84: =K82+K83 -> 541507.05 | L84: =L82+L83 -> 561587.5 | M84: =M82+M83 -> 585905.83
D85: Current Liabilities | E85: =E79 -> 599585.82 | F85: =F79 -> 599585.82 | G85: =G79 -> 589166.5 | H85: =H79 -> 607083.01 | I85: =I79 -> 636566.62 | J85: =J79 -> 647934.44 | K85: =K79 -> 670389.16 | L85: =L79 -> 688430.39 | M85: =M79 -> 710279.11
D86: Quick Ratio | E86: =E84/E85 -> 0.77170049 | F86: =F84/F85 -> 0.77170049 | G86: =G84/G85 -> 0.7656641 | H86: =H84/H85 -> 0.77591577 | I86: =I84/I85 -> 0.79152985 | J86: =J84/J85 -> 0.7971705 | K86: =K84/K85 -> 0.8077503 | L86: =L84/L85 -> 0.8157506 | M86: =M84/M85 -> 0.8248952

Sheet 3-Statement (Base)
C1: ACTUALS | D1: ACTUALS | E1: ACTUALS | F1: ACTUALS | G1: ACTUALS | H1: ACTUALS | I1: ACTUALS | J1: FORECAST | K1: FORECAST | L1: FORECAST | M1: FORECAST | N1: FORECAST | O1: FORECAST | P1: FORECAST | Q1: FORECAST | R1: FORECAST
B2: Drivers: | C2: 44196 | D2: =EOMONTH(C2,12) -> 44561 | E2: =EOMONTH(D2,12) -> 44926 | F2: =EOMONTH(E2,12) -> 45291 | G2: Q1-24 | H2: Q2-24 | I2: Q3-24 | J2: Q4-24 | K2: =EOMONTH(F2,12) -> 45657 | L2: =EOMONTH(K2,12) -> 46022 | M2: =EOMONTH(L2,12) -> 46387 | N2: =EOMONTH(M2,12) -> 46752 | O2: =EOMONTH(N2,12) -> 47118 | P2: =EOMONTH(O2,12) -> 47483 | Q2: =EOMONTH(P2,12) -> 47848 | R2: =EOMONTH(Q2,12) -> 48213
B4: Market Size:
B5: Growth Rate:
B7: Market Share %:
B9: Revenue | C9: =C43 -> 3192399 | D9: =D43 -> 3243224 | E9: =E43 -> 3691893 | F9: =F43 -> 4009282 | G9: =G43 -> 953969 | H9: =H43 -> 935348 | I9: =I43 -> 979350 | J9: =K9-I9-H9-G9 -> 952178.75 | K9: =F9*(1+K10) -> 3820845.7 | L9: =K9*(1+L10) -> 3800977.3 | M9: =L9*(1+M10) -> 3978863.1 | N9: =M9*(1+N10) -> 4240672.3 | O9: =N9*(1+O10) -> 4373829.4 | P9: =O9*(1+P10) -> 4592520.9 | Q9: =P9*(1+Q10) -> 4765934.4 | R9: =Q9*(1+R10) -> 4986845
B10: Growth Rate: | D10: =D9/C9-1 -> 0.015920629 | E10: =E9/D9-1 -> 0.13834043 | F10: =F9/E9-1 -> 0.085969176 | H10: =H9/G9-1 -> -0.019519502 | I10: =I9/H9-1 -> 0.047043453 | J10: =J9/I9-1 -> -0.027744171 | K10: -0.047 | L10: -0.0052 | M10: 0.0468 | N10: 0.0658 | O10: 0.0314 | P10: 0.05 | Q10: =AVERAGE(L10:P10) -> 0.03776 | R10: =AVERAGE(M10:Q10) -> 0.046352
B12: COGS % Revenue: | C12: =-C46/C43 -> 0.57921237 | D12: =-D46/D43 -> 0.58883044 | E12: =-E46/E43 -> 0.5779271 | F12: =-F46/F43 -> 0.59020967 | G12: =-G46/G43 -> 0.58791428 | H12: =-H46/H43 -> 0.5845279 | I12: =-I46/I43 -> 0.59110941 | J12: =AVERAGE(G12:I12) -> 0.58785053 | K12: =-K46/K43 -> 0.58788837 | L12: =AVERAGE(C12:F12,K12) -> 0.58481359 | M12: =AVERAGE(K12:L12,D12:F12) -> 0.58593383 | N12: =AVERAGE(K12:M12,E12:F12) -> 0.58535451 | O12: =AVERAGE(K12:N12,F12) -> 0.58683999 | P12: =AVERAGE(K12:O12) -> 0.58616606 | Q12: =AVERAGE(L12:P12) -> 0.5858216 | R12: =AVERAGE(M12:Q12) -> 0.5860232
B13: OpEx % Revenue: | C13: =-C47/C44 -> 0.30558618 | D13: =-D47/D44 -> 0.30662945 | E13: =-E47/E44 -> 0.29357893 | F13: =-F47/F44 -> 0.2871574 | G13: =-G47/G44 -> 0.30465665 | H13: =-H47/H44 -> 0.3113654 | I13: =-I47/I44 -> 0.29508449 | J13: =AVERAGE(G13:I13) -> 0.30370218 | K13: =-K47/K44 -> 0.30360759 | L13: =AVERAGE(C13:F13,K13) -> 0.29931191 | M13: =AVERAGE(K13:L13,D13:F13) -> 0.29805706 | N13: =AVERAGE(K13:M13,E13:F13) -> 0.29634258 | O13: =AVERAGE(K13:N13,F13) -> 0.29689531 | P13: =AVERAGE(K13:O13) -> 0.29884289 | Q13: =AVERAGE(L13:P13) -> 0.29788995 | R13: =AVERAGE(M13:Q13) -> 0.29760556
B14: Impairment % Revenue: | C14: =-C48/C43 -> 0 | D14: =-D48/D43 -> 0.0018148608 | E14: =-E48/E43 -> 0 | F14: =-F48/F43 -> 0 | G14: =-G48/G43 -> 0 | H14: =-H48/H43 -> 0 | I14: =-I48/I43 -> 0 | J14: =AVERAGE(G14:I14) -> 0 | K14: =-K48/K43 -> 0 | L14: =AVERAGE(C14:F14,K14) -> 0.00036297215 | M14: =AVERAGE(K14:L14,D14:F14) -> 0.00043556658 | N14: =AVERAGE(K14:M14,E14:F14) -> 0.00015970775 | O14: =AVERAGE(K14:N14,F14) -> 0.0001916493 | P14: =AVERAGE(K14:O14) -> 0.00022997916 | Q14: =AVERAGE(L14:P14) -> 0.00027597499 | R14: =AVERAGE(M14:Q14) -> 0.00025857555
B15: Restructuring % of Revenue: | C15: =C49/C46 -> 0.0092094596 | D15: =D49/D46 -> 0.016438107 | E15: =E49/E46 -> 0.0074075116 | F15: =F49/F46 -> 0.0033541575 | G15: =G49/G46 -> 0.0016332294 | H15: =H49/H46 -> 0.011305253 | I15: =I49/I46 -> 0.00810153 | J15: =AVERAGE(G15:I15) -> 0.0070133374 | K15: =K49/K46 -> 0.0082204157 | L15: =AVERAGE(C15:F15,K15) -> 0.0089259302 | M15: =AVERAGE(K15:L15,D15:F15) -> 0.0088692243 | N15: =AVERAGE(K15:M15,E15:F15) -> 0.0073554479 | O15: =AVERAGE(K15:N15,F15) -> 0.0073450351 | P15: =AVERAGE(K15:O15) -> 0.0081432106 | Q15: =AVERAGE(L15:P15) -> 0.0081277696 | R15: =AVERAGE(M15:Q15) -> 0.0079681375
B16: Gain on Sale % Revenue: | C16: =-C50/C43 -> 0 | D16: =-D50/D43 -> 0 | E16: =-E50/E43 -> -0.0027443916 | F16: =-F50/F43 -> 0 | G16: =-G50/G43 -> 0 | H16: =-H50/H43 -> 0 | I16: =-I50/I43 -> 0 | J16: =AVERAGE(G16:I16) -> 0 | K16: =-K50/K43 -> 0 | L16: =AVERAGE(C16:F16,K16) -> -0.00054887831 | M16: =AVERAGE(K16:L16,D16:F16) -> -0.00065865398 | N16: =AVERAGE(K16:M16,E16:F16) -> -0.00079038477 | O16: =AVERAGE(K16:N16,F16) -> -0.00039958341 | P16: =AVERAGE(K16:O16) -> -0.00047950009 | Q16: =AVERAGE(L16:P16) -> -0.00057540011 | R16: =AVERAGE(M16:Q16) -> -0.00058070447
B17: Other Income % Revenue: | C17: =C54/C43 -> -0.0051184078 | D17: =D54/D43 -> -0.0044535931 | E17: =E54/E43 -> -0.0047263017 | F17: =F54/F43 -> -0.005364801 | G17: =G54/G43 -> -0.0054456696 | H17: =H54/H43 -> -0.0073854865 | I17: =I54/I43 -> -0.0068923265 | J17: =AVERAGE(G17:I17) -> -0.0065744942 | K17: =K54/K43 -> -0.0065726531 | L17: =AVERAGE(C17:F17,K17) -> -0.0052471513 | M17: =AVERAGE(K17:L17,D17:F17) -> -0.0052729 | N17: =AVERAGE(K17:M17,E17:F17) -> -0.0054367614 | O17: =AVERAGE(K17:N17,F17) -> -0.0055788534 | P17: =AVERAGE(K17:O17) -> -0.0056216639 | Q17: =AVERAGE(L17:P17) -> -0.005431466 | R17: =AVERAGE(M17:Q17) -> -0.0054683289
B18: Tax Rate: | C18: =-C58/C56 -> 0.24679731 | D18: =-D58/D56 -> 0.24426883 | E18: =-E58/E56 -> 0.24527189 | F18: =-F58/F56 -> 0.24782969 | G18: =-G58/G56 -> 0.242997 | H18: =-H58/H56 -> 0.23000438 | I18: =-I58/I56 -> 0.25199295 | J18: =AVERAGE(G18:I18) -> 0.24166478 | K18: =-K58/K56 -> 0.24215879 | L18: =AVERAGE(C18:F18,K18) -> 0.2452653 | M18: =AVERAGE(K18:L18,D18:F18) -> 0.2449589 | N18: =AVERAGE(K18:M18,E18:F18) -> 0.24509691 | O18: =AVERAGE(K18:N18,F18) -> 0.24506192 | P18: =AVERAGE(K18:O18) -> 0.24450837 | Q18: =AVERAGE(L18:P18) -> 0.24497828 | R18: =AVERAGE(M18:Q18) -> 0.24492088
B19: NCI Net Income % Total: | C19: =C61/C60 -> 0.0025460959 | D19: =D61/D60 -> 0.0047261365 | E19: =E61/E60 -> 0.0020441609 | F19: =F61/F60 -> -0.00036723238 | G19: =G61/G60 -> -0.0032114339 | H19: =H61/H60 -> -0.0045805246 | I19: =I61/I60 -> -0.0055109939 | J19: =AVERAGE(G19:I19) -> -0.0044343175 | K19: =K61/K60 -> -0.0025060834 | L19: =AVERAGE(C19:F19,K19) -> 0.0012886155 | M19: =AVERAGE(K19:L19,D19:F19) -> 0.0010371194 | N19: =AVERAGE(K19:M19,E19:F19) -> 0.000299316 | O19: =AVERAGE(K19:N19,F19) -> -4.9652985e-05 | P19: =AVERAGE(K19:O19) -> 1.3862893e-05 | Q19: =AVERAGE(L19:P19) -> 0.00051785216 | R19: =AVERAGE(M19:Q19) -> 0.0003636995
B21: NWC % Revenue: | C21: =C69/C44 -> 0.25876277 | D21: =D69/D44 -> 0.28188432 | E21: =E69/E44 -> 0.29790192 | F21: =F69/F44 -> 0.21149922 | G21: =G69/G44/4 -> 0.22572825 | H21: =H69/H44/4 -> 0.23255649 | I21: =I69/I44/4 -> 0.20670419 | J21: =AVERAGE(G21:I21) -> 0.22166298 | K21: =K69/K44 -> 0.22095922 | L21: =AVERAGE(F21,K21) -> 0.21622922 | M21: =AVERAGE(K21,L21,F21) -> 0.21622922 | N21: =AVERAGE(L21,M21,K21) -> 0.21780589 | O21: =AVERAGE(M21,N21,L21) -> 0.21675477 | P21: =AVERAGE(N21,O21,M21) -> 0.21692996 | Q21: =AVERAGE(O21,P21,N21) -> 0.21716354 | R21: =AVERAGE(P21,Q21,O21) -> 0.21694942
B22: CapEx % Revenue: | C22: =-C101/C44 -> 0.014719651 | D22: =-D101/D44 -> 0.016571782 | E22: =-E101/E44 -> 0.016623721 | F22: =-F101/F44 -> 0.023069717 | G22: =-G101/G44 -> 0.019322431 | H22: =-H101/H44 -> 0.027102212 | I22: =-I101/I44 -> 0.030194517 | J22: =AVERAGE(G22:I22) -> 0.02553972 | K22: =-K101/K44 -> 0.025563026 | L22: =AVERAGE(C22:F22,K22) -> 0.019309579 | M22: =AVERAGE(K22:L22,D22:F22) -> 0.020227565 | N22: =AVERAGE(K22:M22,E22:F22) -> 0.020958722 | O22: =AVERAGE(K22:N22,F22) -> 0.021825722 | P22: =AVERAGE(K22:O22) -> 0.021576923 | Q22: =AVERAGE(L22:P22) -> 0.020779702 | R22: =AVERAGE(M22:Q22) -> 0.021073727
B23: D&A % Revenue: | C23: =C94/C44 -> 0.021638586 | D23: =D94/D44 -> 0.021227643 | E23: =E94/E44 -> 0.019062308 | F23: =F94/F44 -> 0.018738767 | G23: =G94/G44 -> 0.020736523 | H23: =H94/H44 -> 0.022764789 | I23: =I94/I44 -> 0.021085414 | J23: =AVERAGE(G23:I23) -> 0.021528909 | K23: =K94/K44 -> 0.021519939 | L23: =AVERAGE(C23:F23,K23) -> 0.020437448 | M23: =AVERAGE(K23:L23,D23:F23) -> 0.020197221 | N23: =AVERAGE(K23:M23,E23:F23) -> 0.019991137 | O23: =AVERAGE(K23:N23,F23) -> 0.020176902 | P23: =AVERAGE(K23:O23) -> 0.02046453 | Q23: =AVERAGE(L23:P23) -> 0.020253448 | R23: =AVERAGE(M23:Q23) -> 0.020216647
B24: Other Items % Revenue: | C24: =C97/C44 -> 0.011421191 | D24: =D97/D44 -> 0.0039633402 | E24: =E97/E44 -> 0.0080557589 | F24: =F97/F44 -> 0.0090470064 | G24: =G97/G44 -> 0.005879646 | H24: =H97/H44 -> 0.0010830194 | I24: =I97/I44 -> -0.005415837 | J24: =AVERAGE(G24:I24) -> 0.00051560944 | K24: =K97/K44 -> 0.00047344292 | L24: =AVERAGE(C24:F24,K24) -> 0.006592148 | M24: =AVERAGE(K24:L24,D24:F24) -> 0.0056263393 | N24: =AVERAGE(K24:M24,E24:F24) -> 0.0059589391 | O24: =AVERAGE(K24:N24,F24) -> 0.0055395751 | P24: =AVERAGE(K24:O24) -> 0.0048380889 | Q24: =AVERAGE(L24:P24) -> 0.0057110181 | R24: =AVERAGE(M24:Q24) -> 0.0055347921
B25: Acquisitions & Other % Revenue: | C25: =-C102/C43 -> 0.0007160759 | D25: =-D102/D43 -> 0.0067833736 | E25: =-E102/E43 -> 0.0089710076 | F25: =-F102/F43 -> 0.005033819 | G25: =-G102/G43 -> 0 | H25: =-H102/H43 -> 0.010550084 | I25: =-I102/I43 -> -9.1897687e-06 | J25: =AVERAGE(G25:I25) -> 0.0035136314 | K25: =-K102/K43 -> 0.0034559378 | L25: =AVERAGE(C25:F25,K25) -> 0.0049920428 | M25: =AVERAGE(K25:L25,D25:F25) -> 0.0058472361 | N25: =AVERAGE(K25:M25,E25:F25) -> 0.0056600087 | O25: =AVERAGE(K25:N25,F25) -> 0.0049978089 | P25: =AVERAGE(K25:O25) -> 0.0049906068 | Q25: =AVERAGE(L25:P25) -> 0.0052975407 | R25: =AVERAGE(M25:Q25) -> 0.0053586402
B27: Dividends % Net Income: | C27: =-C108/C62 -> 0.66318489 | D27: =-D108/D62 -> 0.77129369 | E27: =-E108/E62 -> 0.4925924 | F27: =-F108/F62 -> 0.51485434 | G27: =-G108/G62 -> 0.68049027 | H27: =-H108/H62 -> 0.75625333 | I27: =-I108/I62 -> 0.65171188 | J27: =AVERAGE(G27:I27) -> 0.69615183 | K27: =-K108/K62 -> 0.6940755 | L27: =AVERAGE(C27:F27,K27) -> 0.62720016 | M27: =AVERAGE(K27:L27,D27:F27) -> 0.62000322 | N27: =AVERAGE(K27:M27,E27:F27) -> 0.58974512 | O27: =AVERAGE(K27:N27,F27) -> 0.60917567 | P27: =AVERAGE(K27:O27) -> 0.62803993 | Q27: =AVERAGE(L27:P27) -> 0.61483282 | R27: =AVERAGE(M27:Q27) -> 0.61235935
B28: Stock Repurchases % Net Income: | C28: =-C109/C62 -> 0.013714723 | D28: =-D109/D62 -> 0.3285325 | E28: =-E109/E62 -> 0.080518326 | F28: =-F109/F62 -> 0.27904951 | G28: =-G109/G62 -> 1.9040375 | H28: =-H109/H62 -> 0.26892169 | I28: =-I109/I62 -> 0.25784813 | J28: 0 | K28: =-K109/K62 -> 0.6247163 | L28: 0.45 | M28: 0.3 | N28: 0.25 | O28: 0.35 | P28: 0.25 | Q28: 0.3 | R28: 0.3 | S28: Set to maintain capital structure
B29: Other Items % Debt Issuances: | C29: =C111/(C107+C106) -> 0.10910804 | D29: =D111/(D107+D106) -> 0.20243173 | E29: =E111/(E107+E106) -> 5.6242536 | F29: =F111/(F107+F106) -> -0.10019784 | G29: =G111/(G107+G106) -> 0.087705615 | H29: =H111/(H107+H106) -> 0.14705469 | I29: =I111/(I107+I106) -> -0.00048888889 | J29: =AVERAGE(G29:I29) -> 0.078090472 | K29: =K111/(K107+K106) -> 0.12855637 | L29: =K29 -> 0.12855637 | M29: =L29 -> 0.12855637 | N29: =M29 -> 0.12855637 | O29: =N29 -> 0.12855637 | P29: =O29 -> 0.12855637 | Q29: =P29 -> 0.12855637 | R29: =Q29 -> 0.12855637
B31: Total Cash Flow Before Revolver | J31: =I68+J98+J103+SUM(J107:J111)+J114 -> 4127.5042 | K31: =J68+K98+K103+SUM(K107:K111)+K114 -> -61924.496 | L31: =K68+L98+L103+SUM(L107:L111)+L114 -> 35655.546 | M31: =L68+M98+M103+SUM(M107:M111)+M114 -> 8326.2324 | N31: =M68+N98+N103+SUM(N107:N111)+N114 -> 10124.675 | O31: =N68+O98+O103+SUM(O107:O111)+O114 -> 8624.2992 | P31: =O68+P98+P103+SUM(P107:P111)+P114 -> 11600.945 | Q31: =P68+Q98+Q103+SUM(Q107:Q111)+Q114 -> 15748.062 | R31: =Q68+R98+R103+SUM(R107:R111)+R114 -> 7303.2909
B32: Revolver Borrowing to Zero | J32: =-MIN(J31,I76) -> -4127.5042 | K32: =-MIN(K31,J76) -> 61924.496 | L32: =-MIN(L31,K76) -> -35655.546 | M32: =-MIN(M31,L76) -> -8326.2324 | N32: =-MIN(N31,M76) -> -10124.675 | O32: =-MIN(O31,N76) -> -8624.2992 | P32: =-MIN(P31,O76) -> -11600.945 | Q32: =-MIN(Q31,P76) -> -15748.062 | R32: =-MIN(R31,Q76) -> -7303.2909
B33: Estimated Minimum Cash Balance | J33: 25000 | K33: 25000 | L33: 25000 | M33: 25000 | N33: 25000 | O33: 25000 | P33: 25000 | Q33: 25000 | R33: 25000 | S33: Estimate based on historicals
B34: Total Revolver Borrowing Needed | J34: =SUM(J32:J33) -> 20872.496 | K34: =SUM(K32:K33) -> 86924.496 | L34: =SUM(L32:L33) -> -10655.546 | M34: =SUM(M32:M33) -> 16673.768 | N34: =SUM(N32:N33) -> 14875.325 | O34: =SUM(O32:O33) -> 16375.701 | P34: =SUM(P32:P33) -> 13399.055 | Q34: =SUM(Q32:Q33) -> 9251.9376 | R34: =SUM(R32:R33) -> 17696.709
B36: Revolver Maximum Balance | I36: 600000 | J36: 600000 | K36: 600000 | L36: 600000 | M36: 600000 | N36: 600000 | O36: 600000 | P36: 600000 | Q36: 600000 | R36: 600000
B37: Revolver Utilization | I37: =I76 -> 81300 | J37: =J76 -> 102172.5 | K37: =K76 -> 102172.5 | L37: =L76 -> 91516.95 | M37: =M76 -> 108190.72 | N37: =N76 -> 123066.04 | O37: =O76 -> 139441.74 | P37: =P76 -> 152840.8 | ... R37: =R76 -> 179789.44
B38: Net Revolver Balance | I38: =I36-I37 -> 518700 | J38: =J36-J37 -> 497827.5 | K38: =K36-K37 -> 497827.5 | L38: =L36-L37 -> 508483.05 | M38: =M36-M37 -> 491809.28 | N38: =N36-N37 -> 476933.96 | O38: =O36-O37 -> 460558.26 | P38: =P36-P37 -> 447159.2 | ... R38: =R36-R37 -> 420210.56
B39: 50 Bps on Unutilized Revolver | I39: =I38*0.005 -> 2593.5 | J39: =J38*0.005 -> 2489.1375 | K39: =K38*0.005 -> 2489.1375 | L39: =L38*0.005 -> 2542.4153 | M39: =M38*0.005 -> 2459.0464 | N39: =N38*0.005 -> 2384.6698 | O39: =O38*0.005 -> 2302.7913 | P39: =P38*0.005 -> 2235.796 | ... R39: =R38*0.005 -> 2101.0528
B41: Income Statement: | C41: =C$2 -> 44196 | D41: =D$2 -> 44561 | E41: =E$2 -> 44926 | F41: =F$2 -> 45291 | G41: =G$2 -> Q1-24 | H41: =H$2 -> Q2-24 | I41: =I$2 -> Q3-24 | J41: =J$2 -> Q4-24 | ... R41: =R$2 -> 48213
B43: Revenue: | C43: ='Income Statement'!C6 -> 3192399 | D43: ='Income Statement'!D6 -> 3243224 | E43: ='Income Statement'!E6 -> 3691893 | F43: ='Income Statement'!F6 -> 4009282 | G43: ='Income Statement'!G6 -> 953969 | H43: ='Income Statement'!H6 -> 935348 | I43: ='Income Statement'!I6 -> 979350 | J43: =J9 -> 952178.75 | K43: =SUM(G43:J43) -> 3820845.7 | L43: =L9 -> 3800977.3 | M43: =M9 -> 3978863.1 | N43: =N9 -> 4240672.3 | O43: =O9 -> 4373829.4 | P43: =P9 -> 4592520.9 | Q43: =Q9 -> 4765934.4 | R43: =R9 -> 4986845
B44: Total Revenue: | C44: =SUM(C43:C43) -> 3192399 | D44: =SUM(D43:D43) -> 3243224 | E44: =SUM(E43:E43) -> 3691893 | F44: =SUM(F43:F43) -> 4009282 | G44: =SUM(G43:G43) -> 953969 | H44: =SUM(H43:H43) -> 935348 | I44: =SUM(I43:I43) -> 979350 | J44: =SUM(J43:J43) -> 952178.75 | ... R44: =SUM(R43:R43) -> 4986845
B46: Cost of Sales: | C46: =-'Income Statement'!C7 -> -1849077 | D46: =-'Income Statement'!D7 -> -1909709 | E46: =-'Income Statement'!E7 -> -2133645 | F46: =-'Income Statement'!F7 -> -2366317 | G46: =-'Income Statement'!G7 -> -560852 | H46: =-'Income Statement'!H7 -> -546737 | I46: =-'Income Statement'!I7 -> -578903 | J46: =-J$43*J12 -> -559738.78 | K46: =SUM(G46:J46) -> -2246230.8 | L46: =-L$43*L12 -> -2222863.2 | M46: =-M$43*M12 -> -2331350.5 | N46: =-N$43*N12 -> -2482296.6 | O46: =-O$43*O12 -> -2566738 | P46: =-P$43*P12 -> -2691979.9 | Q46: =-Q$43*Q12 -> -2791987.3 | R46: =-R$43*R12 -> -2922406.9
B47: Operating Expenses: | C47: =-'Income Statement'!C11 -> -975553 | D47: =-'Income Statement'!D11 -> -994468 | E47: =-'Income Statement'!E11 -> -1083862 | F47: =-'Income Statement'!F11 -> -1151295 | G47: =-'Income Statement'!G11 -> -290633 | H47: =-'Income Statement'!H11 -> -291235 | I47: =-'Income Statement'!I11 -> -288991 | J47: =-J$43*J13 -> -289178.76 | K47: =SUM(G47:J47) -> -1160037.8 | L47: =-L$43*L13 -> -1137677.8 | M47: =-M$43*M13 -> -1185928.2 | N47: =-N$43*N13 -> -1256691.8 | O47: =-O$43*O13 -> -1298569.4 | P47: =-P$43*P13 -> -1372442.2 | Q47: =-Q$43*Q13 -> -1419724 | R47: =-R$43*R13 -> -1484112.8
B48: Impairment Loss: | C48: =-'Income Statement'!C12 -> 0 | D48: =-'Income Statement'!D12 -> -5886 | E48: =-'Income Statement'!E12 -> 0 | F48: =-'Income Statement'!F12 -> 0 | G48: =-'Income Statement'!G12 -> 0 | H48: =-'Income Statement'!H12 -> 0 | I48: =-'Income Statement'!I12 -> 0 | J48: =-J$43*J14 -> 0 | K48: =SUM(G48:J48) -> 0 | L48: =K48 -> 0 | M48: =L48 -> 0 | N48: =M48 -> 0 | O48: =N48 -> 0 | P48: =O48 -> 0 | Q48: =P48 -> 0 | R48: =Q48 -> 0
B49: Restructuring Costs: | C49: =-'Income Statement'!C13 -> -17029 | D49: =-'Income Statement'!D13 -> -31392 | E49: =-'Income Statement'!E13 -> -15805 | F49: =-'Income Statement'!F13 -> -7937 | G49: =-'Income Statement'!G13 -> -916 | H49: =-'Income Statement'!H13 -> -6181 | I49: =-'Income Statement'!I13 -> -4690 | J49: =-J$43*J15 -> -6677.9508 | K49: =SUM(G49:J49) -> -18464.951 | L49: =-L$43*L15 -> -33927.258 | M49: =-M$43*M15 -> -35289.429 | N49: =-N$43*N15 -> -31192.044 | O49: =-O$43*O15 -> -32125.93 | P49: =-P$43*P15 -> -37397.865 | Q49: =-Q$43*Q15 -> -38736.417 | R49: =-R$43*R15 -> -39735.867
B50: Gain on Sale of Property: | C50: =-'Income Statement'!C14 -> 0 | D50: =-'Income Statement'!D14 -> 0 | E50: =-'Income Statement'!E14 -> 10132 | F50: =-'Income Statement'!F14 -> 0 | G50: =-'Income Statement'!G14 -> 0 | H50: =-'Income Statement'!H14 -> 0 | I50: =-'Income Statement'!I14 -> 0 | J50: =-J$43*J16 -> 0 | K50: =SUM(G50:J50) -> 0 | L50: =K50 -> 0 | M50: =L50 -> 0 | N50: =M50 -> 0 | O50: =N50 -> 0 | P50: =O50 -> 0 | Q50: =P50 -> 0 | R50: =Q50 -> 0
B51: Operating Income: | C51: =C44+SUM(C46:C50) -> 350740 | D51: =D44+SUM(D46:D50) -> 301769 | E51: =E44+SUM(E46:E50) -> 468713 | F51: =F44+SUM(F46:F50) -> 483733 | G51: =G44+SUM(G46:G50) -> 101568 | H51: =H44+SUM(H46:H50) -> 91195 | I51: =I44+SUM(I46:I50) -> 106766 | J51: =J44+SUM(J46:J50) -> 96583.254 | ... R51: =R44+SUM(R46:R50) -> 540589.51
B52: Margin Percentage | C52: =(SUM(C44:C46)/C44) -> 0.42078763 | D52: =(SUM(D44:D46)/D44) -> 0.41116956 | E52: =(SUM(E44:E46)/E44) -> 0.4220729 | F52: =(SUM(F44:F46)/F44) -> 0.40979033 | G52: =(SUM(G44:G46)/G44) -> 0.41208572 | H52: =(SUM(H44:H46)/H44) -> 0.4154721 | I52: =(SUM(I44:I46)/I44) -> 0.40889059 | J52: =(SUM(J44:J46)/J44) -> 0.41214947 | ... R52: =(SUM(R44:R46)/R44) -> 0.4139768
B54: Other Income / (Expense): | C54: ='Income Statement'!C19+'Income Statement'!C20 -> -16340 | D54: ='Income Statement'!D19+'Income Statement'!D20 -> -14444 | E54: ='Income Statement'!E19+'Income Statement'!E20 -> -17449 | F54: ='Income Statement'!F19+'Income Statement'!F20 -> -21509 | G54: ='Income Statement'!G19+'Income Statement'!G20 -> -5195 | H54: ='Income Statement'!H19+'Income Statement'!H20 -> -6908 | I54: ='Income Statement'!I19+'Income Statement'!I20 -> -6750 | J54: =J$43*J17 -> -6260.0937 | K54: =SUM(G54:J54) -> -25113.094 | L54: =L$43*L17 -> -19944.303 | M54: =M$43*M17 -> -20980.147 | N54: =N$43*N17 -> -23055.523 | O54: =O$43*O17 -> -24400.953 | P54: =P$43*P17 -> -25817.608 | Q54: =Q$43*Q17 -> -25886.011 | R54: =R$43*R17 -> -27269.709
B55: Interest Income / (Expense): | C55: ='Income Statement'!C21 -> -150 | D55: ='Income Statement'!D21 -> 1054 | E55: ='Income Statement'!E21 -> -132 | F55: ='Income Statement'!F21 -> -6068 | G55: ='Income Statement'!G21 -> -5055 | H55: ='Income Statement'!H21 -> -4332 | I55: ='Income Statement'!I21 -> -4680 | J55: =-SOFR!$C$29*I78/4-I39/4 -> -4723.6238 | K55: =SUM(G55:J55) -> -18790.624 | L55: =-SOFR!$C$29*K78-K39 -> -18749.482 | M55: =-SOFR!$C$29*L78-L39 -> -18641.766 | N55: =-SOFR!$C$29*M78-M39 -> -18398.998 | O55: =-SOFR!$C$29*N78-N39 -> -18166.8 | P55: =-SOFR!$C$29*O78-O39 -> -17928.663 | Q55: =-SOFR!$C$29*P78-P39 -> -17706.956 | R55: =-SOFR!$C$29*Q78-Q39 -> -17507.516 | S55: SOFR + 3% on Long-Term Debt, 50 bps on unutilized Revolver
B56: Pre-Tax Income: | C56: =C51+SUM(C54:C55) -> 334250 | D56: =D51+SUM(D54:D55) -> 288379 | E56: =E51+SUM(E54:E55) -> 451132 | F56: =F51+SUM(F54:F55) -> 456156 | G56: =G51+SUM(G54:G55) -> 91318 | H56: =H51+SUM(H54:H55) -> 79955 | I56: =I51+SUM(I54:I55) -> 95336 | J56: =J51+SUM(J54:J55) -> 85599.536 | ... R56: =R51+SUM(R54:R55) -> 495812.28
B58: Income Taxes: | C58: =-'Income Statement'!C24 -> -82492 | D58: =-'Income Statement'!D24 -> -70442 | E58: =-'Income Statement'!E24 -> -110650 | F58: =-'Income Statement'!F24 -> -113049 | G58: =-'Income Statement'!G24 -> -22190 | H58: =-'Income Statement'!H24 -> -18390 | I58: =-'Income Statement'!I24 -> -24024 | J58: =-J56*J18 -> -20686.393 | K58: =SUM(G58:J58) -> -85290.393 | L58: =-L56*L18 -> -90212.334 | M58: =-M56*M18 -> -94719 | N58: =-N56*N18 -> -105155.72 | O58: =-O56*O18 -> -106314.79 | P58: =-P56*P18 -> -109284.16 | Q58: =-Q56*Q18 -> -115603.72 | R58: =-R56*R18 -> -121434.78
B60: Net Income: | C60: =C56+C58 -> 251758 | D60: =D56+D58 -> 217937 | E60: =E56+E58 -> 340482 | F60: =F56+F58 -> 343107 | G60: =G56+G58 -> 69128 | H60: =H56+H58 -> 61565 | I60: =I56+I58 -> 71312 | J60: =J56+J58 -> 64913.144 | ... R60: =R56+R58 -> 374377.5
B61: (-) NCI Net Income: | C61: 641 | D61: 1030 | E61: 696 | F61: -126 | G61: -222 | H61: -282 | I61: -393 | J61: =J25*J60 -> 228.08086 | K61: =SUM(G61:J61) -> -668.91914 | L61: =L25*L60 -> 1385.8059 | M61: =M25*M60 -> 1707.1242 | N61: =N25*N60 -> 1833.1726 | O61: =O25*O60 -> 1636.8498 | P61: =P25*P60 -> 1685.1808 | Q61: =Q25*Q60 -> 1887.461 | R61: =R25*R60 -> 2006.1543
B62: Net Income to Parent: | C62: =C60-C61 -> 251117 | D62: =D60-D61 -> 216907 | E62: =E60-E61 -> 339786 | F62: =F60-F61 -> 343233 | G62: =G60-G61 -> 69350 | H62: =H60-H61 -> 61847 | I62: =I60-I61 -> 71705 | J62: =J60-J61 -> 64685.063 | ... R62: =R60-R61 -> 372371.35
B63: Profit Margin | C63: =C62/C44 -> 0.078660907 | D63: =D62/D44 -> 0.066880055 | E63: =E62/E44 -> 0.092035712 | F63: =F62/F44 -> 0.085609593 | G63: =G62/G44 -> 0.072696283 | H63: =H62/H44 -> 0.066121914 | I63: =I62/I44 -> 0.07321693 | J63: =J62/J44 -> 0.067933739 | ... R63: =R62/R44 -> 0.074670728
B65: Balance Sheet: | C65: =C$2 -> 44196 | D65: =D$2 -> 44561 | E65: =E$2 -> 44926 | F65: =F$2 -> 45291 | G65: =G$2 -> Q1-24 | H65: =H$2 -> Q2-24 | I65: =I$2 -> Q3-24 | J65: =J$2 -> Q4-24 | ... R65: =R$2 -> 48213
B67: ASSETS:
B68: Cash: | C68: ='Balance Sheet NWC (Base)'!C7 -> 125211 | D68: ='Balance Sheet NWC (Base)'!D7 -> 40536 | E68: ='Balance Sheet NWC (Base)'!E7 -> 43537 | F68: ='Balance Sheet NWC (Base)'!F7 -> 50052 | G68: ='Balance Sheet NWC (Base)'!G7 -> 25805 | H68: ='Balance Sheet NWC (Base)'!H7 -> 22227 | I68: ='Balance Sheet NWC (Base)'!I7 -> 25928 | J68: =I68+J116 -> 25000 | K68: =J68 -> 25000 | L68: =K68+L116 -> 25000 | M68: =L68+M116 -> 25000 | N68: =M68+N116 -> 25000 | O68: =N68+O116 -> 25000 | P68: =O68+P116 -> 25000 | Q68: =P68+Q116 -> 25000 | R68: =Q68+R116 -> 25000
B69: NWC: | C69: ='Balance Sheet NWC (Base)'!C11-'Balance Sheet NWC (Base)'!C7-'Balance Sheet NWC (Base)'!C24+'Balance Sheet NWC (Base)'!C20 -> 826074 | D69: ='Balance Sheet NWC (Base)'!D11-'Balance Sheet NWC (Base)'!D7-'Balance Sheet NWC (Base)'!D24+'Balance Sheet NWC (Base)'!D20 -> 914214 | E69: ='Balance Sheet NWC (Base)'!E11-'Balance Sheet NWC (Base)'!E7-'Balance Sheet NWC (Base)'!E24+'Balance Sheet NWC (Base)'!E20 -> 1099822 | F69: ='Balance Sheet NWC (Base)'!F11-'Balance Sheet NWC (Base)'!F7-'Balance Sheet NWC (Base)'!F24+'Balance Sheet NWC (Base)'!F20 -> 847960 | G69: ='Balance Sheet NWC (Base)'!G11-'Balance Sheet NWC (Base)'!G7-'Balance Sheet NWC (Base)'!G24+'Balance Sheet NWC (Base)'!G20 -> 861351 | H69: ='Balance Sheet NWC (Base)'!H11-'Balance Sheet NWC (Base)'!H7-'Balance Sheet NWC (Base)'!H24+'Balance Sheet NWC (Base)'!H20 -> 870085 | I69: ='Balance Sheet NWC (Base)'!I11-'Balance Sheet NWC (Base)'!I7-'Balance Sheet NWC (Base)'!I24+'Balance Sheet NWC (Base)'!I20 -> 809743 | J69: =J43*J$21*4 -> 844251.1 | K69: =J69 -> 844251.1 | L69: =L43*L$21 -> 821882.36 | M69: =M43*M$21 -> 860346.46 | N69: =N43*N$21 -> 923643.38 | O69: =O43*O$21 -> 948048.4 | P69: =P43*P$21 -> 996255.37 | Q69: =Q43*Q$21 -> 1034987.2 | R69: =R43*R$21 -> 1081893.2
B70: Net PP&E, Goodwill & Intangibles: | C70: ='Balance Sheet NWC (Base)'!C12+'Balance Sheet NWC (Base)'!C13+'Balance Sheet NWC (Base)'!C14 -> 1084431 | D70: ='Balance Sheet NWC (Base)'!D12+'Balance Sheet NWC (Base)'!D13+'Balance Sheet NWC (Base)'!D14 -> 1092974 | E70: ='Balance Sheet NWC (Base)'!E12+'Balance Sheet NWC (Base)'!E13+'Balance Sheet NWC (Base)'!E14 -> 1111124 | F70: ='Balance Sheet NWC (Base)'!F12+'Balance Sheet NWC (Base)'!F13+'Balance Sheet NWC (Base)'!F14 -> 1148475 | G70: ='Balance Sheet NWC (Base)'!G12+'Balance Sheet NWC (Base)'!G13+'Balance Sheet NWC (Base)'!G14 -> 1147299 | H70: ='Balance Sheet NWC (Base)'!H12+'Balance Sheet NWC (Base)'!H13+'Balance Sheet NWC (Base)'!H14 -> 1159699 | I70: ='Balance Sheet NWC (Base)'!I12+'Balance Sheet NWC (Base)'!I13+'Balance Sheet NWC (Base)'!I14 -> 1169573 | J70: =I70-J101-J94 -> 1173392 | K70: =J70 -> 1173392 | L70: =K70-L101-L94 -> 1169105 | M70: =L70-M101-M94 -> 1169225.7 | N70: =M70-N101-N94 -> 1173328.9 | O70: =N70-O101-O94 -> 1180540.6 | P70: =O70-P101-P94 -> 1185649.3 | Q70: =P70-Q101-Q94 -> 1188157.4 | R70: =Q70-R101-R94 -> 1192431.5
B71: Op. Lease Assets: | C71: ='Balance Sheet NWC (Base)'!C15 -> 56173 | D71: ='Balance Sheet NWC (Base)'!D15 -> 49011 | E71: ='Balance Sheet NWC (Base)'!E15 -> 64780 | F71: ='Balance Sheet NWC (Base)'!F15 -> 65909 | G71: ='Balance Sheet NWC (Base)'!G15 -> 61076 | H71: ='Balance Sheet NWC (Base)'!H15 -> 61943 | I71: ='Balance Sheet NWC (Base)'!I15 -> 60878 | J71: =I71 -> 60878 | K71: =J71 -> 60878 | L71: =K71 -> 60878 | M71: =L71 -> 60878 | N71: =M71 -> 60878 | O71: =N71 -> 60878 | P71: =O71 -> 60878 | Q71: =P71 -> 60878 | R71: =Q71 -> 60878 | S71: No change
B72: Other Assets: | C72: ='Balance Sheet NWC (Base)'!C16 -> 4056 | D72: ='Balance Sheet NWC (Base)'!D16 -> 5885 | E72: ='Balance Sheet NWC (Base)'!E16 -> 9887 | F72: ='Balance Sheet NWC (Base)'!F16 -> 12237 | G72: ='Balance Sheet NWC (Base)'!G16 -> 14383 | H72: ='Balance Sheet NWC (Base)'!H16 -> 14839 | I72: ='Balance Sheet NWC (Base)'!I16 -> 24495 | J72: =I72-J97-J102 -> 27349.653 | K72: =J72 -> 27349.653 | L72: =K72-L97-L102 -> 21267.689 | M72: =L72-M97-M102 -> 22146.608 | N72: =M72-N97-N102 -> 20878.941 | O72: =N72-O97-O102 -> 18509.348 | P72: =O72-P97-P102 -> 19209.79 | Q72: =P72-Q97-Q102 -> 17239.184 | R72: =Q72-R97-R102 -> 16360.742
B73: Total Assets: | C73: =SUM(C68:C72) -> 2095945 | D73: =SUM(D68:D72) -> 2102620 | E73: =SUM(E68:E72) -> 2329150 | F73: =SUM(F68:F72) -> 2124633 | G73: =SUM(G68:G72) -> 2109914 | H73: =SUM(H68:H72) -> 2128793 | I73: =SUM(I68:I72) -> 2090617 | J73: =SUM(J68:J72) -> 2130870.8 | ... R73: =SUM(R68:R72) -> 2376563.4
B75: LIABILITES & EQUITY:
B76: Revolver: | C76: 174200 | D76: 204200 | E76: 205300 | F76: 40300 | G76: 125300 | H76: 176300 | I76: 81300 | J76: =I76+J106 -> 102172.5 | K76: =J76 -> 102172.5 | L76: =K76+L106 -> 91516.95 | M76: =L76+M106 -> 108190.72 | N76: =M76+N106 -> 123066.04 | O76: =N76+O106 -> 139441.74 | P76: =O76+P106 -> 152840.8 | Q76: =P76+Q106 -> 162092.74 | R76: =Q76+R106 -> 179789.44
B77: Short-Term Debt: | C77: ='Balance Sheet NWC (Base)'!C20 -> 122248 | D77: ='Balance Sheet NWC (Base)'!D20 -> 202433 | E77: ='Balance Sheet NWC (Base)'!E20 -> 325680 | F77: ='Balance Sheet NWC (Base)'!F20 -> 229935 | G77: ='Balance Sheet NWC (Base)'!G20 -> 244048 | H77: ='Balance Sheet NWC (Base)'!H20 -> 257829 | I77: ='Balance Sheet NWC (Base)'!I20 -> 206335 | J77: =I77 -> 206335 | K77: =J77 -> 206335 | L77: =K77 -> 206335 | M77: =L77 -> 206335 | N77: =M77 -> 206335 | O77: =N77 -> 206335 | P77: =O77 -> 206335 | Q77: =P77 -> 206335 | R77: =Q77 -> 206335 | S77: No change
B78: Long-Term Debt: | C78: ='Balance Sheet NWC (Base)'!C25-C76 -> 322818 | D78: ='Balance Sheet NWC (Base)'!D25-D76 -> 379416 | E78: ='Balance Sheet NWC (Base)'!E25-E76 -> 263612 | F78: ='Balance Sheet NWC (Base)'!F25-F76 -> 184091 | G78: ='Balance Sheet NWC (Base)'!G25-G76 -> 169130 | H78: ='Balance Sheet NWC (Base)'!H25-H76 -> 118174 | I78: ='Balance Sheet NWC (Base)'!I25-I76 -> 218512 | J78: =I78/1.0025 -> 217967.08 | K78: =J78 -> 217967.08 | L78: =K78/1.01 -> 215808.99 | M78: =L78/1.01 -> 213672.27 | N78: =M78/1.01 -> 211556.7 | O78: =N78/1.01 -> 209462.08 | P78: =O78/1.01 -> 207388.2 | Q78: =P78/1.01 -> 205334.85 | R78: =Q78/1.01 -> 203301.83 | S78: 1% Annual Amortization
B79: Op. Lease Liabilities: | C79: ='Balance Sheet NWC (Base)'!C26 -> 34379 | D79: ='Balance Sheet NWC (Base)'!D26 -> 36429 | E79: ='Balance Sheet NWC (Base)'!E26 -> 47616 | F79: ='Balance Sheet NWC (Base)'!F26 -> 45924 | G79: ='Balance Sheet NWC (Base)'!G26 -> 41410 | H79: ='Balance Sheet NWC (Base)'!H26 -> 41230 | I79: ='Balance Sheet NWC (Base)'!I26 -> 39532 | J79: =I79 -> 39532 | K79: =J79 -> 39532 | L79: =K79 -> 39532 | M79: =L79 -> 39532 | N79: =M79 -> 39532 | O79: =N79 -> 39532 | P79: =O79 -> 39532 | Q79: =P79 -> 39532 | R79: =Q79 -> 39532 | S79: No change
B80: Other Liabilities: | C80: ='Balance Sheet NWC (Base)'!C27+'Balance Sheet NWC (Base)'!C28 -> 121727 | D80: ='Balance Sheet NWC (Base)'!D27+'Balance Sheet NWC (Base)'!D28 -> 118270 | E80: ='Balance Sheet NWC (Base)'!E27+'Balance Sheet NWC (Base)'!E28 -> 124659 | F80: ='Balance Sheet NWC (Base)'!F27+'Balance Sheet NWC (Base)'!F28 -> 131801 | G80: ='Balance Sheet NWC (Base)'!G27+'Balance Sheet NWC (Base)'!G28 -> 131801 | H80: ='Balance Sheet NWC (Base)'!H27+'Balance Sheet NWC (Base)'!H28 -> 131761 | I80: ='Balance Sheet NWC (Base)'!I27+'Balance Sheet NWC (Base)'!I28 -> 130729 | J80: =I80 -> 130729 | K80: =J80 -> 130729 | L80: =K80 -> 130729 | M80: =L80 -> 130729 | N80: =M80 -> 130729 | O80: =N80 -> 130729 | P80: =O80 -> 130729 | Q80: =P80 -> 130729 | R80: =Q80 -> 130729 | S80: No change
B81: Total Liabilities: | C81: =SUM(C76:C80) -> 775372 | D81: =SUM(D76:D80) -> 940748 | E81: =SUM(E76:E80) -> 966867 | F81: =SUM(F76:F80) -> 632051 | G81: =SUM(G76:G80) -> 711689 | H81: =SUM(H76:H80) -> 725294 | I81: =SUM(I76:I80) -> 676408 | J81: =SUM(J76:J80) -> 696735.58 | ... R81: =SUM(R76:R80) -> 759687.28
B83: Common Shareholders' Equity: | C83: ='Balance Sheet NWC (Base)'!C40 -> 1314945 | D83: ='Balance Sheet NWC (Base)'!D40 -> 1150871 | E83: ='Balance Sheet NWC (Base)'!E40 -> 1350434 | F83: ='Balance Sheet NWC (Base)'!F40 -> 1479164 | G83: ='Balance Sheet NWC (Base)'!G40 -> 1385073 | H83: ='Balance Sheet NWC (Base)'!H40 -> 1390509 | I83: ='Balance Sheet NWC (Base)'!I40 -> 1401616 | J83: =I83+J93+J108+J109+J111+J114-J61 -> 1421314.1 | K83: =J83 -> 1421314.1 | L83: =K83+L93+L108+L109+L111+L114-L61 -> 1400004.2 | M83: =L83+M93+M108+M109+M111+M114-M61 -> 1423223.8 | N83: =M83+N93+N108+N109+N111+N114-N61 -> 1474763.3 | O83: =N83+O93+O108+O109+O111+O114-O61 -> 1488092.5 | P83: =O83+P93+P108+P109+P111+P114-P61 -> 1529098.2 | Q83: =P83+Q93+Q108+Q109+Q111+Q114-Q61 -> 1559281.5 | R83: =Q83+R93+R108+R109+R111+R114-R61 -> 1591913.3
B84: Noncontrolling Interests: | C84: ='Balance Sheet NWC (Base)'!C41 -> 5628 | D84: ='Balance Sheet NWC (Base)'!D41 -> 11001 | E84: ='Balance Sheet NWC (Base)'!E41 -> 11849 | F84: ='Balance Sheet NWC (Base)'!F41 -> 13418 | G84: ='Balance Sheet NWC (Base)'!G41 -> 13152 | H84: ='Balance Sheet NWC (Base)'!H41 -> 12990 | I84: ='Balance Sheet NWC (Base)'!I41 -> 12593 | J84: =I84+J61+J110 -> 12821.081 | K84: =J84 -> 12821.081 | L84: =K84+L61+L110 -> 14206.887 | M84: =L84+M61+M110 -> 15914.011 | N84: =M84+N61+N110 -> 17747.184 | O84: =N84+O61+O110 -> 19384.033 | P84: =O84+P61+P110 -> 21069.214 | Q84: =P84+Q61+Q110 -> 22956.675 | R84: =Q84+R61+R110 -> 24962.83
B85: Total Equity: | C85: =SUM(C83:C84) -> 1320573 | D85: =SUM(D83:D84) -> 1161872 | E85: =SUM(E83:E84) -> 1362283 | F85: =SUM(F83:F84) -> 1492582 | G85: =SUM(G83:G84) -> 1398225 | H85: =SUM(H83:H84) -> 1403499 | I85: =SUM(I83:I84) -> 1414209 | J85: =SUM(J83:J84) -> 1434135.2 | ... R85: =SUM(R83:R84) -> 1616876.1
B87: TOTAL LIABILITIES + EQUITY: | C87: =C81+C85 -> 2095945 | D87: =D81+D85 -> 2102620 | E87: =E81+E85 -> 2329150 | F87: =F81+F85 -> 2124633 | G87: =G81+G85 -> 2109914 | H87: =H81+H85 -> 2128793 | I87: =I81+I85 -> 2090617 | J87: =J81+J85 -> 2130870.8 | ... R87: =R81+R85 -> 2376563.4
B89: Balance Check: | C89: =C73-C87 -> 0 | D89: =D73-D87 -> 0 | E89: =E73-E87 -> 0 | F89: =F73-F87 -> 0 | G89: =G73-G87 -> 0 | H89: =H73-H87 -> 0 | I89: =I73-I87 -> 0 | J89: =J73-J87 -> 0 | ... R89: =R73-R87 -> 0
B91: Cash Flow Statement: | C91: =C$2 -> 44196 | D91: =D$2 -> 44561 | E91: =E$2 -> 44926 | F91: =F$2 -> 45291 | G91: =G$2 -> Q1-24 | H91: =H$2 -> Q2-24 | I91: =I$2 -> Q3-24 | J91: =J$2 -> Q4-24 | ... R91: =R$2 -> 48213
B92: Cash Flow from Operations:
B93: Net Income to Parent: | C93: =C60 -> 251758 | D93: =D60 -> 217937 | E93: =E60 -> 340482 | F93: =F60 -> 343107 | G93: =G60 -> 69128 | H93: =H60 -> 61565 | I93: =I60 -> 71312 | J93: =J60 -> 64913.144 | K93: =SUM(G93:J93) -> 266918.14 | L93: =L60 -> 277602.98 | M93: =M60 -> 291954.03 | N93: =N60 -> 323881.59 | O93: =O60 -> 327513.49 | P93: =P60 -> 337670.52 | Q93: =Q60 -> 356290.05 | R93: =R60 -> 374377.5
B94: (+) D&A: | C94: ='Cash Flows'!C8+'Cash Flows'!C9 -> 69079 | D94: ='Cash Flows'!D8+'Cash Flows'!D9 -> 68846 | E94: ='Cash Flows'!E8+'Cash Flows'!E9 -> 70376 | F94: ='Cash Flows'!F8+'Cash Flows'!F9 -> 75129 | G94: ='Cash Flows'!G8+'Cash Flows'!G9 -> 19782 | H94: ='Cash Flows'!H8+'Cash Flows'!H9 -> 21293 | I94: ='Cash Flows'!I8+'Cash Flows'!I9 -> 20650 | J94: =J44*J23 -> 20499.369 | K94: =SUM(G94:J94) -> 82224.369 | L94: =L44*L23 -> 77682.279 | M94: =M44*M23 -> 80361.977 | N94: =N44*N23 -> 84775.859 | O94: =O44*O23 -> 88250.329 | P94: =P44*P23 -> 93983.779 | Q94: =Q44*Q23 -> 96526.604 | R94: =R44*R23 -> 100817.29
B95: (+/-) Change in NWC: | C95: ='Cash Flows'!C14+'Cash Flows'!C21+'Cash Flows'!C22+'Cash Flows'!C23+'Cash Flows'!C25+'Cash Flows'!C26 -> 38929 | D95: ='Cash Flows'!D14+'Cash Flows'!D21+'Cash Flows'!D22+'Cash Flows'!D23+'Cash Flows'!D25+'Cash Flows'!D26 -> -76776 | E95: ='Cash Flows'!E14+'Cash Flows'!E21+'Cash Flows'!E22+'Cash Flows'!E23+'Cash Flows'!E25+'Cash Flows'!E26 -> -194459 | F95: ='Cash Flows'!F14+'Cash Flows'!F21+'Cash Flows'!F22+'Cash Flows'!F23+'Cash Flows'!F25+'Cash Flows'!F26 -> 245281 | G95: ='Cash Flows'!G14+'Cash Flows'!G21+'Cash Flows'!G22+'Cash Flows'!G23+'Cash Flows'!G25+'Cash Flows'!G26 -> -13193 | H95: ='Cash Flows'!H14+'Cash Flows'!H21+'Cash Flows'!H22+'Cash Flows'!H23+'Cash Flows'!H25+'Cash Flows'!H26 -> -5072 | I95: ='Cash Flows'!I14+'Cash Flows'!I21+'Cash Flows'!I22+'Cash Flows'!I23+'Cash Flows'!I25+'Cash Flows'!I26 -> 56945 | J95: =I69-J69 -> -34508.102 | K95: =SUM(G95:J95) -> 4171.8983 | L95: =K69-L69 -> 22368.739 | M95: =L69-M69 -> -38464.095 | N95: =M69-N69 -> -63296.927 | O95: =N69-O69 -> -24405.019 | P95: =O69-P69 -> -48206.962 | Q95: =P69-Q69 -> -38731.831 | R95: =Q69-R69 -> -46905.966
B96: (+/-) Change in Leases: | C96: ='Cash Flows'!C10+'Cash Flows'!C15+'Cash Flows'!C24 -> 512 | D96: ='Cash Flows'!D10+'Cash Flows'!D15+'Cash Flows'!D24 -> 1601 | E96: ='Cash Flows'!E10+'Cash Flows'!E15+'Cash Flows'!E24 -> 43 | F96: ='Cash Flows'!F10+'Cash Flows'!F15+'Cash Flows'!F24 -> -207 | G96: ='Cash Flows'!G10+'Cash Flows'!G15+'Cash Flows'!G24 -> -158 | H96: ='Cash Flows'!H10+'Cash Flows'!H15+'Cash Flows'!H24 -> -56 | I96: ='Cash Flows'!I10+'Cash Flows'!I15+'Cash Flows'!I24 -> -81 | J96: =I71-J71+J79-I79 -> 0 | K96: =SUM(G96:J96) -> -295 | L96: =K71-L71+L79-K79 -> 0 | M96: =L71-M71+M79-L79 -> 0 | N96: =M71-N71+N79-M79 -> 0 | O96: =N71-O71+O79-N79 -> 0 | P96: =O71-P71+P79-O79 -> 0 | Q96: =P71-Q71+Q79-P79 -> 0 | R96: =Q71-R71+R79-Q79 -> 0
B97: (+/-) Other Items: | C97: =SUM('Cash Flows'!C11:C13,'Cash Flows'!C16:C19) -> 36461 | D97: =SUM('Cash Flows'!D11:D13,'Cash Flows'!D16:D19) -> 12854 | E97: =SUM('Cash Flows'!E11:E13,'Cash Flows'!E16:E19) -> 29741 | F97: =SUM('Cash Flows'!F11:F13,'Cash Flows'!F16:F19) -> 36272 | G97: =SUM('Cash Flows'!G11:G13,'Cash Flows'!G16:G19) -> 5609 | H97: =SUM('Cash Flows'!H11:H13,'Cash Flows'!H16:H19) -> 1013 | I97: =SUM('Cash Flows'!I11:I13,'Cash Flows'!I16:I19) -> -5304 | J97: =J44*J24 -> 490.95235 | K97: =SUM(G97:J97) -> 1808.9523 | L97: =L44*L24 -> 25056.605 | M97: =M44*M24 -> 22386.434 | N97: =N44*N24 -> 25269.908 | O97: =O44*O24 -> 24229.157 | P97: =P44*P24 -> 22219.024 | Q97: =Q44*Q24 -> 27218.338 | R97: =R44*R24 -> 27601.151
B98: Cash Flow from Operations: | C98: =SUM(C93:C97) -> 396739 | D98: =SUM(D93:D97) -> 224462 | E98: =SUM(E93:E97) -> 246183 | F98: =SUM(F93:F97) -> 699582 | G98: =SUM(G93:G97) -> 81168 | H98: =SUM(H93:H97) -> 78743 | I98: =SUM(I93:I97) -> 143522 | J98: =SUM(J93:J97) -> 51395.363 | ... R98: =SUM(R93:R97) -> 455889.97
B100: Cash Flow from Investing:
B101: (-) CapEx: | C101: ='Cash Flows'!C30 -> -46991 | D101: ='Cash Flows'!D30 -> -53746 | E101: ='Cash Flows'!E30 -> -61373 | F101: ='Cash Flows'!F30 -> -92493 | G101: ='Cash Flows'!G30 -> -18433 | H101: ='Cash Flows'!H30 -> -25350 | I101: ='Cash Flows'!I30 -> -29571 | J101: =-J44*J22 -> -24318.379 | K101: =SUM(G101:J101) -> -97672.379 | L101: =-L44*L22 -> -73395.274 | M101: =-M44*M22 -> -80482.712 | N101: =-N44*N22 -> -88879.07 | O101: =-O44*O22 -> -95461.983 | P101: =-P44*P22 -> -99092.467 | Q101: =-Q44*Q22 -> -99034.698 | R101: =-R44*R22 -> -105091.41
B102: (-) Acquisitions & Other: | C102: ='Cash Flows'!C32+'Cash Flows'!C33 -> -2286 | D102: ='Cash Flows'!D32+'Cash Flows'!D33 -> -22000 | E102: ='Cash Flows'!E32+'Cash Flows'!E33 -> -33120 | F102: ='Cash Flows'!F32+'Cash Flows'!F33 -> -20182 | G102: ='Cash Flows'!G32+'Cash Flows'!G33 -> 0 | H102: ='Cash Flows'!H32+'Cash Flows'!H33 -> -9868 | I102: ='Cash Flows'!I32+'Cash Flows'!I33 -> 9 | J102: =-J25*J43 -> -3345.6052 | K102: =SUM(G102:J102) -> -13204.605 | L102: =-L25*L43 -> -18974.641 | M102: =-M25*M43 -> -23265.352 | N102: =-N25*N43 -> -24002.242 | O102: =-O25*O43 -> -21859.563 | P102: =-P25*P43 -> -22919.466 | Q102: =-Q25*Q43 -> -25247.731 | R102: =-R25*R43 -> -26722.708
B103: Cash Flow from Investing: | C103: =SUM(C101:C102) -> -49277 | D103: =SUM(D101:D102) -> -75746 | E103: =SUM(E101:E102) -> -94493 | F103: =SUM(F101:F102) -> -112675 | G103: =SUM(G101:G102) -> -18433 | H103: =SUM(H101:H102) -> -35218 | I103: =SUM(I101:I102) -> -29562 | J103: =SUM(J101:J102) -> -27663.984 | ... R103: =SUM(R101:R102) -> -131814.12
B105: Cash Flow from Financing:
B106: (+/-) Revolver: | C106: =C76 -> 174200 | D106: =D76-C76 -> 30000 | E106: =E76-D76 -> 1100 | F106: =F76-E76 -> -165000 | G106: =G76-F76 -> 85000 | H106: =H76-G76 -> 51000 | I106: =I76-H76 -> -95000 | J106: =J34 -> 20872.496 | K106: =SUM(G106:J106) -> 61872.496 | L106: =L34 -> -10655.546 | M106: =M34 -> 16673.768 | N106: =N34 -> 14875.325 | O106: =O34 -> 16375.701 | P106: =P34 -> 13399.055 | Q106: =Q34 -> 9251.9376 | R106: =R34 -> 17696.709
B107: (+/-) Change in Debt: | C107: ='Cash Flows'!C41+'Cash Flows'!C42+'Cash Flows'!C44+'Cash Flows'!C45+'Cash Flows'!C46+'Cash Flows'!C47-C106 -> -189 | D107: ='Cash Flows'!D41+'Cash Flows'!D42+'Cash Flows'!D44+'Cash Flows'!D45+'Cash Flows'!D46+'Cash Flows'!D47-D106 -> 136466 | E107: ='Cash Flows'!E41+'Cash Flows'!E42+'Cash Flows'!E44+'Cash Flows'!E45+'Cash Flows'!E46+'Cash Flows'!E47-E106 -> 5934 | F107: ='Cash Flows'!F41+'Cash Flows'!F42+'Cash Flows'!F44+'Cash Flows'!F45+'Cash Flows'!F46+'Cash Flows'!F47-F106 -> -177193 | G107: ='Cash Flows'!G41+'Cash Flows'!G42+'Cash Flows'!G44+'Cash Flows'!G45+'Cash Flows'!G46+'Cash Flows'!G47-G106 -> -376 | H107: ='Cash Flows'!H41+'Cash Flows'!H42+'Cash Flows'!H44+'Cash Flows'!H45+'Cash Flows'!H46+'Cash Flows'!H47-H106 -> -36774 | I107: ='Cash Flows'!I41+'Cash Flows'!I42+'Cash Flows'!I44+'Cash Flows'!I45+'Cash Flows'!I46+'Cash Flows'!I47-I106 -> 50000 | J107: =J78-I78+J80-I80+J77-I77 -> -544.91771 | K107: =SUM(G107:J107) -> 12305.082 | L107: =L78-K78+L80-K80+L77-K77 -> -2158.0899 | M107: =M78-L78+M80-L80+M77-L77 -> -2136.7227 | N107: =N78-M78+N80-M80+N77-M77 -> -2115.567 | O107: =O78-N78+O80-N80+O77-N77 -> -2094.6208 | P107: =P78-O78+P80-O80+P77-O77 -> -2073.882 | Q107: =Q78-P78+Q80-P80+Q77-P77 -> -2053.3485 | R107: =R78-Q78+R80-Q80+R77-Q77 -> -2033.0183
B108: (-) Common Dividends: | C108: ='Cash Flows'!C37 -> -166537 | D108: ='Cash Flows'!D37 -> -167299 | E108: ='Cash Flows'!E37 -> -167376 | F108: ='Cash Flows'!F37 -> -176715 | G108: ='Cash Flows'!G37 -> -47192 | H108: ='Cash Flows'!H37 -> -46772 | I108: ='Cash Flows'!I37 -> -46731 | J108: =-J62*J27 -> -45030.624 | K108: =SUM(G108:J108) -> -185725.62 | L108: =-L62*L27 -> -173243.46 | M108: =-M62*M27 -> -179954.02 | N108: =-N62*N27 -> -189926.48 | O108: =-O62*O27 -> -198516.12 | P108: =-P62*P27 -> -211012.21 | Q108: =-Q62*Q27 -> -217898.34 | R108: =-R62*R27 -> -228025.08
B109: (-) Stock Repurchases: | C109: ='Cash Flows'!C36 -> -3444 | D109: ='Cash Flows'!D36 -> -71261 | E109: ='Cash Flows'!E36 -> -27359 | F109: ='Cash Flows'!F36 -> -95779 | G109: ='Cash Flows'!G36 -> -132045 | H109: ='Cash Flows'!H36 -> -16632 | I109: ='Cash Flows'!I36 -> -18489 | J109: =-J28*J62 -> 0 | K109: =SUM(G109:J109) -> -167166 | L109: =-L28*L62 -> -124297.73 | M109: =-M28*M62 -> -87074.072 | N109: =-N28*N62 -> -80512.105 | O109: =-O28*O62 -> -114056.82 | P109: =-P28*P62 -> -83996.334 | Q109: =-Q28*Q62 -> -106320.78 | R109: =-R28*R62 -> -111711.4
B110: (-) Dividends to NCI: | C110: ='Cash Flows'!C38 -> -277634 | D110: ='Cash Flows'!D38 -> -195351 | E110: ='Cash Flows'!E38 -> 0 | F110: ='Cash Flows'!F38 -> 0 | G110: ='Cash Flows'!G38 -> 0 | H110: ='Cash Flows'!H38 -> 0 | I110: ='Cash Flows'!I38 -> 0 | J110: 0 | K110: =SUM(G110:J110) -> 0 | L110: 0 | M110: 0 | N110: 0 | O110: 0 | P110: 0 | Q110: 0 | R110: 0
B111: (+/-) Other Items: | C111: ='Cash Flows'!C39+'Cash Flows'!C40+'Cash Flows'!C43+'Cash Flows'!C48 -> 18986 | D111: ='Cash Flows'!D39+'Cash Flows'!D40+'Cash Flows'!D43+'Cash Flows'!D48 -> 33698 | E111: ='Cash Flows'!E39+'Cash Flows'!E40+'Cash Flows'!E43+'Cash Flows'!E48 -> 39561 | F111: ='Cash Flows'!F39+'Cash Flows'!F40+'Cash Flows'!F43+'Cash Flows'!F48 -> 34287 | G111: ='Cash Flows'!G39+'Cash Flows'!G40+'Cash Flows'!G43+'Cash Flows'!G48 -> 7422 | H111: ='Cash Flows'!H39+'Cash Flows'!H40+'Cash Flows'!H43+'Cash Flows'!H48 -> 2092 | I111: ='Cash Flows'!I39+'Cash Flows'!I40+'Cash Flows'!I43+'Cash Flows'!I48 -> 22 | J111: =MAX(J107,0)*J29 -> 0 | K111: =SUM(G111:J111) -> 9536 | L111: =MAX(L107,0)*L29 -> 0 | M111: =MAX(M107,0)*M29 -> 0 | N111: =MAX(N107,0)*N29 -> 0 | O111: =MAX(O107,0)*O29 -> 0 | P111: =MAX(P107,0)*P29 -> 0 | Q111: =MAX(Q107,0)*Q29 -> 0 | R111: =MAX(R107,0)*R29 -> 0 | S111: Capital structure fixed via buybacks
B112: Cash Flow from Financing: | C112: =SUM(C106:C111) -> -254618 | D112: =SUM(D106:D111) -> -233747 | E112: =SUM(E106:E111) -> -148140 | F112: =SUM(F106:F111) -> -580400 | G112: =SUM(G106:G111) -> -87191 | H112: =SUM(H106:H111) -> -47086 | I112: =SUM(I106:I111) -> -110198 | J112: =SUM(J106:J111) -> -24703.046 | ... R112: =SUM(R106:R111) -> -324072.79
B114: FX Rate Effects: | C114: ='Cash Flows'!C50 -> 81 | D114: ='Cash Flows'!D50 -> 356 | E114: ='Cash Flows'!E50 -> -549 | F114: ='Cash Flows'!F50 -> 8 | G114: ='Cash Flows'!G50 -> 209 | H114: ='Cash Flows'!H50 -> -17 | I114: ='Cash Flows'!I50 -> -61 | J114: =AVERAGE(G114:I114) -> 43.666667 | K114: =SUM(G114:J114) -> 174.66667 | L114: =AVERAGE(C114:F114,K114) -> 14.133333 | M114: =AVERAGE(K114:L114,D114:F114) -> 0.76 | N114: =AVERAGE(K114:M114,E114:F114) -> -70.288 | O114: =AVERAGE(K114:N114,F114) -> 25.4544 | P114: =AVERAGE(K114:O114) -> 28.94528 | Q114: =AVERAGE(L114:P114) -> -0.19899733 | R114: =AVERAGE(M114:Q114) -> -3.0654635
B116: Net Change in Cash: | C116: =C98+C103+C112+C114 -> 92925 | D116: =D98+D103+D112+D114 -> -84675 | E116: =E98+E103+E112+E114 -> 3001 | F116: =F98+F103+F112+F114 -> 6515 | G116: =G98+G103+G112+G114 -> -24247 | H116: =H98+H103+H112+H114 -> -3578 | I116: =I98+I103+I112+I114 -> 3701 | J116: =J98+J103+J112+J114 -> -928 | ... R116: =R98+R103+R112+R114 -> -1.5510215e-10
C117: ='Cash Flows'!C51 -> 92925 | D117: ='Cash Flows'!D51 -> -84675 | E117: ='Cash Flows'!E51 -> 3001 | F117: ='Cash Flows'!F51 -> 6515 | G117: ='Cash Flows'!G51 -> -24247 | H117: ='Cash Flows'!H51 -> -3578 | I117: ='Cash Flows'!I51 -> 3701
B118: Check | C118: =C116-C117 -> 0 | D118: =D116-D117 -> 0 | E118: =E116-E117 -> 0 | F118: =F116-F117 -> 0 | G118: =G116-G117 -> 0 | H118: =H116-H117 -> 0 | I118: =I116-I117 -> 0

Sheet Valuation (Downside)
D3: VALUATION
E4: ='3-Statement (Downside)'!J2 -> Q4-24 | F4: ='3-Statement (Downside)'!K2 -> 45657 | G4: ='3-Statement (Downside)'!L2 -> 46022 | H4: ='3-Statement (Downside)'!M2 -> 46387 | I4: ='3-Statement (Downside)'!N2 -> 46752 | J4: ='3-Statement (Downside)'!O2 -> 47118 | K4: ='3-Statement (Downside)'!P2 -> 47483 | L4: ='3-Statement (Downside)'!Q2 -> 47848 | M4: ='3-Statement (Downside)'!R2 -> 48213
D5: Revenue | E5: ='3-Statement (Downside)'!J48 -> 952178.75 | F5: ='3-Statement (Downside)'!K48 -> 3820845.7 | G5: ='3-Statement (Downside)'!L48 -> 3629803.5 | H5: ='3-Statement (Downside)'!M48 -> 3520909.4 | I5: ='3-Statement (Downside)'!N48 -> 3520909.4 | J5: ='3-Statement (Downside)'!O48 -> 3591327.5 | K5: ='3-Statement (Downside)'!P48 -> 3699067.4 | L5: ='3-Statement (Downside)'!Q48 -> 3838744.2 | M5: ='3-Statement (Downside)'!R48 -> 4016677.6
D6: Cost of Goods Sold | E6: ='3-Statement (Downside)'!J51 -> -559738.78 | F6: ='3-Statement (Downside)'!K51 -> -2246230.8 | G6: ='3-Statement (Downside)'!L51 -> -2159056.4 | H6: ='3-Statement (Downside)'!M51 -> -2091187.2 | I6: ='3-Statement (Downside)'!N51 -> -2078584.7 | J6: ='3-Statement (Downside)'!O51 -> -2118308.6 | K6: ='3-Statement (Downside)'!P51 -> -2168267.7 | L6: ='3-Statement (Downside)'!Q51 -> -2248819.2 | M6: ='3-Statement (Downside)'!R51 -> -2353866.3
D7: Operating Expenses | E7: ='3-Statement (Downside)'!J52 -> -289178.76 | F7: ='3-Statement (Downside)'!K52 -> -1160037.8 | G7: ='3-Statement (Downside)'!L52 -> -1140890.5 | H7: ='3-Statement (Downside)'!M52 -> -1091682.8 | I7: ='3-Statement (Downside)'!N52 -> -1071562.6 | J7: ='3-Statement (Downside)'!O52 -> -1084204.9 | K7: ='3-Statement (Downside)'!P52 -> -1105440 | L7: ='3-Statement (Downside)'!Q52 -> -1143523.3 | M7: ='3-Statement (Downside)'!R52 -> -1195385.6
D8: Restructuring Costs | E8: ='3-Statement (Downside)'!J54 -> -6677.9508 | F8: ='3-Statement (Downside)'!K54 -> -18464.951 | G8: ='3-Statement (Downside)'!L54 -> -32399.372 | H8: ='3-Statement (Downside)'!M54 -> -31227.735 | I8: ='3-Statement (Downside)'!N54 -> -25897.865 | J8: ='3-Statement (Downside)'!O54 -> -26378.427 | K8: ='3-Statement (Downside)'!P54 -> -30122.285 | L8: ='3-Statement (Downside)'!Q54 -> -31200.428 | M8: ='3-Statement (Downside)'!R54 -> -32005.44
D9: EBIT | E9: =SUM(E5:E8) -> 96583.254 | F9: =SUM(F5:F8) -> 396112.25 | G9: =SUM(G5:G8) -> 297457.21 | H9: =SUM(H5:H8) -> 306811.64 | I9: =SUM(I5:I8) -> 344864.14 | J9: =SUM(J5:J8) -> 362435.57 | K9: =SUM(K5:K8) -> 395237.37 | L9: =SUM(L5:L8) -> 415201.2 | M9: =SUM(M5:M8) -> 435420.34
D10: Net Interest | E10: ='3-Statement (Downside)'!J60 -> -4723.6238 | F10: ='3-Statement (Downside)'!K60 -> -18790.624 | G10: ='3-Statement (Downside)'!L60 -> -18747.69 | H10: ='3-Statement (Downside)'!M60 -> -18589.578 | I10: ='3-Statement (Downside)'!N60 -> -18430.884 | J10: ='3-Statement (Downside)'!O60 -> -18332.077 | K10: ='3-Statement (Downside)'!P60 -> -18153.481 | L10: ='3-Statement (Downside)'!Q60 -> -17996.658 | M10: ='3-Statement (Downside)'!R60 -> -17765.012
D11: Other Income (Expense) | E11: ='3-Statement (Downside)'!J59 -> -6260.0937 | F11: ='3-Statement (Downside)'!K59 -> -25113.094 | G11: ='3-Statement (Downside)'!L59 -> -19046.128 | H11: ='3-Statement (Downside)'!M59 -> -18565.403 | I11: ='3-Statement (Downside)'!N59 -> -19142.344 | J11: ='3-Statement (Downside)'!O59 -> -20035.49 | K11: ='3-Statement (Downside)'!P59 -> -20794.913 | L11: ='3-Statement (Downside)'!Q59 -> -20850.008 | M11: ='3-Statement (Downside)'!R59 -> -21964.514
D12: Taxes | E12: ='3-Statement (Downside)'!J63 -> -20686.393 | F12: ='3-Statement (Downside)'!K63 -> -85290.393 | G12: ='3-Statement (Downside)'!L63 -> -63686.42 | H12: ='3-Statement (Downside)'!M63 -> -66054.8 | I12: ='3-Statement (Downside)'!N63 -> -75316.055 | J12: ='3-Statement (Downside)'!O63 -> -79416.727 | K12: ='3-Statement (Downside)'!P63 -> -87115.634 | L12: ='3-Statement (Downside)'!Q63 -> -92198.686 | M12: ='3-Statement (Downside)'!R63 -> -96912.941
D13: Net Income | E13: =SUM(E9:E12) -> 64913.144 | F13: =SUM(F9:F12) -> 266918.14 | G13: =SUM(G9:G12) -> 195976.97 | H13: =SUM(H9:H12) -> 203601.86 | I13: =SUM(I9:I12) -> 231974.86 | J13: =SUM(J9:J12) -> 244651.28 | K13: =SUM(K9:K12) -> 269173.34 | L13: =SUM(L9:L12) -> 284155.85 | M13: =SUM(M9:M12) -> 298777.87
D15: Cash Flow from Operations | E15: ='3-Statement (Downside)'!J103 -> 51395.363 | F15: ='3-Statement (Downside)'!K103 -> 354828.36 | G15: ='3-Statement (Downside)'!L103 -> 246028.06 | H15: ='3-Statement (Downside)'!M103 -> 328503.4 | I15: ='3-Statement (Downside)'!N103 -> 348427.1 | J15: ='3-Statement (Downside)'!O103 -> 326668.12 | K15: ='3-Statement (Downside)'!P103 -> 350106.44 | L15: ='3-Statement (Downside)'!Q103 -> 351042.82 | M15: ='3-Statement (Downside)'!R103 -> 363724.93
D16: Capital Expenditures | E16: ='3-Statement (Downside)'!J106 -> -24318.379 | F16: ='3-Statement (Downside)'!K106 -> -97672.379 | G16: ='3-Statement (Downside)'!L106 -> -59200.568 | H16: ='3-Statement (Downside)'!M106 -> -64177.604 | I16: ='3-Statement (Downside)'!N106 -> -70272.85 | J16: ='3-Statement (Downside)'!O106 -> -74791.988 | K16: ='3-Statement (Downside)'!P106 -> -79814.491 | L16: ='3-Statement (Downside)'!Q106 -> -79767.96 | M16: ='3-Statement (Downside)'!R106 -> -84646.366
D17: Free Cash Flow | E17: =SUM(E15:E16) -> 27076.985 | F17: =SUM(F15:F16) -> 257155.98 | G17: =SUM(G15:G16) -> 186827.5 | H17: =SUM(H15:H16) -> 264325.8 | I17: =SUM(I15:I16) -> 278154.25 | J17: =SUM(J15:J16) -> 251876.13 | K17: =SUM(K15:K16) -> 270291.95 | L17: =SUM(L15:L16) -> 271274.86 | M17: =SUM(M15:M16) -> 279078.56
D19: Free Cash Flow | G19: =G17 -> 186827.5 | H19: =H17 -> 264325.8 | I19: =I17 -> 278154.25 | J19: =J17 -> 251876.13 | K19: =K17 -> 270291.95 | L19: =L17 -> 271274.86 | M19: =M17 -> 279078.56
D20: Growth Rate | M20: 0.03
D21: WACC (Given) | M21: 0.093
D22: Terminal Value | M22: =(M19*(1+M20))/(M21-M20) -> 4562713
D23: Discounted Terminal Value | M23: =(M22/(1+M21)^COUNT(G19:M19)) -> 2448398
D24: Present Value of Cash Flows | M24: =NPV(M21,G19:M19) -> 1263832.5
D25: Enterprise Value | M25: =M24+M23 -> 3712230.5
D27: Enterprise Value | M27: =M25 -> 3712230.5
D28: Total Debt | M28: =-M48 -> -526567.73
D29: Cash & Cash Equivalents | M29: ='3-Statement (Downside)'!R73 -> 25000
D30: Net Debt | M30: =M28+M29 -> -501567.73
D31: Minority Interest | M31: =-'3-Statement (Downside)'!R89 -> -12060.464
D32: Implied Equity Value | M32: =M27+M30+M31 -> 3198602.3
D34: Implied Equity Value | M34: =M32 -> 3198602.3
D35: Weighted-Average Shares Outstanding | M35: 55900
D36: Per-Share Value | M36: =M34/M35 -> 57.220078
D38: Net Income | F38: =F13 -> 266918.14
D39: Shares | F39: =$M$35 -> 55900
D40: EPS | F40: =F38/F39 -> 4.7749221
D41: Market Capitalization | F41: =F38*F42 -> 3203017.7
D42: Recessionary PE Hypothesis | F42: 12
D43: Per-Share Value | F43: =F41/F39 -> 57.299065
D44: Average Per-Share Value | F44: =AVERAGE(F43,M36) -> 57.259571
D46: SUMMARY OUTPUTS
E47: =E4 -> Q4-24 | F47: =F4 -> 45657 | G47: =G4 -> 46022 | H47: =H4 -> 46387 | I47: =I4 -> 46752 | J47: =J4 -> 47118 | K47: =K4 -> 47483 | L47: =L4 -> 47848 | M47: =M4 -> 48213
D48: Total Debt | E48: ='3-Statement (Downside)'!J81+'3-Statement (Downside)'!J82+'3-Statement (Downside)'!J83 -> 526832.95 | F48: ='3-Statement (Downside)'!K81+'3-Statement (Downside)'!K82+'3-Statement (Downside)'!K83 -> 526832.95 | G48: ='3-Statement (Downside)'!L81+'3-Statement (Downside)'!L82+'3-Statement (Downside)'!L83 -> 524098.46 | H48: ='3-Statement (Downside)'!M81+'3-Statement (Downside)'!M82+'3-Statement (Downside)'!M83 -> 521820.75 | I48: ='3-Statement (Downside)'!N81+'3-Statement (Downside)'!N82+'3-Statement (Downside)'!N83 -> 507902.3 | J48: ='3-Statement (Downside)'!O81+'3-Statement (Downside)'!O82+'3-Statement (Downside)'!O83 -> 510275.08 | K48: ='3-Statement (Downside)'!P81+'3-Statement (Downside)'!P82+'3-Statement (Downside)'!P83 -> 508623.52 | L48: ='3-Statement (Downside)'!Q81+'3-Statement (Downside)'!Q82+'3-Statement (Downside)'!Q83 -> 522263.44 | M48: ='3-Statement (Downside)'!R81+'3-Statement (Downside)'!R82+'3-Statement (Downside)'!R83 -> 526567.73
D49: Total Capitalization | E49: =E48+E52 -> 1935999.5 | F49: =F48+F52 -> 1935999.5 | G49: =G48+G52 -> 1956836.4 | H49: =H48+H52 -> 1909390.6 | I49: =I48+I52 -> 1874767.7 | J49: =J48+J52 -> 1875449.4 | K49: =K48+K52 -> 1880369.4 | L49: =L48+L52 -> 1904050.5 | M49: =M48+M52 -> 1934753.8
D50: Debt-to-Capital | E50: =E48/E49 -> 0.27212454 | F50: =F48/F49 -> 0.27212454 | G50: =G48/G49 -> 0.26782947 | H50: =H48/H49 -> 0.27329178 | I50: =I48/I49 -> 0.27091479 | J50: =J48/J49 -> 0.27208149 | K50: =K48/K49 -> 0.27049128 | L50: =L48/L49 -> 0.27429075 | M50: =M48/M49 -> 0.27216265
D52: Total Equity | E52: ='3-Statement (Downside)'!J88-'3-Statement (Downside)'!J89 -> 1409166.5 | F52: ='3-Statement (Downside)'!K88-'3-Statement (Downside)'!K89 -> 1409166.5 | G52: ='3-Statement (Downside)'!L88-'3-Statement (Downside)'!L89 -> 1432737.9 | H52: ='3-Statement (Downside)'!M88-'3-Statement (Downside)'!M89 -> 1387569.8 | I52: ='3-Statement (Downside)'!N88-'3-Statement (Downside)'!N89 -> 1366865.4 | J52: ='3-Statement (Downside)'!O88-'3-Statement (Downside)'!O89 -> 1365174.4 | K52: ='3-Statement (Downside)'!P88-'3-Statement (Downside)'!P89 -> 1371745.8 | L52: ='3-Statement (Downside)'!Q88-'3-Statement (Downside)'!Q89 -> 1381787 | M52: ='3-Statement (Downside)'!R88-'3-Statement (Downside)'!R89 -> 1408186.1
D53: Total Capitalization | E53: =E48+E52 -> 1935999.5 | F53: =F48+F52 -> 1935999.5 | G53: =G48+G52 -> 1956836.4 | H53: =H48+H52 -> 1909390.6 | I53: =I48+I52 -> 1874767.7 | J53: =J48+J52 -> 1875449.4 | K53: =K48+K52 -> 1880369.4 | L53: =L48+L52 -> 1904050.5 | M53: =M48+M52 -> 1934753.8
D54: Equity-to-Capital | E54: =E52/E53 -> 0.72787546 | F54: =F52/F53 -> 0.72787546 | G54: =G52/G53 -> 0.73217053 | H54: =H52/H53 -> 0.72670822 | I54: =I52/I53 -> 0.72908521 | J54: =J52/J53 -> 0.72791851 | K54: =K52/K53 -> 0.72950872 | L54: =L52/L53 -> 0.72570925 | M54: =M52/M53 -> 0.72783735
D56: Total Debt | E56: =E48 -> 526832.95 | F56: =F48 -> 526832.95 | G56: =G48 -> 524098.46 | H56: =H48 -> 521820.75 | I56: =I48 -> 507902.3 | J56: =J48 -> 510275.08 | K56: =K48 -> 508623.52 | L56: =L48 -> 522263.44 | M56: =M48 -> 526567.73
D57: EBIT | E57: =E9 -> 96583.254 | F57: =F9 -> 396112.25 | G57: =G9 -> 297457.21 | H57: =H9 -> 306811.64 | I57: =I9 -> 344864.14 | J57: =J9 -> 362435.57 | K57: =K9 -> 395237.37 | L57: =L9 -> 415201.2 | M57: =M9 -> 435420.34
D58: Depreciation & Amortization | E58: ='3-Statement (Downside)'!J99 -> 20499.369 | F58: ='3-Statement (Downside)'!K99 -> 82224.369 | G58: ='3-Statement (Downside)'!L99 -> 74183.921 | H58: ='3-Statement (Downside)'!M99 -> 71112.584 | I58: ='3-Statement (Downside)'!N99 -> 70386.98 | J58: ='3-Statement (Downside)'!O99 -> 72461.865 | K58: ='3-Statement (Downside)'!P99 -> 75699.674 | L58: ='3-Statement (Downside)'!Q99 -> 77747.804 | M58: ='3-Statement (Downside)'!R99 -> 81203.755
D59: Annualized EBITDA | E59: =(E57+E58)*4 -> 468330.49 | F59: =(F57+F58) -> 478336.62 | G59: =(G57+G58) -> 371641.13 | H59: =(H57+H58) -> 377924.23 | I59: =(I57+I58) -> 415251.12 | J59: =(J57+J58) -> 434897.44 | K59: =(K57+K58) -> 470937.04 | L59: =(L57+L58) -> 492949 | M59: =(M57+M58) -> 516624.1
D60: Debt-to-EBITDA | E60: =E56/E59 -> 1.124917 | F60: =F56/F59 -> 1.1013854 | G60: =G56/G59 -> 1.4102273 | H60: =H56/H59 -> 1.3807549 | I60: =I56/I59 -> 1.2231208 | J60: =J56/J59 -> 1.1733228 | K60: =K56/K59 -> 1.0800245 | L60: =L56/L59 -> 1.0594675 | M60: =M56/M59 -> 1.0192473
D62: EBIT | E62: =E57 -> 96583.254 | F62: =F57 -> 396112.25 | G62: =G57 -> 297457.21 | H62: =H57 -> 306811.64 | I62: =I57 -> 344864.14 | J62: =J57 -> 362435.57 | K62: =K57 -> 395237.37 | L62: =L57 -> 415201.2 | M62: =M57 -> 435420.34
D63: Interest Expense | E63: =-'3-Statement (Downside)'!J60 -> 4723.6238 | F63: =-'3-Statement (Downside)'!K60 -> 18790.624 | G63: =-'3-Statement (Downside)'!L60 -> 18747.69 | H63: =-'3-Statement (Downside)'!M60 -> 18589.578 | I63: =-'3-Statement (Downside)'!N60 -> 18430.884 | J63: =-'3-Statement (Downside)'!O60 -> 18332.077 | K63: =-'3-Statement (Downside)'!P60 -> 18153.481 | L63: =-'3-Statement (Downside)'!Q60 -> 17996.658 | M63: =-'3-Statement (Downside)'!R60 -> 17765.012
D64: Interest Coverage | E64: =E62/E63 -> 20.446856 | F64: =F62/F63 -> 21.080314 | G64: =G62/G63 -> 15.866339 | H64: =H62/H63 -> 16.504497 | I64: =I62/I63 -> 18.71121 | J64: =J62/J63 -> 19.770568 | K64: =K62/K63 -> 21.771987 | L64: =L62/L63 -> 23.071017 | M64: =M62/M63 -> 24.509994
D66: EBITDA | E66: =E59/4 -> 117082.62 | F66: =F59 -> 478336.62 | G66: =G59 -> 371641.13 | H66: =H59 -> 377924.23 | I66: =I59 -> 415251.12 | J66: =J59 -> 434897.44 | K66: =K59 -> 470937.04 | L66: =L59 -> 492949 | M66: =M59 -> 516624.1
D67: Interest Expense | E67: =E63 -> 4723.6238 | F67: =F63 -> 18790.624 | G67: =G63 -> 18747.69 | H67: =H63 -> 18589.578 | I67: =I63 -> 18430.884 | J67: =J63 -> 18332.077 | K67: =K63 -> 18153.481 | L67: =L63 -> 17996.658 | M67: =M63 -> 17765.012
D68: Estimated Principal Payment (1%) | E68: ='3-Statement (Downside)'!J83*0.01 -> 2179.6708 | F68: ='3-Statement (Downside)'!K83*0.01 -> 2179.6708 | G68: ='3-Statement (Downside)'!L83*0.01 -> 2158.0899 | H68: ='3-Statement (Downside)'!M83*0.01 -> 2136.7227 | I68: ='3-Statement (Downside)'!N83*0.01 -> 2115.567 | J68: ='3-Statement (Downside)'!O83*0.01 -> 2094.6208 | K68: ='3-Statement (Downside)'!P83*0.01 -> 2073.882 | L68: ='3-Statement (Downside)'!Q83*0.01 -> 2053.3485 | M68: ='3-Statement (Downside)'!R83*0.01 -> 2033.0183
D69: Total Debt Service | E69: =(E67+E68) -> 6903.2946 | F69: =(F67+F68) -> 20970.295 | G69: =(G67+G68) -> 20905.78 | H69: =(H67+H68) -> 20726.301 | I69: =(I67+I68) -> 20546.451 | J69: =(J67+J68) -> 20426.698 | K69: =(K67+K68) -> 20227.363 | L69: =(L67+L68) -> 20050.007 | M69: =(M67+M68) -> 19798.03
D70: Debt Service Coverage Ratio | E70: =E66/E69 -> 16.960398 | F70: =F66/F69 -> 22.8102 | G70: =G66/G69 -> 17.776956 | H70: =H66/H69 -> 18.234041 | I70: =I66/I69 -> 20.210358 | J70: =J66/J69 -> 21.290638 | K70: =K66/K69 -> 23.282176 | L70: =L66/L69 -> 24.585977 | M70: =M66/M69 -> 26.094722
D72: EBITDA | E72: =E66 -> 117082.62 | F72: =F66 -> 478336.62 | G72: =G66 -> 371641.13 | H72: =H66 -> 377924.23 | I72: =I66 -> 415251.12 | J72: =J66 -> 434897.44 | K72: =K66 -> 470937.04 | L72: =L66 -> 492949 | M72: =M66 -> 516624.1
D73: Interest Expense | E73: =E63 -> 4723.6238 | F73: =F63 -> 18790.624 | G73: =G63 -> 18747.69 | H73: =H63 -> 18589.578 | I73: =I63 -> 18430.884 | J73: =J63 -> 18332.077 | K73: =K63 -> 18153.481 | L73: =L63 -> 17996.658 | M73: =M63 -> 17765.012
D74: Other Expense | E74: =-'3-Statement (Downside)'!J59 -> 6260.0937 | F74: =-'3-Statement (Downside)'!K59 -> 25113.094 | G74: =-'3-Statement (Downside)'!L59 -> 19046.128 | H74: =-'3-Statement (Downside)'!M59 -> 18565.403 | I74: =-'3-Statement (Downside)'!N59 -> 19142.344 | J74: =-'3-Statement (Downside)'!O59 -> 20035.49 | K74: =-'3-Statement (Downside)'!P59 -> 20794.913 | L74: =-'3-Statement (Downside)'!Q59 -> 20850.008 | M74: =-'3-Statement (Downside)'!R59 -> 21964.514
D75: Fixed Charges | E75: =SUM(E73:E74) -> 10983.717 | F75: =SUM(F73:F74) -> 43903.717 | G75: =SUM(G73:G74) -> 37793.818 | H75: =SUM(H73:H74) -> 37154.982 | I75: =SUM(I73:I74) -> 37573.228 | J75: =SUM(J73:J74) -> 38367.567 | K75: =SUM(K73:K74) -> 38948.395 | L75: =SUM(L73:L74) -> 38846.666 | M75: =SUM(M73:M74) -> 39729.526
D76: Fixed Charge Coverage Ratio | E76: =(E72+E75)/E75 -> 11.659654 | F76: =(F72+F75)/F75 -> 11.895128 | G76: =(G72+G75)/G75 -> 10.833384 | H76: =(H72+H75)/H75 -> 11.171563 | I76: =(I72+I75)/I75 -> 12.051782 | J76: =(J72+J75)/J75 -> 12.335028 | K76: =(K72+K75)/K75 -> 13.091308 | L76: =(L72+L75)/L75 -> 13.689609 | M76: =(M72+M75)/M75 -> 14.00353
D78: Current Assets | E78: ='Balance Sheet NWC (Downside)'!J11 -> 1262501.9 | F78: ='Balance Sheet NWC (Downside)'!K11 -> 1262501.9 | G78: ='Balance Sheet NWC (Downside)'!L11 -> 1363429.1 | H78: ='Balance Sheet NWC (Downside)'!M11 -> 1391074.3 | I78: ='Balance Sheet NWC (Downside)'!N11 -> 1416170.8 | J78: ='Balance Sheet NWC (Downside)'!O11 -> 1433881.3 | K78: ='Balance Sheet NWC (Downside)'!P11 -> 1485309.5 | L78: ='Balance Sheet NWC (Downside)'!Q11 -> 1542082.6 | M78: ='Balance Sheet NWC (Downside)'!R11 -> 1610837.3
D79: Current Liabilities | E79: ='Balance Sheet NWC (Downside)'!J24 -> 599585.82 | F79: ='Balance Sheet NWC (Downside)'!K24 -> 599585.82 | G79: ='Balance Sheet NWC (Downside)'!L24 -> 631658.24 | H79: ='Balance Sheet NWC (Downside)'!M24 -> 640443.28 | I79: ='Balance Sheet NWC (Downside)'!N24 -> 648418.41 | J79: ='Balance Sheet NWC (Downside)'!O24 -> 654046.41 | K79: ='Balance Sheet NWC (Downside)'!P24 -> 670389.16 | L79: ='Balance Sheet NWC (Downside)'!Q24 -> 688430.39 | M79: ='Balance Sheet NWC (Downside)'!R24 -> 710279.11
D80: Current Ratio | E80: =E78/E79 -> 2.1056234 | F80: =F78/F79 -> 2.1056234 | G80: =G78/G79 -> 2.1584917 | H80: =H78/H79 -> 2.1720491 | I80: =I78/I79 -> 2.1840386 | J80: =J78/J79 -> 2.1923235 | K80: =K78/K79 -> 2.215593 | L80: =L78/L79 -> 2.2399978 | M80: =M78/M79 -> 2.2678933
D82: Current Assets | E82: =E78 -> 1262501.9 | F82: =F78 -> 1262501.9 | G82: =G78 -> 1363429.1 | H82: =H78 -> 1391074.3 | I82: =I78 -> 1416170.8 | J82: =J78 -> 1433881.3 | K82: =K78 -> 1485309.5 | L82: =L78 -> 1542082.6 | M82: =M78 -> 1610837.3
D83: Inventory & Other | E83: =-'Balance Sheet NWC (Downside)'!J9-'Balance Sheet NWC (Downside)'!J10 -> -799801.25 | F83: =-'Balance Sheet NWC (Downside)'!K9-'Balance Sheet NWC (Downside)'!K10 -> -799801.25 | G83: =-'Balance Sheet NWC (Downside)'!L9-'Balance Sheet NWC (Downside)'!L10 -> -865030.76 | H83: =-'Balance Sheet NWC (Downside)'!M9-'Balance Sheet NWC (Downside)'!M10 -> -882897.95 | I83: =-'Balance Sheet NWC (Downside)'!N9-'Balance Sheet NWC (Downside)'!N10 -> -899117.93 | J83: =-'Balance Sheet NWC (Downside)'!O9-'Balance Sheet NWC (Downside)'!O10 -> -910564.26 | K83: =-'Balance Sheet NWC (Downside)'!P9-'Balance Sheet NWC (Downside)'!P10 -> -943802.48 | L83: =-'Balance Sheet NWC (Downside)'!Q9-'Balance Sheet NWC (Downside)'!Q10 -> -980495.08 | M83: =-'Balance Sheet NWC (Downside)'!R9-'Balance Sheet NWC (Downside)'!R10 -> -1024931.4
D84: Net Current Assets | E84: =E82+E83 -> 462700.67 | F84: =F82+F83 -> 462700.67 | G84: =G82+G83 -> 498398.29 | H84: =H82+H83 -> 508176.32 | I84: =I82+I83 -> 517052.9 | J84: =J82+J83 -> 523317.04 | K84: =K82+K83 -> 541507.05 | L84: =L82+L83 -> 561587.5 | M84: =M82+M83 -> 585905.83
D85: Current Liabilities | E85: =E79 -> 599585.82 | F85: =F79 -> 599585.82 | G85: =G79 -> 631658.24 | H85: =H79 -> 640443.28 | I85: =I79 -> 648418.41 | J85: =J79 -> 654046.41 | K85: =K79 -> 670389.16 | L85: =L79 -> 688430.39 | M85: =M79 -> 710279.11
D86: Quick Ratio | E86: =E84/E85 -> 0.77170049 | F86: =F84/F85 -> 0.77170049 | G86: =G84/G85 -> 0.78903157 | H86: =H84/H85 -> 0.79347593 | I86: =I84/I85 -> 0.79740626 | J86: =J84/J85 -> 0.80012218 | K86: =K84/K85 -> 0.8077503 | L86: =L84/L85 -> 0.8157506 | M86: =M84/M85 -> 0.8248952

Sheet 3-Statement (Downside)
C1: ACTUALS | D1: ACTUALS | E1: ACTUALS | F1: ACTUALS | G1: ACTUALS | H1: ACTUALS | I1: ACTUALS | J1: FORECAST | K1: FORECAST | L1: FORECAST | M1: FORECAST | N1: FORECAST | O1: FORECAST | P1: FORECAST | Q1: FORECAST | R1: FORECAST
B2: Drivers: | C2: 44196 | D2: =EOMONTH(C2,12) -> 44561 | E2: =EOMONTH(D2,12) -> 44926 | F2: =EOMONTH(E2,12) -> 45291 | G2: Q1-24 | H2: Q2-24 | I2: Q3-24 | J2: Q4-24 | K2: =EOMONTH(F2,12) -> 45657 | L2: =EOMONTH(K2,12) -> 46022 | M2: =EOMONTH(L2,12) -> 46387 | N2: =EOMONTH(M2,12) -> 46752 | O2: =EOMONTH(N2,12) -> 47118 | P2: =EOMONTH(O2,12) -> 47483 | Q2: =EOMONTH(P2,12) -> 47848 | R2: =EOMONTH(Q2,12) -> 48213
B4: Market Size:
B5: Growth Rate:
B7: Market Share %:
B9: Revenue | C9: =C48 -> 3192399 | D9: =D48 -> 3243224 | E9: =E48 -> 3691893 | F9: =F48 -> 4009282 | G9: =G48 -> 953969 | H9: =H48 -> 935348 | I9: =I48 -> 979350 | J9: =K9-I9-H9-G9 -> 952178.75 | K9: =F9*(1+K10) -> 3820845.7 | L9: =K9*(1+L10) -> 3629803.5 | M9: =L9*(1+M10) -> 3520909.4 | N9: =M9*(1+N10) -> 3520909.4 | O9: =N9*(1+O10) -> 3591327.5 | P9: =O9*(1+P10) -> 3699067.4 | Q9: =P9*(1+Q10) -> 3838744.2 | R9: =Q9*(1+R10) -> 4016677.6
B10: Growth Rate: | D10: =D9/C9-1 -> 0.015920629 | E10: =E9/D9-1 -> 0.13834043 | F10: =F9/E9-1 -> 0.085969176 | H10: =H9/G9-1 -> -0.019519502 | I10: =I9/H9-1 -> 0.047043453 | J10: =J9/I9-1 -> -0.027744171 | K10: -0.047 | L10: -0.05 | M10: -0.03 | N10: 0 | O10: 0.02 | P10: 0.03 | Q10: ='3-Statement (Base)'!Q10 -> 0.03776 | R10: ='3-Statement (Base)'!R10 -> 0.046352
B12: Recessionary COGS Adj | L12: 0.01 | M12: 0.008 | N12: 0.005 | O12: 0.003
B13: COGS % Revenue: | C13: =-C51/C48 -> 0.57921237 | D13: =-D51/D48 -> 0.58883044 | E13: =-E51/E48 -> 0.5779271 | F13: =-F51/F48 -> 0.59020967 | G13: =-G51/G48 -> 0.58791428 | H13: =-H51/H48 -> 0.5845279 | I13: =-I51/I48 -> 0.59110941 | J13: =AVERAGE(G13:I13) -> 0.58785053 | K13: =-K51/K48 -> 0.58788837 | L13: ='3-Statement (Base)'!L12+L12 -> 0.59481359 | M13: ='3-Statement (Base)'!M12+M12 -> 0.59393383 | N13: ='3-Statement (Base)'!N12+N12 -> 0.59035451 | O13: ='3-Statement (Base)'!O12+O12 -> 0.58983999 | P13: ='3-Statement (Base)'!P12+P12 -> 0.58616606 | Q13: ='3-Statement (Base)'!Q12+Q12 -> 0.5858216 | R13: ='3-Statement (Base)'!R12+R12 -> 0.5860232
B14: Recessionary OpEx Adj | L14: 0.015 | M14: 0.012 | N14: 0.008 | O14: 0.005
B15: OpEx % Revenue: | C15: =-C52/C49 -> 0.30558618 | D15: =-D52/D49 -> 0.30662945 | E15: =-E52/E49 -> 0.29357893 | F15: =-F52/F49 -> 0.2871574 | G15: =-G52/G49 -> 0.30465665 | H15: =-H52/H49 -> 0.3113654 | I15: =-I52/I49 -> 0.29508449 | J15: =AVERAGE(G15:I15) -> 0.30370218 | K15: =-K52/K49 -> 0.30360759 | L15: ='3-Statement (Base)'!L13+L14 -> 0.31431191 | M15: ='3-Statement (Base)'!M13+M14 -> 0.31005706 | N15: ='3-Statement (Base)'!N13+N14 -> 0.30434258 | O15: ='3-Statement (Base)'!O13+O14 -> 0.30189531 | P15: ='3-Statement (Base)'!P13+P14 -> 0.29884289 | Q15: ='3-Statement (Base)'!Q13+Q14 -> 0.29788995 | R15: ='3-Statement (Base)'!R13+R14 -> 0.29760556
B16: Impairment % Revenue: | C16: =-C53/C48 -> 0 | D16: =-D53/D48 -> 0.0018148608 | E16: =-E53/E48 -> 0 | F16: =-F53/F48 -> 0 | G16: =-G53/G48 -> 0 | H16: =-H53/H48 -> 0 | I16: =-I53/I48 -> 0 | J16: =AVERAGE(G16:I16) -> 0 | K16: =-K53/K48 -> 0 | L16: =AVERAGE(C16:F16,K16) -> 0.00036297215 | M16: =AVERAGE(K16:L16,D16:F16) -> 0.00043556658 | N16: =AVERAGE(K16:M16,E16:F16) -> 0.00015970775 | O16: =AVERAGE(K16:N16,F16) -> 0.0001916493 | P16: =AVERAGE(K16:O16) -> 0.00022997916 | Q16: =AVERAGE(L16:P16) -> 0.00027597499 | R16: =AVERAGE(M16:Q16) -> 0.00025857555
B17: Restructuring % of Revenue: | C17: =C54/C51 -> 0.0092094596 | D17: =D54/D51 -> 0.016438107 | E17: =E54/E51 -> 0.0074075116 | F17: =F54/F51 -> 0.0033541575 | G17: =G54/G51 -> 0.0016332294 | H17: =H54/H51 -> 0.011305253 | I17: =I54/I51 -> 0.00810153 | J17: =AVERAGE(G17:I17) -> 0.0070133374 | K17: =K54/K51 -> 0.0082204157 | L17: =AVERAGE(C17:F17,K17) -> 0.0089259302 | M17: =AVERAGE(K17:L17,D17:F17) -> 0.0088692243 | N17: =AVERAGE(K17:M17,E17:F17) -> 0.0073554479 | O17: =AVERAGE(K17:N17,F17) -> 0.0073450351 | P17: =AVERAGE(K17:O17) -> 0.0081432106 | Q17: =AVERAGE(L17:P17) -> 0.0081277696 | R17: =AVERAGE(M17:Q17) -> 0.0079681375
B18: Gain on Sale % Revenue: | C18: =-C55/C48 -> 0 | D18: =-D55/D48 -> 0 | E18: =-E55/E48 -> -0.0027443916 | F18: =-F55/F48 -> 0 | G18: =-G55/G48 -> 0 | H18: =-H55/H48 -> 0 | I18: =-I55/I48 -> 0 | J18: =AVERAGE(G18:I18) -> 0 | K18: =-K55/K48 -> 0 | L18: =AVERAGE(C18:F18,K18) -> -0.00054887831 | M18: =AVERAGE(K18:L18,D18:F18) -> -0.00065865398 | N18: =AVERAGE(K18:M18,E18:F18) -> -0.00079038477 | O18: =AVERAGE(K18:N18,F18) -> -0.00039958341 | P18: =AVERAGE(K18:O18) -> -0.00047950009 | Q18: =AVERAGE(L18:P18) -> -0.00057540011 | R18: =AVERAGE(M18:Q18) -> -0.00058070447
B19: Other Income % Revenue: | C19: =C59/C48 -> -0.0051184078 | D19: =D59/D48 -> -0.0044535931 | E19: =E59/E48 -> -0.0047263017 | F19: =F59/F48 -> -0.005364801 | G19: =G59/G48 -> -0.0054456696 | H19: =H59/H48 -> -0.0073854865 | I19: =I59/I48 -> -0.0068923265 | J19: =AVERAGE(G19:I19) -> -0.0065744942 | K19: =K59/K48 -> -0.0065726531 | L19: =AVERAGE(C19:F19,K19) -> -0.0052471513 | M19: =AVERAGE(K19:L19,D19:F19) -> -0.0052729 | N19: =AVERAGE(K19:M19,E19:F19) -> -0.0054367614 | O19: =AVERAGE(K19:N19,F19) -> -0.0055788534 | P19: =AVERAGE(K19:O19) -> -0.0056216639 | Q19: =AVERAGE(L19:P19) -> -0.005431466 | R19: =AVERAGE(M19:Q19) -> -0.0054683289
B20: Tax Rate: | C20: =-C63/C61 -> 0.24679731 | D20: =-D63/D61 -> 0.24426883 | E20: =-E63/E61 -> 0.24527189 | F20: =-F63/F61 -> 0.24782969 | G20: =-G63/G61 -> 0.242997 | H20: =-H63/H61 -> 0.23000438 | I20: =-I63/I61 -> 0.25199295 | J20: =AVERAGE(G20:I20) -> 0.24166478 | K20: =-K63/K61 -> 0.24215879 | L20: =AVERAGE(C20:F20,K20) -> 0.2452653 | M20: =AVERAGE(K20:L20,D20:F20) -> 0.2449589 | N20: =AVERAGE(K20:M20,E20:F20) -> 0.24509691 | O20: =AVERAGE(K20:N20,F20) -> 0.24506192 | P20: =AVERAGE(K20:O20) -> 0.24450837 | Q20: =AVERAGE(L20:P20) -> 0.24497828 | R20: =AVERAGE(M20:Q20) -> 0.24492088
B21: NCI Net Income % Total: | C21: =C66/C65 -> 0.0025460959 | D21: =D66/D65 -> 0.0047261365 | E21: =E66/E65 -> 0.0020441609 | F21: =F66/F65 -> -0.00036723238 | G21: =G66/G65 -> -0.0032114339 | H21: =H66/H65 -> -0.0045805246 | I21: =I66/I65 -> -0.0055109939 | J21: =AVERAGE(G21:I21) -> -0.0044343175 | K21: =K66/K65 -> -0.0044389844 | L21: =AVERAGE(C21:F21,K21) -> 0.00090203528 | M21: =AVERAGE(K21:L21,D21:F21) -> 0.00057322317 | N21: =AVERAGE(K21:M21,E21:F21) -> -0.00025735949 | O21: =AVERAGE(K21:N21,F21) -> -0.00071766357 | P21: =AVERAGE(K21:O21) -> -0.00078774981 | Q21: =AVERAGE(L21:P21) -> -5.7502886e-05 | R21: =AVERAGE(M21:Q21) -> -0.00024941052
B23: Recessionary NWC Adj | L23: 0.024 | M23: 0.018 | N23: 0.006 | O23: 0.003 | P23: 0 | Q23: 0 | R23: 0
B24: NWC % Revenue: | C24: =C74/C49 -> 0.25876277 | D24: =D74/D49 -> 0.28188432 | E24: =E74/E49 -> 0.29790192 | F24: =F74/F49 -> 0.21149922 | G24: =G74/G49/4 -> 0.22572825 | H24: =H74/H49/4 -> 0.23255649 | I24: =I74/I49/4 -> 0.20670419 | J24: =AVERAGE(G24:I24) -> 0.22166298 | K24: =K74/K49 -> 0.22095922 | L24: ='3-Statement (Base)'!L21+L23 -> 0.24022922 | M24: ='3-Statement (Base)'!M21+M23 -> 0.23422922 | N24: ='3-Statement (Base)'!N21+N23 -> 0.22380589 | O24: ='3-Statement (Base)'!O21+O23 -> 0.21975477 | P24: ='3-Statement (Base)'!P21+P23 -> 0.21692996 | Q24: ='3-Statement (Base)'!Q21+Q23 -> 0.21716354 | R24: ='3-Statement (Base)'!R21+R23 -> 0.21694942
B25: Recessionary CapEx Adj | L25: -0.003 | M25: -0.002 | N25: -0.001 | O25: -0.001
B26: CapEx % Revenue: | C26: =-C106/C49 -> 0.014719651 | D26: =-D106/D49 -> 0.016571782 | E26: =-E106/E49 -> 0.016623721 | F26: =-F106/F49 -> 0.023069717 | G26: =-G106/G49 -> 0.019322431 | H26: =-H106/H49 -> 0.027102212 | I26: =-I106/I49 -> 0.030194517 | J26: =AVERAGE(G26:I26) -> 0.02553972 | K26: =-K106/K49 -> 0.025563026 | L26: ='3-Statement (Base)'!L22+L25 -> 0.016309579 | M26: ='3-Statement (Base)'!M22+M25 -> 0.018227565 | N26: ='3-Statement (Base)'!N22+N25 -> 0.019958722 | O26: ='3-Statement (Base)'!O22+O25 -> 0.020825722 | P26: ='3-Statement (Base)'!P22+P25 -> 0.021576923 | Q26: ='3-Statement (Base)'!Q22+Q25 -> 0.020779702 | R26: ='3-Statement (Base)'!R22+R25 -> 0.021073727
B27: D&A % Revenue: | C27: =C99/C49 -> 0.021638586 | D27: =D99/D49 -> 0.021227643 | E27: =E99/E49 -> 0.019062308 | F27: =F99/F49 -> 0.018738767 | G27: =G99/G49 -> 0.020736523 | H27: =H99/H49 -> 0.022764789 | I27: =I99/I49 -> 0.021085414 | J27: =AVERAGE(G27:I27) -> 0.021528909 | K27: =K99/K49 -> 0.021519939 | L27: =AVERAGE(C27:F27,K27) -> 0.020437448 | M27: =AVERAGE(K27:L27,D27:F27) -> 0.020197221 | N27: =AVERAGE(K27:M27,E27:F27) -> 0.019991137 | O27: =AVERAGE(K27:N27,F27) -> 0.020176902 | P27: =AVERAGE(K27:O27) -> 0.02046453 | Q27: =AVERAGE(L27:P27) -> 0.020253448 | R27: =AVERAGE(M27:Q27) -> 0.020216647
B28: Recessionary Other Adj | L28: -0.004 | M28: -0.004 | N28: -0.003 | O28: -0.002
B29: Other Items % Revenue: | C29: =C100/C49 -> 0.011421191 | D29: =D100/D49 -> 0.0039633402 | E29: =E100/E49 -> 0.0080557589 | F29: =F100/F49 -> 0.0090470064 | G29: =G100/G49 -> 0.005879646 | H29: =H100/H49 -> 0.0010830194 | I29: =I100/I49 -> -0.005415837 | J29: =AVERAGE(G29:I29) -> 0.00051560944 | K29: =K100/K49 -> 0.00047344292 | L29: ='3-Statement (Base)'!L25+L28 -> 0.00099204277 | M29: ='3-Statement (Base)'!M25+M28 -> 0.0018472361 | N29: ='3-Statement (Base)'!N25+N28 -> 0.0026600087 | O29: ='3-Statement (Base)'!O25+O28 -> 0.0029978089 | P29: ='3-Statement (Base)'!P25+P28 -> 0.0049906068 | Q29: ='3-Statement (Base)'!Q25+Q28 -> 0.0052975407 | R29: ='3-Statement (Base)'!R25+R28 -> 0.0053586402
B30: Acquisitions & Other % Revenue: | C30: =-C107/C48 -> 0.0007160759 | D30: =-D107/D48 -> 0.0067833736 | E30: =-E107/E48 -> 0.0089710076 | F30: =-F107/F48 -> 0.005033819 | G30: =-G107/G48 -> 0 | H30: =-H107/H48 -> 0.010550084 | I30: =-I107/I48 -> -9.1897687e-06 | J30: =AVERAGE(G30:I30) -> 0.0035136314 | K30: =K60/K49 -> -0.0049179226 | L30: =AVERAGE(C30:F30,K30) -> 0.0033172707 | M30: =AVERAGE(K30:L30,D30:F30) -> 0.0038375096 | N30: =AVERAGE(K30:M30,E30:F30) -> 0.0032483369 | O30: =AVERAGE(K30:N30,F30) -> 0.0021038027 | P30: =AVERAGE(K30:O30) -> 0.0015177995 | Q30: =AVERAGE(L30:P30) -> 0.0028049439 | R30: =AVERAGE(M30:Q30) -> 0.0027024785
B32: Dividends % Net Income: | C32: =-C113/C67 -> 0.6598164 | D32: =-D113/D67 -> 0.7640375 | E32: =-E113/E67 -> 0.49058263 | F32: =-F113/F67 -> 0.51523262 | G32: =-G113/G67 -> 0.68487505 | H32: =-H113/H67 -> 0.76321329 | I32: =-I113/I67 -> 0.65893484 | J32: =AVERAGE(G32:I32) -> 0.70234106 | K32: =-K113/K67 -> 0.70026602 | L32: ='3-Statement (Base)'!L27 -> 0.62720016 | M32: ='3-Statement (Base)'!M27 -> 0.62000322 | N32: ='3-Statement (Base)'!N27 -> 0.58974512 | O32: ='3-Statement (Base)'!O27 -> 0.60917567 | P32: ='3-Statement (Base)'!P27 -> 0.62803993 | Q32: ='3-Statement (Base)'!Q27 -> 0.61483282 | R32: ='3-Statement (Base)'!R27 -> 0.61235935
B33: Stock Repurchases % Net Income: | C33: =-C114/C67 -> 0.013645062 | D33: =-D114/D67 -> 0.32544173 | E33: =-E114/E67 -> 0.080189813 | F33: =-F114/F67 -> 0.27925454 | G33: =-G114/G67 -> 1.9163063 | H33: =-H114/H67 -> 0.27139664 | I33: =-I114/I67 -> 0.26070588 | J33: 0 | K33: =-K114/K67 -> 0.62907434 | L33: 0.25 | M33: 0.6 | N33: 0.5 | O33: 0.4 | P33: 0.35 | Q33: 0.35 | R33: 0.3 | S33: Set to maintain capital structure
B34: Other Items % Debt Issuances: | C34: =C116/(C112+C111) -> 0.10910804 | D34: =D116/(D112+D111) -> 0.20243173 | E34: =E116/(E112+E111) -> 5.6242536 | F34: =F116/(F112+F111) -> -0.10019784 | G34: =G116/(G112+G111) -> 0.087705615 | H34: =H116/(H112+H111) -> 0.14705469 | I34: =I116/(I112+I111) -> -0.00048888889 | J34: =AVERAGE(G34:I34) -> 0.078090472 | K34: =K116/(K112+K111) -> 0.12793826 | L34: =K34 -> 0.12793826 | M34: =L34 -> 0.12793826 | N34: =M34 -> 0.12793826 | O34: =N34 -> 0.12793826 | P34: =O34 -> 0.12793826 | Q34: =P34 -> 0.12793826 | R34: =Q34 -> 0.12793826
B36: Total Cash Flow Before Revolver | J36: =I73+J103+J108+SUM(J112:J116)+J119 -> 3769.1284 | K36: =J73+K103+K108+SUM(K112:K116)+K119 -> -62282.872 | L36: =K73+L103+L108+SUM(L112:L116)+L119 -> 25576.399 | M36: =L73+M103+M108+SUM(M112:M116)+M119 -> 25140.996 | N36: =M73+N103+N108+SUM(N112:N116)+N119 -> 36802.88 | O36: =N73+O103+O108+SUM(O112:O116)+O119 -> 20532.594 | P36: =O73+P103+P108+SUM(P112:P116)+P119 -> 24577.682 | Q36: =P73+Q103+Q108+SUM(Q112:Q116)+Q119 -> 9306.7277 | R36: =Q73+R103+R108+SUM(R112:R116)+R119 -> 18662.695
B37: Revolver Borrowing to Zero | J37: =-MIN(J36,I81) -> -3769.1284 | K37: =-MIN(K36,J81) -> 62282.872 | L37: =-MIN(L36,K81) -> -25576.399 | M37: =-MIN(M36,L81) -> -25140.996 | N37: =-MIN(N36,M81) -> -36802.88 | O37: =-MIN(O36,N81) -> -20532.594 | P37: =-MIN(P36,O81) -> -24577.682 | Q37: =-MIN(Q36,P81) -> -9306.7277 | R37: =-MIN(R36,Q81) -> -18662.695
B38: 25k Minimum Cash Balance | J38: 25000 | K38: 25000 | L38: 25000 | M38: 25000 | N38: 25000 | O38: 25000 | P38: 25000 | Q38: 25000 | R38: 25000 | S38: Estimate based on historicals
B39: Total Revolver Borrowing Needed | J39: =SUM(J37:J38) -> 21230.872 | K39: =SUM(K37:K38) -> 87282.872 | L39: =SUM(L37:L38) -> -576.39925 | M39: =SUM(M37:M38) -> -140.99577 | N39: =SUM(N37:N38) -> -11802.88 | O39: =SUM(O37:O38) -> 4467.4064 | P39: =SUM(P37:P38) -> 422.31766 | Q39: =SUM(Q37:Q38) -> 15693.272 | R39: =SUM(R37:R38) -> 6337.3053
B41: Revolver Maximum Balance | I41: 600000 | J41: 600000 | K41: 600000 | L41: 600000 | M41: 600000 | N41: 600000 | O41: 600000 | P41: 600000 | Q41: 600000 | R41: 600000
B42: Revolver Utilization | I42: =I81 -> 81300 | J42: =J81 -> 102530.87 | K42: =K81 -> 102530.87 | L42: =L81 -> 101954.47 | M42: =M81 -> 101813.48 | N42: =N81 -> 90010.596 | O42: =O81 -> 94478.003 | P42: =P81 -> 94900.321 | ... R42: =R81 -> 116930.9
B43: Net Revolver Balance | I43: =I41-I42 -> 518700 | J43: =J41-J42 -> 497469.13 | K43: =K41-K42 -> 497469.13 | L43: =L41-L42 -> 498045.53 | M43: =M41-M42 -> 498186.52 | N43: =N41-N42 -> 509989.4 | O43: =O41-O42 -> 505522 | P43: =P41-P42 -> 505099.68 | ... R43: =R41-R42 -> 483069.1
B44: 50 Bps on Unutilized Revolver | I44: =I43*0.005 -> 2593.5 | J44: =J43*0.005 -> 2487.3456 | K44: =K43*0.005 -> 2487.3456 | L44: =L43*0.005 -> 2490.2276 | M44: =M43*0.005 -> 2490.9326 | N44: =N43*0.005 -> 2549.947 | O44: =O43*0.005 -> 2527.61 | P44: =P43*0.005 -> 2525.4984 | ... R44: =R43*0.005 -> 2415.3455
B46: Income Statement: | C46: =C$2 -> 44196 | D46: =D$2 -> 44561 | E46: =E$2 -> 44926 | F46: =F$2 -> 45291 | G46: =G$2 -> Q1-24 | H46: =H$2 -> Q2-24 | I46: =I$2 -> Q3-24 | J46: =J$2 -> Q4-24 | ... R46: =R$2 -> 48213
B48: Revenue: | C48: ='Income Statement'!C6 -> 3192399 | D48: ='Income Statement'!D6 -> 3243224 | E48: ='Income Statement'!E6 -> 3691893 | F48: ='Income Statement'!F6 -> 4009282 | G48: ='Income Statement'!G6 -> 953969 | H48: ='Income Statement'!H6 -> 935348 | I48: ='Income Statement'!I6 -> 979350 | J48: =J9 -> 952178.75 | K48: =SUM(G48:J48) -> 3820845.7 | L48: =L9 -> 3629803.5 | M48: =M9 -> 3520909.4 | N48: =N9 -> 3520909.4 | O48: =O9 -> 3591327.5 | P48: =P9 -> 3699067.4 | Q48: =Q9 -> 3838744.2 | R48: =R9 -> 4016677.6
B49: Total Revenue: | C49: =SUM(C48:C48) -> 3192399 | D49: =SUM(D48:D48) -> 3243224 | E49: =SUM(E48:E48) -> 3691893 | F49: =SUM(F48:F48) -> 4009282 | G49: =SUM(G48:G48) -> 953969 | H49: =SUM(H48:H48) -> 935348 | I49: =SUM(I48:I48) -> 979350 | J49: =SUM(J48:J48) -> 952178.75 | ... R49: =SUM(R48:R48) -> 4016677.6
B51: Cost of Sales: | C51: =-'Income Statement'!C7 -> -1849077 | D51: =-'Income Statement'!D7 -> -1909709 | E51: =-'Income Statement'!E7 -> -2133645 | F51: =-'Income Statement'!F7 -> -2366317 | G51: =-'Income Statement'!G7 -> -560852 | H51: =-'Income Statement'!H7 -> -546737 | I51: =-'Income Statement'!I7 -> -578903 | J51: =-J$48*J13 -> -559738.78 | K51: =SUM(G51:J51) -> -2246230.8 | L51: =-L$48*L13 -> -2159056.4 | M51: =-M$48*M13 -> -2091187.2 | N51: =-N$48*N13 -> -2078584.7 | O51: =-O$48*O13 -> -2118308.6 | P51: =-P$48*P13 -> -2168267.7 | Q51: =-Q$48*Q13 -> -2248819.2 | R51: =-R$48*R13 -> -2353866.3
B52: Operating Expenses: | C52: =-'Income Statement'!C11 -> -975553 | D52: =-'Income Statement'!D11 -> -994468 | E52: =-'Income Statement'!E11 -> -1083862 | F52: =-'Income Statement'!F11 -> -1151295 | G52: =-'Income Statement'!G11 -> -290633 | H52: =-'Income Statement'!H11 -> -291235 | I52: =-'Income Statement'!I11 -> -288991 | J52: =-J$48*J15 -> -289178.76 | K52: =SUM(G52:J52) -> -1160037.8 | L52: =-L$48*L15 -> -1140890.5 | M52: =-M$48*M15 -> -1091682.8 | N52: =-N$48*N15 -> -1071562.6 | O52: =-O$48*O15 -> -1084204.9 | P52: =-P$48*P15 -> -1105440 | Q52: =-Q$48*Q15 -> -1143523.3 | R52: =-R$48*R15 -> -1195385.6
B53: Impairment Loss: | C53: =-'Income Statement'!C12 -> 0 | D53: =-'Income Statement'!D12 -> -5886 | E53: =-'Income Statement'!E12 -> 0 | F53: =-'Income Statement'!F12 -> 0 | G53: =-'Income Statement'!G12 -> 0 | H53: =-'Income Statement'!H12 -> 0 | I53: =-'Income Statement'!I12 -> 0 | J53: =-J$48*J16 -> 0 | K53: =SUM(G53:J53) -> 0 | L53: =K53 -> 0 | M53: =L53 -> 0 | N53: =M53 -> 0 | O53: =N53 -> 0 | P53: =O53 -> 0 | Q53: =P53 -> 0 | R53: =Q53 -> 0
B54: Restructuring Costs: | C54: =-'Income Statement'!C13 -> -17029 | D54: =-'Income Statement'!D13 -> -31392 | E54: =-'Income Statement'!E13 -> -15805 | F54: =-'Income Statement'!F13 -> -7937 | G54: =-'Income Statement'!G13 -> -916 | H54: =-'Income Statement'!H13 -> -6181 | I54: =-'Income Statement'!I13 -> -4690 | J54: =-J$48*J17 -> -6677.9508 | K54: =SUM(G54:J54) -> -18464.951 | L54: =-L$48*L17 -> -32399.372 | M54: =-M$48*M17 -> -31227.735 | N54: =-N$48*N17 -> -25897.865 | O54: =-O$48*O17 -> -26378.427 | P54: =-P$48*P17 -> -30122.285 | Q54: =-Q$48*Q17 -> -31200.428 | R54: =-R$48*R17 -> -32005.44
B55: Gain on Sale of Property: | C55: =-'Income Statement'!C14 -> 0 | D55: =-'Income Statement'!D14 -> 0 | E55: =-'Income Statement'!E14 -> 10132 | F55: =-'Income Statement'!F14 -> 0 | G55: =-'Income Statement'!G14 -> 0 | H55: =-'Income Statement'!H14 -> 0 | I55: =-'Income Statement'!I14 -> 0 | J55: =-J$48*J18 -> 0 | K55: =SUM(G55:J55) -> 0 | L55: =K55 -> 0 | M55: =L55 -> 0 | N55: =M55 -> 0 | O55: =N55 -> 0 | P55: =O55 -> 0 | Q55: =P55 -> 0 | R55: =Q55 -> 0
B56: Operating Income: | C56: =C49+SUM(C51:C55) -> 350740 | D56: =D49+SUM(D51:D55) -> 301769 | E56: =E49+SUM(E51:E55) -> 468713 | F56: =F49+SUM(F51:F55) -> 483733 | G56: =G49+SUM(G51:G55) -> 101568 | H56: =H49+SUM(H51:H55) -> 91195 | I56: =I49+SUM(I51:I55) -> 106766 | J56: =J49+SUM(J51:J55) -> 96583.254 | ... R56: =R49+SUM(R51:R55) -> 435420.34
B57: Margin Percentage | C57: =(SUM(C49:C51)/C49) -> 0.42078763 | D57: =(SUM(D49:D51)/D49) -> 0.41116956 | E57: =(SUM(E49:E51)/E49) -> 0.4220729 | F57: =(SUM(F49:F51)/F49) -> 0.40979033 | G57: =(SUM(G49:G51)/G49) -> 0.41208572 | H57: =(SUM(H49:H51)/H49) -> 0.4154721 | I57: =(SUM(I49:I51)/I49) -> 0.40889059 | J57: =(SUM(J49:J51)/J49) -> 0.41214947 | ... R57: =(SUM(R49:R51)/R49) -> 0.4139768
B59: Other Income / (Expense): | C59: ='Income Statement'!C19+'Income Statement'!C20 -> -16340 | D59: ='Income Statement'!D19+'Income Statement'!D20 -> -14444 | E59: ='Income Statement'!E19+'Income Statement'!E20 -> -17449 | F59: ='Income Statement'!F19+'Income Statement'!F20 -> -21509 | G59: ='Income Statement'!G19+'Income Statement'!G20 -> -5195 | H59: ='Income Statement'!H19+'Income Statement'!H20 -> -6908 | I59: ='Income Statement'!I19+'Income Statement'!I20 -> -6750 | J59: =J$48*J19 -> -6260.0937 | K59: =SUM(G59:J59) -> -25113.094 | L59: =L$48*L19 -> -19046.128 | M59: =M$48*M19 -> -18565.403 | N59: =N$48*N19 -> -19142.344 | O59: =O$48*O19 -> -20035.49 | P59: =P$48*P19 -> -20794.913 | Q59: =Q$48*Q19 -> -20850.008 | R59: =R$48*R19 -> -21964.514
B60: Interest Income / (Expense): | C60: ='Income Statement'!C21 -> -150 | D60: ='Income Statement'!D21 -> 1054 | E60: ='Income Statement'!E21 -> -132 | F60: ='Income Statement'!F21 -> -6068 | G60: ='Income Statement'!G21 -> -5055 | H60: ='Income Statement'!H21 -> -4332 | I60: ='Income Statement'!I21 -> -4680 | J60: =-SOFR!$C$29*I83/4-I44/4 -> -4723.6238 | K60: =SUM(G60:J60) -> -18790.624 | L60: =-SOFR!$C$29*K83-K44 -> -18747.69 | M60: =-SOFR!$C$29*L83-L44 -> -18589.578 | N60: =-SOFR!$C$29*M83-M44 -> -18430.884 | O60: =-SOFR!$C$29*N83-N44 -> -18332.077 | P60: =-SOFR!$C$29*O83-O44 -> -18153.481 | Q60: =-SOFR!$C$29*P83-P44 -> -17996.658 | R60: =-SOFR!$C$29*Q83-Q44 -> -17765.012 | S60: SOFR + 3% on Long-Term Debt, 50 bps on unutilized Revolver
B61: Pre-Tax Income: | C61: =C56+SUM(C59:C60) -> 334250 | D61: =D56+SUM(D59:D60) -> 288379 | E61: =E56+SUM(E59:E60) -> 451132 | F61: =F56+SUM(F59:F60) -> 456156 | G61: =G56+SUM(G59:G60) -> 91318 | H61: =H56+SUM(H59:H60) -> 79955 | I61: =I56+SUM(I59:I60) -> 95336 | J61: =J56+SUM(J59:J60) -> 85599.536 | ... R61: =R56+SUM(R59:R60) -> 395690.81
B63: Income Taxes: | C63: =-'Income Statement'!C24 -> -82492 | D63: =-'Income Statement'!D24 -> -70442 | E63: =-'Income Statement'!E24 -> -110650 | F63: =-'Income Statement'!F24 -> -113049 | G63: =-'Income Statement'!G24 -> -22190 | H63: =-'Income Statement'!H24 -> -18390 | I63: =-'Income Statement'!I24 -> -24024 | J63: =-J61*J20 -> -20686.393 | K63: =SUM(G63:J63) -> -85290.393 | L63: =-L61*L20 -> -63686.42 | M63: =-M61*M20 -> -66054.8 | N63: =-N61*N20 -> -75316.055 | O63: =-O61*O20 -> -79416.727 | P63: =-P61*P20 -> -87115.634 | Q63: =-Q61*Q20 -> -92198.686 | R63: =-R61*R20 -> -96912.941
B65: Net Income: | C65: =C61+C63 -> 251758 | D65: =D61+D63 -> 217937 | E65: =E61+E63 -> 340482 | F65: =F61+F63 -> 343107 | G65: =G61+G63 -> 69128 | H65: =H61+H63 -> 61565 | I65: =I61+I63 -> 71312 | J65: =J61+J63 -> 64913.144 | ... R65: =R61+R63 -> 298777.87
B66: (-) NCI Net Income: | C66: 641 | D66: 1030 | E66: 696 | F66: -126 | G66: -222 | H66: -282 | I66: -393 | J66: =J65*J21 -> -287.84549 | K66: =SUM(G66:J66) -> -1184.8455 | L66: =L65*L21 -> 176.77814 | M66: =M65*M21 -> 116.7093 | N66: =N65*N21 -> -59.700931 | O66: =O65*O21 -> -175.57731 | P66: =P65*P21 -> -212.04125 | Q66: =Q65*Q21 -> -16.339781 | R66: =R65*R21 -> -74.518345
B67: Net Income to Parent: | C67: =SUM(C65:C66) -> 252399 | D67: =SUM(D65:D66) -> 218967 | E67: =SUM(E65:E66) -> 341178 | F67: =SUM(F65:F66) -> 342981 | G67: =SUM(G65:G66) -> 68906 | H67: =SUM(H65:H66) -> 61283 | I67: =SUM(I65:I66) -> 70919 | J67: =SUM(J65:J66) -> 64625.298 | ... R67: =SUM(R65:R66) -> 298703.36
B68: Profit Margin | C68: =C67/C49 -> 0.079062486 | D68: =D67/D49 -> 0.067515226 | E68: =E67/E49 -> 0.092412754 | F68: =F67/F49 -> 0.085546739 | G68: =G67/G49 -> 0.072230859 | H68: =H67/H49 -> 0.06551893 | I68: =I67/I49 -> 0.072414356 | J68: =J67/J49 -> 0.067870973 | ... R68: =R67/R49 -> 0.074365778
B70: Balance Sheet: | C70: =C$2 -> 44196 | D70: =D$2 -> 44561 | E70: =E$2 -> 44926 | F70: =F$2 -> 45291 | G70: =G$2 -> Q1-24 | H70: =H$2 -> Q2-24 | I70: =I$2 -> Q3-24 | J70: =J$2 -> Q4-24 | ... R70: =R$2 -> 48213
B72: ASSETS:
B73: Cash: | C73: ='Balance Sheet NWC (Base)'!C7 -> 125211 | D73: ='Balance Sheet NWC (Base)'!D7 -> 40536 | E73: ='Balance Sheet NWC (Base)'!E7 -> 43537 | F73: ='Balance Sheet NWC (Base)'!F7 -> 50052 | G73: ='Balance Sheet NWC (Base)'!G7 -> 25805 | H73: ='Balance Sheet NWC (Base)'!H7 -> 22227 | I73: ='Balance Sheet NWC (Base)'!I7 -> 25928 | J73: =I73+J121 -> 25000 | K73: =J73 -> 25000 | L73: =K73+L121 -> 25000 | M73: =L73+M121 -> 25000 | N73: =M73+N121 -> 25000 | O73: =N73+O121 -> 25000 | P73: =O73+P121 -> 25000 | Q73: =P73+Q121 -> 25000 | R73: =Q73+R121 -> 25000
B74: NWC: | C74: ='Balance Sheet NWC (Base)'!C11-'Balance Sheet NWC (Base)'!C7-'Balance Sheet NWC (Base)'!C24+'Balance Sheet NWC (Downside)'!C20 -> 826074 | D74: ='Balance Sheet NWC (Base)'!D11-'Balance Sheet NWC (Base)'!D7-'Balance Sheet NWC (Base)'!D24+'Balance Sheet NWC (Downside)'!D20 -> 914214 | E74: ='Balance Sheet NWC (Base)'!E11-'Balance Sheet NWC (Base)'!E7-'Balance Sheet NWC (Base)'!E24+'Balance Sheet NWC (Downside)'!E20 -> 1099822 | F74: ='Balance Sheet NWC (Base)'!F11-'Balance Sheet NWC (Base)'!F7-'Balance Sheet NWC (Base)'!F24+'Balance Sheet NWC (Downside)'!F20 -> 847960 | G74: ='Balance Sheet NWC (Base)'!G11-'Balance Sheet NWC (Base)'!G7-'Balance Sheet NWC (Base)'!G24+'Balance Sheet NWC (Downside)'!G20 -> 861351 | H74: ='Balance Sheet NWC (Base)'!H11-'Balance Sheet NWC (Base)'!H7-'Balance Sheet NWC (Base)'!H24+'Balance Sheet NWC (Downside)'!H20 -> 870085 | I74: ='Balance Sheet NWC (Base)'!I11-'Balance Sheet NWC (Base)'!I7-'Balance Sheet NWC (Base)'!I24+'Balance Sheet NWC (Downside)'!I20 -> 809743 | J74: =J48*J$24*4 -> 844251.1 | K74: =J74 -> 844251.1 | L74: =L48*L$24 -> 871984.85 | M74: =M48*M$24 -> 824699.85 | N74: =N48*N$24 -> 788000.24 | O74: =O48*O$24 -> 789211.37 | P74: =P48*P$24 -> 802438.54 | Q74: =Q48*Q$24 -> 833635.27 | R74: =R48*R$24 -> 871415.9
B75: Net PP&E, Goodwill & Intangibles: | C75: ='Balance Sheet NWC (Base)'!C12+'Balance Sheet NWC (Base)'!C13+'Balance Sheet NWC (Base)'!C14 -> 1084431 | D75: ='Balance Sheet NWC (Base)'!D12+'Balance Sheet NWC (Base)'!D13+'Balance Sheet NWC (Base)'!D14 -> 1092974 | E75: ='Balance Sheet NWC (Base)'!E12+'Balance Sheet NWC (Base)'!E13+'Balance Sheet NWC (Base)'!E14 -> 1111124 | F75: ='Balance Sheet NWC (Base)'!F12+'Balance Sheet NWC (Base)'!F13+'Balance Sheet NWC (Base)'!F14 -> 1148475 | G75: ='Balance Sheet NWC (Base)'!G12+'Balance Sheet NWC (Base)'!G13+'Balance Sheet NWC (Base)'!G14 -> 1147299 | H75: ='Balance Sheet NWC (Base)'!H12+'Balance Sheet NWC (Base)'!H13+'Balance Sheet NWC (Base)'!H14 -> 1159699 | I75: ='Balance Sheet NWC (Base)'!I12+'Balance Sheet NWC (Base)'!I13+'Balance Sheet NWC (Base)'!I14 -> 1169573 | J75: =I75-J106-J99 -> 1173392 | K75: =J75 -> 1173392 | L75: =K75-L106-L99 -> 1158408.7 | M75: =L75-M106-M99 -> 1151473.7 | N75: =M75-N106-N99 -> 1151359.5 | O75: =N75-O106-O99 -> 1153689.7 | P75: =O75-P106-P99 -> 1157804.5 | Q75: =P75-Q106-Q99 -> 1159824.6 | R75: =Q75-R106-R99 -> 1163267.3
B76: Op. Lease Assets: | C76: ='Balance Sheet NWC (Base)'!C15 -> 56173 | D76: ='Balance Sheet NWC (Base)'!D15 -> 49011 | E76: ='Balance Sheet NWC (Base)'!E15 -> 64780 | F76: ='Balance Sheet NWC (Base)'!F15 -> 65909 | G76: ='Balance Sheet NWC (Base)'!G15 -> 61076 | H76: ='Balance Sheet NWC (Base)'!H15 -> 61943 | I76: ='Balance Sheet NWC (Base)'!I15 -> 60878 | J76: =I76 -> 60878 | K76: =J76 -> 60878 | L76: =K76 -> 60878 | M76: =L76 -> 60878 | N76: =M76 -> 60878 | O76: =N76 -> 60878 | P76: =O76 -> 60878 | Q76: =P76 -> 60878 | R76: =Q76 -> 60878 | S76: No change
B77: Other Assets: | C77: ='Balance Sheet NWC (Base)'!C16 -> 4056 | D77: ='Balance Sheet NWC (Base)'!D16 -> 5885 | E77: ='Balance Sheet NWC (Base)'!E16 -> 9887 | F77: ='Balance Sheet NWC (Base)'!F16 -> 12237 | G77: ='Balance Sheet NWC (Base)'!G16 -> 14383 | H77: ='Balance Sheet NWC (Base)'!H16 -> 14839 | I77: ='Balance Sheet NWC (Base)'!I16 -> 24495 | J77: =I77-J100-J107 -> 27349.653 | K77: =J77 -> 27349.653 | L77: =K77-L100-L107 -> 35789.773 | M77: =L77-M100-M107 -> 42797.346 | N77: =M77-N100-N107 -> 44868.796 | O77: =N77-O100-O107 -> 41658.127 | P77: =O77-P100-P107 -> 28811.979 | Q77: =P77-Q100-Q107 -> 19243.537 | R77: =Q77-R100-R107 -> 8574.5918
B78: Total Assets: | C78: =SUM(C73:C77) -> 2095945 | D78: =SUM(D73:D77) -> 2102620 | E78: =SUM(E73:E77) -> 2329150 | F78: =SUM(F73:F77) -> 2124633 | G78: =SUM(G73:G77) -> 2109914 | H78: =SUM(H73:H77) -> 2128793 | I78: =SUM(I73:I77) -> 2090617 | J78: =SUM(J73:J77) -> 2130870.8 | ... R78: =SUM(R73:R77) -> 2129135.7
B80: LIABILITES & EQUITY:
B81: Revolver: | C81: 174200 | D81: 204200 | E81: 205300 | F81: 40300 | G81: 125300 | H81: 176300 | I81: 81300 | J81: =I81+J111 -> 102530.87 | K81: =J81 -> 102530.87 | L81: =K81+L111 -> 101954.47 | M81: =L81+M111 -> 101813.48 | N81: =M81+N111 -> 90010.596 | O81: =N81+O111 -> 94478.003 | P81: =O81+P111 -> 94900.321 | Q81: =P81+Q111 -> 110593.59 | R81: =Q81+R111 -> 116930.9
B82: Short Term Debt: | C82: ='Balance Sheet NWC (Base)'!C20 -> 122248 | D82: ='Balance Sheet NWC (Base)'!D20 -> 202433 | E82: ='Balance Sheet NWC (Base)'!E20 -> 325680 | F82: ='Balance Sheet NWC (Base)'!F20 -> 229935 | G82: ='Balance Sheet NWC (Base)'!G20 -> 244048 | H82: ='Balance Sheet NWC (Base)'!H20 -> 257829 | I82: ='Balance Sheet NWC (Base)'!I20 -> 206335 | J82: =I82 -> 206335 | K82: =J82 -> 206335 | L82: =K82 -> 206335 | M82: =L82 -> 206335 | N82: =M82 -> 206335 | O82: =N82 -> 206335 | P82: =O82 -> 206335 | Q82: =P82 -> 206335 | R82: =Q82 -> 206335 | S82: No change
B83: Long-Term Debt: | C83: ='Balance Sheet NWC (Base)'!C25-C81 -> 322818 | D83: ='Balance Sheet NWC (Base)'!D25-D81 -> 379416 | E83: ='Balance Sheet NWC (Base)'!E25-E81 -> 263612 | F83: ='Balance Sheet NWC (Base)'!F25-F81 -> 184091 | G83: ='Balance Sheet NWC (Base)'!G25-G81 -> 169130 | H83: ='Balance Sheet NWC (Base)'!H25-H81 -> 118174 | I83: ='Balance Sheet NWC (Base)'!I25-I81 -> 218512 | J83: =I83/1.0025 -> 217967.08 | K83: =J83 -> 217967.08 | L83: =K83/1.01 -> 215808.99 | M83: =L83/1.01 -> 213672.27 | N83: =M83/1.01 -> 211556.7 | O83: =N83/1.01 -> 209462.08 | P83: =O83/1.01 -> 207388.2 | Q83: =P83/1.01 -> 205334.85 | R83: =Q83/1.01 -> 203301.83 | S83: 1% Annual Amortization
B84: Op. Lease Liabilities: | C84: ='Balance Sheet NWC (Base)'!C26 -> 34379 | D84: ='Balance Sheet NWC (Base)'!D26 -> 36429 | E84: ='Balance Sheet NWC (Base)'!E26 -> 47616 | F84: ='Balance Sheet NWC (Base)'!F26 -> 45924 | G84: ='Balance Sheet NWC (Base)'!G26 -> 41410 | H84: ='Balance Sheet NWC (Base)'!H26 -> 41230 | I84: ='Balance Sheet NWC (Base)'!I26 -> 39532 | J84: =I84 -> 39532 | K84: =J84 -> 39532 | L84: =K84 -> 39532 | M84: =L84 -> 39532 | N84: =M84 -> 39532 | O84: =N84 -> 39532 | P84: =O84 -> 39532 | Q84: =P84 -> 39532 | R84: =Q84 -> 39532 | S84: No change
B85: Other Liabilities: | C85: ='Balance Sheet NWC (Base)'!C27+'Balance Sheet NWC (Base)'!C28 -> 121727 | D85: ='Balance Sheet NWC (Base)'!D27+'Balance Sheet NWC (Base)'!D28 -> 118270 | E85: ='Balance Sheet NWC (Base)'!E27+'Balance Sheet NWC (Base)'!E28 -> 124659 | F85: ='Balance Sheet NWC (Base)'!F27+'Balance Sheet NWC (Base)'!F28 -> 131801 | G85: ='Balance Sheet NWC (Base)'!G27+'Balance Sheet NWC (Base)'!G28 -> 131801 | H85: ='Balance Sheet NWC (Base)'!H27+'Balance Sheet NWC (Base)'!H28 -> 131761 | I85: ='Balance Sheet NWC (Base)'!I27+'Balance Sheet NWC (Base)'!I28 -> 130729 | J85: =I85 -> 130729 | K85: =J85 -> 130729 | L85: =K85 -> 130729 | M85: =L85 -> 130729 | N85: =M85 -> 130729 | O85: =N85 -> 130729 | P85: =O85 -> 130729 | Q85: =P85 -> 130729 | R85: =Q85 -> 130729 | S85: No change
B86: Total Liabilities: | C86: =SUM(C81:C85) -> 775372 | D86: =SUM(D81:D85) -> 940748 | E86: =SUM(E81:E85) -> 966867 | F86: =SUM(F81:F85) -> 632051 | G86: =SUM(G81:G85) -> 711689 | H86: =SUM(H81:H85) -> 725294 | I86: =SUM(I81:I85) -> 676408 | J86: =SUM(J81:J85) -> 697093.95 | ... R86: =SUM(R81:R85) -> 696828.73
B88: Common Shareholders' Equity: | C88: ='Balance Sheet NWC (Base)'!C40 -> 1314945 | D88: ='Balance Sheet NWC (Base)'!D40 -> 1150871 | E88: ='Balance Sheet NWC (Base)'!E40 -> 1350434 | F88: ='Balance Sheet NWC (Base)'!F40 -> 1479164 | G88: ='Balance Sheet NWC (Base)'!G40 -> 1385073 | H88: ='Balance Sheet NWC (Base)'!H40 -> 1390509 | I88: ='Balance Sheet NWC (Base)'!I40 -> 1401616 | J88: =I88+J98+J113+J114+J116+J119-J66 -> 1421471.7 | K88: =J88 -> 1421471.7 | L88: =K88+L98+L113+L114+L116+L119-L66 -> 1445219.9 | M88: =L88+M98+M113+M114+M116+M119-M66 -> 1400168.5 | N88: =M88+N98+N113+N114+N116+N119-N66 -> 1379404.3 | O88: =N88+O98+O113+O114+O116+O119-O66 -> 1377537.7 | P88: =O88+P98+P113+P114+P116+P119-P66 -> 1383897.2 | Q88: =P88+Q98+Q113+Q114+Q116+Q119-Q66 -> 1393922 | R88: =Q88+R98+R113+R114+R116+R119-R66 -> 1420246.5
B89: Noncontrolling Interests: | C89: ='Balance Sheet NWC (Base)'!C41 -> 5628 | D89: ='Balance Sheet NWC (Base)'!D41 -> 11001 | E89: ='Balance Sheet NWC (Base)'!E41 -> 11849 | F89: ='Balance Sheet NWC (Base)'!F41 -> 13418 | G89: ='Balance Sheet NWC (Base)'!G41 -> 13152 | H89: ='Balance Sheet NWC (Base)'!H41 -> 12990 | I89: ='Balance Sheet NWC (Base)'!I41 -> 12593 | J89: =I89+J66+J115 -> 12305.155 | K89: =J89 -> 12305.155 | L89: =K89+L66+L115 -> 12481.933 | M89: =L89+M66+M115 -> 12598.642 | N89: =M89+N66+N115 -> 12538.941 | O89: =N89+O66+O115 -> 12363.364 | P89: =O89+P66+P115 -> 12151.322 | Q89: =P89+Q66+Q115 -> 12134.983 | R89: =Q89+R66+R115 -> 12060.464
B90: Total Equity: | C90: =SUM(C88:C89) -> 1320573 | D90: =SUM(D88:D89) -> 1161872 | E90: =SUM(E88:E89) -> 1362283 | F90: =SUM(F88:F89) -> 1492582 | G90: =SUM(G88:G89) -> 1398225 | H90: =SUM(H88:H89) -> 1403499 | I90: =SUM(I88:I89) -> 1414209 | J90: =SUM(J88:J89) -> 1433776.8 | ... R90: =SUM(R88:R89) -> 1432307
B92: TOTAL LIABILITIES + EQUITY: | C92: =C86+C90 -> 2095945 | D92: =D86+D90 -> 2102620 | E92: =E86+E90 -> 2329150 | F92: =F86+F90 -> 2124633 | G92: =G86+G90 -> 2109914 | H92: =H86+H90 -> 2128793 | I92: =I86+I90 -> 2090617 | J92: =J86+J90 -> 2130870.8 | ... R92: =R86+R90 -> 2129135.7
B94: Balance Check: | C94: =C78-C92 -> 0 | D94: =D78-D92 -> 0 | E94: =E78-E92 -> 0 | F94: =F78-F92 -> 0 | G94: =G78-G92 -> 0 | H94: =H78-H92 -> 0 | I94: =I78-I92 -> 0 | J94: =J78-J92 -> 0 | ... R94: =R78-R92 -> 0
B96: Cash Flow Statement: | C96: =C$2 -> 44196 | D96: =D$2 -> 44561 | E96: =E$2 -> 44926 | F96: =F$2 -> 45291 | G96: =G$2 -> Q1-24 | H96: =H$2 -> Q2-24 | I96: =I$2 -> Q3-24 | J96: =J$2 -> Q4-24 | ... R96: =R$2 -> 48213
B97: Cash Flow from Operations:
B98: Net Income to Parent: | C98: =C65 -> 251758 | D98: =D65 -> 217937 | E98: =E65 -> 340482 | F98: =F65 -> 343107 | G98: =G65 -> 69128 | H98: =H65 -> 61565 | I98: =I65 -> 71312 | J98: =J65 -> 64913.144 | K98: =SUM(G98:J98) -> 266918.14 | L98: =L65 -> 195976.97 | M98: =M65 -> 203601.86 | N98: =N65 -> 231974.86 | O98: =O65 -> 244651.28 | P98: =P65 -> 269173.34 | Q98: =Q65 -> 284155.85 | R98: =R65 -> 298777.87
B99: (+) D&A: | C99: ='Cash Flows'!C8+'Cash Flows'!C9 -> 69079 | D99: ='Cash Flows'!D8+'Cash Flows'!D9 -> 68846 | E99: ='Cash Flows'!E8+'Cash Flows'!E9 -> 70376 | F99: ='Cash Flows'!F8+'Cash Flows'!F9 -> 75129 | G99: ='Cash Flows'!G8+'Cash Flows'!G9 -> 19782 | H99: ='Cash Flows'!H8+'Cash Flows'!H9 -> 21293 | I99: ='Cash Flows'!I8+'Cash Flows'!I9 -> 20650 | J99: =J49*J27 -> 20499.369 | K99: =SUM(G99:J99) -> 82224.369 | L99: =L49*L27 -> 74183.921 | M99: =M49*M27 -> 71112.584 | N99: =N49*N27 -> 70386.98 | O99: =O49*O27 -> 72461.865 | P99: =P49*P27 -> 75699.674 | Q99: =Q49*Q27 -> 77747.804 | R99: =R49*R27 -> 81203.755
B100: (+/-) Other Items: | C100: =SUM('Cash Flows'!C11:C13,'Cash Flows'!C16:C19) -> 36461 | D100: =SUM('Cash Flows'!D11:D13,'Cash Flows'!D16:D19) -> 12854 | E100: =SUM('Cash Flows'!E11:E13,'Cash Flows'!E16:E19) -> 29741 | F100: =SUM('Cash Flows'!F11:F13,'Cash Flows'!F16:F19) -> 36272 | G100: =SUM('Cash Flows'!G11:G13,'Cash Flows'!G16:G19) -> 5609 | H100: =SUM('Cash Flows'!H11:H13,'Cash Flows'!H16:H19) -> 1013 | I100: =SUM('Cash Flows'!I11:I13,'Cash Flows'!I16:I19) -> -5304 | J100: =J49*J29 -> 490.95235 | K100: =SUM(G100:J100) -> 1808.9523 | L100: =L49*L29 -> 3600.9203 | M100: =M49*M29 -> 6503.951 | N100: =N49*N29 -> 9365.6494 | O100: =O49*O29 -> 10766.114 | P100: =P49*P29 -> 18460.591 | Q100: =Q49*Q29 -> 20335.903 | R100: =R49*R29 -> 21523.93
B101: (+/-) Change in NWC: | C101: ='Cash Flows'!C14+'Cash Flows'!C21+'Cash Flows'!C22+'Cash Flows'!C23+'Cash Flows'!C25+'Cash Flows'!C26 -> 38929 | D101: ='Cash Flows'!D14+'Cash Flows'!D21+'Cash Flows'!D22+'Cash Flows'!D23+'Cash Flows'!D25+'Cash Flows'!D26 -> -76776 | E101: ='Cash Flows'!E14+'Cash Flows'!E21+'Cash Flows'!E22+'Cash Flows'!E23+'Cash Flows'!E25+'Cash Flows'!E26 -> -194459 | F101: ='Cash Flows'!F14+'Cash Flows'!F21+'Cash Flows'!F22+'Cash Flows'!F23+'Cash Flows'!F25+'Cash Flows'!F26 -> 245281 | G101: ='Cash Flows'!G14+'Cash Flows'!G21+'Cash Flows'!G22+'Cash Flows'!G23+'Cash Flows'!G25+'Cash Flows'!G26 -> -13193 | H101: ='Cash Flows'!H14+'Cash Flows'!H21+'Cash Flows'!H22+'Cash Flows'!H23+'Cash Flows'!H25+'Cash Flows'!H26 -> -5072 | I101: ='Cash Flows'!I14+'Cash Flows'!I21+'Cash Flows'!I22+'Cash Flows'!I23+'Cash Flows'!I25+'Cash Flows'!I26 -> 56945 | J101: =I74-J74 -> -34508.102 | K101: =SUM(G101:J101) -> 4171.8983 | L101: =K74-L74 -> -27733.748 | M101: =L74-M74 -> 47285.002 | N101: =M74-N74 -> 36699.609 | O101: =N74-O74 -> -1211.1357 | P101: =O74-P74 -> -13227.161 | Q101: =P74-Q74 -> -31196.734 | R101: =Q74-R74 -> -37780.63
B102: (+/-) Change in Leases: | C102: ='Cash Flows'!C10+'Cash Flows'!C15+'Cash Flows'!C24 -> 512 | D102: ='Cash Flows'!D10+'Cash Flows'!D15+'Cash Flows'!D24 -> 1601 | E102: ='Cash Flows'!E10+'Cash Flows'!E15+'Cash Flows'!E24 -> 43 | F102: ='Cash Flows'!F10+'Cash Flows'!F15+'Cash Flows'!F24 -> -207 | G102: ='Cash Flows'!G10+'Cash Flows'!G15+'Cash Flows'!G24 -> -158 | H102: ='Cash Flows'!H10+'Cash Flows'!H15+'Cash Flows'!H24 -> -56 | I102: ='Cash Flows'!I10+'Cash Flows'!I15+'Cash Flows'!I24 -> -81 | J102: =I76-J76+J84-I84 -> 0 | K102: =SUM(G102:J102) -> -295 | L102: =K76-L76+L84-K84 -> 0 | M102: =L76-M76+M84-L84 -> 0 | N102: =M76-N76+N84-M84 -> 0 | O102: =N76-O76+O84-N84 -> 0 | P102: =O76-P76+P84-O84 -> 0 | Q102: =P76-Q76+Q84-P84 -> 0 | R102: =Q76-R76+R84-Q84 -> 0
B103: Cash Flow from Operations: | C103: =SUM(C98:C102) -> 396739 | D103: =SUM(D98:D102) -> 224462 | E103: =SUM(E98:E102) -> 246183 | F103: =SUM(F98:F102) -> 699582 | G103: =SUM(G98:G102) -> 81168 | H103: =SUM(H98:H102) -> 78743 | I103: =SUM(I98:I102) -> 143522 | J103: =SUM(J98:J102) -> 51395.363 | ... R103: =SUM(R98:R102) -> 363724.93
B105: Cash Flow from Investing:
B106: (-) CapEx: | C106: ='Cash Flows'!C30 -> -46991 | D106: ='Cash Flows'!D30 -> -53746 | E106: ='Cash Flows'!E30 -> -61373 | F106: ='Cash Flows'!F30 -> -92493 | G106: ='Cash Flows'!G30 -> -18433 | H106: ='Cash Flows'!H30 -> -25350 | I106: ='Cash Flows'!I30 -> -29571 | J106: =-J49*J26 -> -24318.379 | K106: =SUM(G106:J106) -> -97672.379 | L106: =-L49*L26 -> -59200.568 | M106: =-M49*M26 -> -64177.604 | N106: =-N49*N26 -> -70272.85 | O106: =-O49*O26 -> -74791.988 | P106: =-P49*P26 -> -79814.491 | Q106: =-Q49*Q26 -> -79767.96 | R106: =-R49*R26 -> -84646.366
B107: (-) Acquisitions & Other: | C107: ='Cash Flows'!C32+'Cash Flows'!C33 -> -2286 | D107: ='Cash Flows'!D32+'Cash Flows'!D33 -> -22000 | E107: ='Cash Flows'!E32+'Cash Flows'!E33 -> -33120 | F107: ='Cash Flows'!F32+'Cash Flows'!F33 -> -20182 | G107: ='Cash Flows'!G32+'Cash Flows'!G33 -> 0 | H107: ='Cash Flows'!H32+'Cash Flows'!H33 -> -9868 | I107: ='Cash Flows'!I32+'Cash Flows'!I33 -> 9 | J107: =-J30*J48 -> -3345.6052 | K107: =SUM(G107:J107) -> -13204.605 | L107: =-L30*L48 -> -12041.041 | M107: =-M30*M48 -> -13511.524 | N107: =-N30*N48 -> -11437.1 | O107: =-O30*O48 -> -7555.4446 | P107: =-P30*P48 -> -5614.4424 | Q107: =-Q30*Q48 -> -10767.462 | R107: =-R30*R48 -> -10854.985
B108: Cash Flow from Investing: | C108: =SUM(C106:C107) -> -49277 | D108: =SUM(D106:D107) -> -75746 | E108: =SUM(E106:E107) -> -94493 | F108: =SUM(F106:F107) -> -112675 | G108: =SUM(G106:G107) -> -18433 | H108: =SUM(H106:H107) -> -35218 | I108: =SUM(I106:I107) -> -29562 | J108: =SUM(J106:J107) -> -27663.984 | ... R108: =SUM(R106:R107) -> -95501.351
B110: Cash Flow from Financing:
B111: (+/-) Revolver: | C111: =C81 -> 174200 | D111: =D81-C81 -> 30000 | E111: =E81-D81 -> 1100 | F111: =F81-E81 -> -165000 | G111: =G81-F81 -> 85000 | H111: =H81-G81 -> 51000 | I111: =I81-H81 -> -95000 | J111: =J39 -> 21230.872 | K111: =SUM(G111:J111) -> 62230.872 | L111: =L39 -> -576.39925 | M111: =M39 -> -140.99577 | N111: =N39 -> -11802.88 | O111: =O39 -> 4467.4064 | P111: =P39 -> 422.31766 | Q111: =Q39 -> 15693.272 | R111: =R39 -> 6337.3053
B112: (+/-) Change in Debt: | C112: ='Cash Flows'!C41+'Cash Flows'!C42+'Cash Flows'!C44+'Cash Flows'!C45+'Cash Flows'!C46+'Cash Flows'!C47-C111 -> -189 | D112: ='Cash Flows'!D41+'Cash Flows'!D42+'Cash Flows'!D44+'Cash Flows'!D45+'Cash Flows'!D46+'Cash Flows'!D47-D111 -> 136466 | E112: ='Cash Flows'!E41+'Cash Flows'!E42+'Cash Flows'!E44+'Cash Flows'!E45+'Cash Flows'!E46+'Cash Flows'!E47-E111 -> 5934 | F112: ='Cash Flows'!F41+'Cash Flows'!F42+'Cash Flows'!F44+'Cash Flows'!F45+'Cash Flows'!F46+'Cash Flows'!F47-F111 -> -177193 | G112: ='Cash Flows'!G41+'Cash Flows'!G42+'Cash Flows'!G44+'Cash Flows'!G45+'Cash Flows'!G46+'Cash Flows'!G47-G111 -> -376 | H112: ='Cash Flows'!H41+'Cash Flows'!H42+'Cash Flows'!H44+'Cash Flows'!H45+'Cash Flows'!H46+'Cash Flows'!H47-H111 -> -36774 | I112: ='Cash Flows'!I41+'Cash Flows'!I42+'Cash Flows'!I44+'Cash Flows'!I45+'Cash Flows'!I46+'Cash Flows'!I47-I111 -> 50000 | J112: =J83-I83+J85-I85+J82-I82 -> -544.91771 | K112: =SUM(G112:J112) -> 12305.082 | L112: =L83-K83+L85-K85+L82-K82 -> -2158.0899 | M112: =M83-L83+M85-L85+M82-L82 -> -2136.7227 | N112: =N83-M83+N85-M85+N82-M82 -> -2115.567 | O112: =O83-N83+O85-N85+O82-N82 -> -2094.6208 | P112: =P83-O83+P85-O85+P82-O82 -> -2073.882 | Q112: =Q83-P83+Q85-P85+Q82-P82 -> -2053.3485 | R112: =R83-Q83+R85-Q85+R82-Q82 -> -2033.0183
B113: (-) Common Dividends: | C113: ='Cash Flows'!C37 -> -166537 | D113: ='Cash Flows'!D37 -> -167299 | E113: ='Cash Flows'!E37 -> -167376 | F113: ='Cash Flows'!F37 -> -176715 | G113: ='Cash Flows'!G37 -> -47192 | H113: ='Cash Flows'!H37 -> -46772 | I113: ='Cash Flows'!I37 -> -46731 | J113: =-J67*J32 -> -45389 | K113: =SUM(G113:J113) -> -186084 | L113: =-L67*L32 -> -123027.66 | M113: =-M67*M32 -> -126306.17 | N113: =-N67*N32 -> -136770.83 | O113: =-O67*O32 -> -148928.65 | P113: =-P67*P32 -> -168918.44 | Q113: =-Q67*Q32 -> -174698.3 | R113: =-R67*R32 -> -182913.79
B114: (-) Stock Repurchases: | C114: ='Cash Flows'!C36 -> -3444 | D114: ='Cash Flows'!D36 -> -71261 | E114: ='Cash Flows'!E36 -> -27359 | F114: ='Cash Flows'!F36 -> -95779 | G114: ='Cash Flows'!G36 -> -132045 | H114: ='Cash Flows'!H36 -> -16632 | I114: ='Cash Flows'!I36 -> -18489 | J114: =-J33*J67 -> 0 | K114: =SUM(G114:J114) -> -167166 | L114: =-L33*L67 -> -49038.437 | M114: =-M33*M67 -> -122231.14 | N114: =-N33*N67 -> -115957.58 | O114: =-O33*O67 -> -97790.279 | P114: =-P33*P67 -> -94136.454 | Q114: =-Q33*Q67 -> -99448.828 | R114: =-R33*R67 -> -89611.007
B115: (-) Dividends to NCI: | C115: ='Cash Flows'!C38 -> -277634 | D115: ='Cash Flows'!D38 -> -195351 | E115: ='Cash Flows'!E38 -> 0 | F115: ='Cash Flows'!F38 -> 0 | G115: ='Cash Flows'!G38 -> 0 | H115: ='Cash Flows'!H38 -> 0 | I115: ='Cash Flows'!I38 -> 0 | J115: 0 | K115: =SUM(G115:J115) -> 0 | L115: 0 | M115: 0 | N115: 0 | O115: 0 | P115: 0 | Q115: 0 | R115: 0
B116: (+/-) Other Items: | C116: ='Cash Flows'!C39+'Cash Flows'!C40+'Cash Flows'!C43+'Cash Flows'!C48 -> 18986 | D116: ='Cash Flows'!D39+'Cash Flows'!D40+'Cash Flows'!D43+'Cash Flows'!D48 -> 33698 | E116: ='Cash Flows'!E39+'Cash Flows'!E40+'Cash Flows'!E43+'Cash Flows'!E48 -> 39561 | F116: ='Cash Flows'!F39+'Cash Flows'!F40+'Cash Flows'!F43+'Cash Flows'!F48 -> 34287 | G116: ='Cash Flows'!G39+'Cash Flows'!G40+'Cash Flows'!G43+'Cash Flows'!G48 -> 7422 | H116: ='Cash Flows'!H39+'Cash Flows'!H40+'Cash Flows'!H43+'Cash Flows'!H48 -> 2092 | I116: ='Cash Flows'!I39+'Cash Flows'!I40+'Cash Flows'!I43+'Cash Flows'!I48 -> 22 | J116: =MAX(J112,0)*J34 -> 0 | K116: =SUM(G116:J116) -> 9536 | L116: =MAX(L112,0)*L34 -> 0 | M116: =MAX(M112,0)*M34 -> 0 | N116: =MAX(N112,0)*N34 -> 0 | O116: =MAX(O112,0)*O34 -> 0 | P116: =MAX(P112,0)*P34 -> 0 | Q116: =MAX(Q112,0)*Q34 -> 0 | R116: =MAX(R112,0)*R34 -> 0 | S116: Capital structure fixed via buybacks
B117: Cash Flow from Financing: | C117: =SUM(C111:C116) -> -254618 | D117: =SUM(D111:D116) -> -233747 | E117: =SUM(E111:E116) -> -148140 | F117: =SUM(F111:F116) -> -580400 | G117: =SUM(G111:G116) -> -87191 | H117: =SUM(H111:H116) -> -47086 | I117: =SUM(I111:I116) -> -110198 | J117: =SUM(J111:J116) -> -24703.046 | ... R117: =SUM(R111:R116) -> -268220.51
B119: FX Rate Effects: | C119: ='Cash Flows'!C50 -> 81 | D119: ='Cash Flows'!D50 -> 356 | E119: ='Cash Flows'!E50 -> -549 | F119: ='Cash Flows'!F50 -> 8 | G119: ='Cash Flows'!G50 -> 209 | H119: ='Cash Flows'!H50 -> -17 | I119: ='Cash Flows'!I50 -> -61 | J119: =AVERAGE(G119:I119) -> 43.666667 | K119: =SUM(G119:J119) -> 174.66667 | L119: =AVERAGE(C119:F119,K119) -> 14.133333 | M119: =AVERAGE(K119:L119,D119:F119) -> 0.76 | N119: =AVERAGE(K119:M119,E119:F119) -> -70.288 | O119: =AVERAGE(K119:N119,F119) -> 25.4544 | P119: =AVERAGE(K119:O119) -> 28.94528 | Q119: =AVERAGE(L119:P119) -> -0.19899733 | R119: =AVERAGE(M119:Q119) -> -3.0654635
B121: Net Change in Cash: | C121: =C103+C108+C117+C119 -> 92925 | D121: =D103+D108+D117+D119 -> -84675 | E121: =E103+E108+E117+E119 -> 3001 | F121: =F103+F108+F117+F119 -> 6515 | G121: =G103+G108+G117+G119 -> -24247 | H121: =H103+H108+H117+H119 -> -3578 | I121: =I103+I108+I117+I119 -> 3701 | J121: =J103+J108+J117+J119 -> -928 | ... R121: =R103+R108+R117+R119 -> -3.8686832e-11
C122: ='Cash Flows'!C51 -> 92925 | D122: ='Cash Flows'!D51 -> -84675 | E122: ='Cash Flows'!E51 -> 3001 | F122: ='Cash Flows'!F51 -> 6515 | G122: ='Cash Flows'!G51 -> -24247 | H122: ='Cash Flows'!H51 -> -3578 | I122: ='Cash Flows'!I51 -> 3701
B123: Check | C123: =C121-C122 -> 0 | D123: =D121-D122 -> 0 | E123: =E121-E122 -> 0 | F123: =F121-F122 -> 0 | G123: =G121-G122 -> 0 | H123: =H121-H122 -> 0 | I123: =I121-I122 -> 0

Sheet Support ->

Sheet SOFR
A1: Effective Date | B1: Rate Type | C1: Rate (%) | D1: 1st Percentile (%) | E1: 25th Percentile (%) | F1: 75th Percentile (%) | G1: 99th Percentile (%) | H1: Volume ($Billions) | I1: Target Rate From (%) | J1: Target Rate To (%) | K1: Intra Day - Low (%) | L1: Intra Day - High (%) | M1: Standard Deviation (%) | N1: 30-Day Average SOFR | O1: 90-Day Average SOFR | P1: 180-Day Average SOFR | Q1: SOFR Index | R1: Revision Indicator (Y/N) | S1: Footnote ID
A2: 12/27/2024 | B2: SOFR | C2: 4.46 | D2: 4.3 | E2: 4.45 | F2: 4.62 | G2: 4.73 | H2: 2275
A3: 12/26/2024 | B3: SOFR | C3: 4.53 | D3: 4.35 | E3: 4.5 | F3: 4.7 | G3: 4.8 | H3: 2320
A4: 12/24/2024 | B4: SOFR | C4: 4.4 | D4: 4.31 | E4: 4.39 | F4: 4.5 | G4: 4.58 | H4: 2282
A5: 12/23/2024 | B5: SOFR | C5: 4.31 | D5: 4.25 | E5: 4.3 | F5: 4.38 | G5: 4.43 | H5: 2337
A6: 12/20/2024 | B6: SOFR | C6: 4.3 | D6: 4.25 | E6: 4.28 | F6: 4.37 | G6: 4.4 | H6: 2330
A7: 12/19/2024 | B7: SOFR | C7: 4.3 | D7: 4.25 | E7: 4.27 | F7: 4.35 | G7: 4.58 | H7: 2390
A8: 12/18/2024 | B8: SOFR | C8: 4.57 | D8: 4.55 | E8: 4.56 | F8: 4.62 | G8: 4.66 | H8: 2291
A9: 12/17/2024 | B9: SOFR | C9: 4.62 | D9: 4.55 | E9: 4.59 | F9: 4.68 | G9: 4.71 | H9: 2341
A10: 12/16/2024 | B10: SOFR | C10: 4.65 | D10: 4.56 | E10: 4.61 | F10: 4.71 | G10: 4.75 | H10: 2360
A11: 12/13/2024 | B11: SOFR | C11: 4.6 | D11: 4.55 | E11: 4.59 | F11: 4.66 | G11: 4.7 | H11: 2255
A12: 12/12/2024 | B12: SOFR | C12: 4.62 | D12: 4.55 | E12: 4.6 | F12: 4.68 | G12: 4.72 | H12: 2262
A13: 12/11/2024 | B13: SOFR | C13: 4.62 | D13: 4.56 | E13: 4.6 | F13: 4.68 | G13: 4.72 | H13: 2287
... A26: 11/21/2024 | B26: SOFR | C26: 4.57 | D26: 4.55 | E26: 4.56 | F26: 4.62 | G26: 4.66 | H26: 2291
C28: Secured Overnight Financing Rate Data - FEDERAL RESERVE BANK of NEW YORK
B29: SOFR + 3% | C29: =(C2+3)/100 -> 0.0746

Sheet Income Statement
L2: CPI | M2: 0.027
J4: =SUM(G6:J6)/F6-1 -> -0.056349188 | K4: =K6/SUM(G6:J6)-1 -> -0.00088868422 | L4: =L6/K6-1 -> 0.042328042 | M4: =AVERAGE($D4:L4) -> -0.0049699433 | N4: =AVERAGE($D4:M4) -> -0.0049699433 | O4: =AVERAGE($D4:N4) -> -0.0049699433 | P4: =AVERAGE($D4:O4) -> -0.0049699433
C5: FY20 | D5: FY21 | E5: FY22 | F5: FY23 | G5: Q1'24 | H5: Q2'24 | I5: Q3'24 | J5: Q4'24 | K5: FY25 | L5: FY26 | M5: FY27 | N5: FY28 | O5: FY29 | P5: FY30 | Q5: FY31
B6: Net sales | C6: =IFERROR(VLOOKUP($B6,'IS FY21'!$A:$G,COLUMNS('IS FY21'!$A:$G),FALSE),0) -> 3192399 | D6: =IFERROR(VLOOKUP($B6,'IS FY21'!$A:$G,COLUMNS('IS FY21'!$A:$D),FALSE),0) -> 3243224 | E6: =IFERROR(VLOOKUP($B6,'IS FY23'!$A:$J,COLUMNS('IS FY23'!$A:$J),FALSE),0) -> 3691893 | F6: =IFERROR(VLOOKUP($B6,'IS FY23'!$A:$J,COLUMNS('IS FY23'!$A:$D),FALSE),0) -> 4009282 | G6: =IFERROR(VLOOKUP($B6,'IS Q1-24'!$A:$J,COLUMNS('IS Q1-24'!$A:$D),FALSE),0) -> 953969 | H6: =IFERROR(VLOOKUP($B6,'IS Q2-24'!$A:$J,COLUMNS('IS Q2-24'!$A:$D),FALSE),0) -> 935348 | I6: =IFERROR(VLOOKUP($B6,'IS Q3-24'!$A:$J,COLUMNS('IS Q3-24'!$A:$D),FALSE),0) -> 979350 | J6: {=(AVERAGE(G6:I6,C6:F6/4))} -> 914695.21 | K6: 3780000 | L6: 3940000 | M6: =ROUND(L6*(1+L4),-4) -> 4110000 | N6: =ROUND(M6*(1+M4),-4) -> 4090000 | O6: =ROUND(N6*(1+N4),-4) -> 4070000 | P6: =ROUND(O6*(1+O4),-4) -> 4050000 | Q6: =ROUND(P6*(1+P4),-4) -> 4030000
B7: Cost of goods sold | C7: =IFERROR(VLOOKUP($B7,'IS FY21'!$A:$G,COLUMNS('IS FY21'!$A:$G),FALSE),0) -> 1849077 | D7: =IFERROR(VLOOKUP($B7,'IS FY21'!$A:$G,COLUMNS('IS FY21'!$A:$D),FALSE),0) -> 1909709 | E7: =IFERROR(VLOOKUP($B7,'IS FY23'!$A:$J,COLUMNS('IS FY23'!$A:$J),FALSE),0) -> 2133645 | F7: =IFERROR(VLOOKUP($B7,'IS FY23'!$A:$J,COLUMNS('IS FY23'!$A:$D),FALSE),0) -> 2366317 | G7: =IFERROR(VLOOKUP($B7,'IS Q1-24'!$A:$J,COLUMNS('IS Q1-24'!$A:$D),FALSE),0) -> 560852 | H7: =IFERROR(VLOOKUP($B7,'IS Q2-24'!$A:$J,COLUMNS('IS Q2-24'!$A:$D),FALSE),0) -> 546737 | I7: =IFERROR(VLOOKUP($B7,'IS Q3-24'!$A:$J,COLUMNS('IS Q3-24'!$A:$D),FALSE),0) -> 578903 | J7: =(J6*(1-J9)) -> 535714.92 | K7: =ROUND(K6*(1-K9),-4) -> 2210000 | L7: =ROUND(L6*(1-L9),-4) -> 2310000 | M7: =ROUND(M6*(1-M9),-4) -> 2410000 | N7: =ROUND(N6*(1-N9),-4) -> 2400000 | O7: =ROUND(O6*(1-O9),-4) -> 2380000 | P7: =ROUND(P6*(1-P9),-4) -> 2370000 | Q7: =ROUND(Q6*(1-Q9),-4) -> 2360000
B8: Gross profit | C8: =IFERROR(VLOOKUP($B8,'IS FY21'!$A:$G,COLUMNS('IS FY21'!$A:$G),FALSE),0) -> 1343322 | D8: =IFERROR(VLOOKUP($B8,'IS FY21'!$A:$G,COLUMNS('IS FY21'!$A:$D),FALSE),0) -> 1333515 | E8: =IFERROR(VLOOKUP($B8,'IS FY23'!$A:$J,COLUMNS('IS FY23'!$A:$J),FALSE),0) -> 1558248 | F8: =IFERROR(VLOOKUP($B8,'IS FY23'!$A:$J,COLUMNS('IS FY23'!$A:$D),FALSE),0) -> 1642965 | G8: =IFERROR(VLOOKUP($B8,'IS Q1-24'!$A:$J,COLUMNS('IS Q1-24'!$A:$D),FALSE),0) -> 393117 | H8: =IFERROR(VLOOKUP($B8,'IS Q2-24'!$A:$J,COLUMNS('IS Q2-24'!$A:$D),FALSE),0) -> 388611 | I8: =IFERROR(VLOOKUP($B8,'IS Q3-24'!$A:$J,COLUMNS('IS Q3-24'!$A:$D),FALSE),0) -> 400447 | J8: =J6-J7 -> 378980.29 | K8: =K6-K7 -> 1570000 | L8: =L6-L7 -> 1630000 | M8: =M6-M7 -> 1700000 | N8: =N6-N7 -> 1690000 | O8: =O6-O7 -> 1690000 | P8: =P6-P7 -> 1680000 | Q8: =Q6-Q7 -> 1670000
B9: Profit / Sales | C9: =C8/C6 -> 0.42078763 | D9: =D8/D6 -> 0.41116956 | E9: =E8/E6 -> 0.4220729 | F9: =F8/F6 -> 0.40979033 | G9: =G8/G6 -> 0.41208572 | H9: =H8/H6 -> 0.4154721 | I9: =I8/I6 -> 0.40889059 | J9: =AVERAGE($C$9:$I$9) -> 0.41432412 | K9: =AVERAGE($C$9:$I$9) -> 0.41432412 | L9: =AVERAGE($C$9:$I$9) -> 0.41432412 | M9: =AVERAGE($C$9:$I$9) -> 0.41432412 | N9: =AVERAGE($C$9:$I$9) -> 0.41432412 | O9: =AVERAGE($C$9:$I$9) -> 0.41432412 | P9: =AVERAGE($C$9:$I$9) -> 0.41432412 | Q9: =AVERAGE($C$9:$I$9) -> 0.41432412
B11: Operating expenses | C11: =IFERROR(VLOOKUP($B11,'IS FY21'!$A:$G,COLUMNS('IS FY21'!$A:$G),FALSE),0) -> 975553 | D11: =IFERROR(VLOOKUP($B11,'IS FY21'!$A:$G,COLUMNS('IS FY21'!$A:$D),FALSE),0) -> 994468 | E11: =IFERROR(VLOOKUP($B11,'IS FY23'!$A:$J,COLUMNS('IS FY23'!$A:$J),FALSE),0) -> 1083862 | F11: =IFERROR(VLOOKUP($B11,'IS FY23'!$A:$J,COLUMNS('IS FY23'!$A:$D),FALSE),0) -> 1151295 | G11: =IFERROR(VLOOKUP($B11,'IS Q1-24'!$A:$J,COLUMNS('IS Q1-24'!$A:$D),FALSE),0) -> 290633 | H11: =IFERROR(VLOOKUP($B11,'IS Q2-24'!$A:$J,COLUMNS('IS Q2-24'!$A:$D),FALSE),0) -> 291235 | I11: =IFERROR(VLOOKUP($B11,'IS Q3-24'!$A:$J,COLUMNS('IS Q3-24'!$A:$D),FALSE),0) -> 288991 | J11: {=(AVERAGE(G11:I11,C11:F11/4))} -> 274593.36 | K11: =ROUND(K16*K6,-4) -> 1140000 | L11: =ROUND(L16*L6,-4) -> 1180000 | M11: =ROUND(M16*M6,-4) -> 1240000 | N11: =ROUND(N16*N6,-4) -> 1230000 | O11: =ROUND(O16*O6,-4) -> 1220000 | P11: =ROUND(P16*P6,-4) -> 1220000 | Q11: =ROUND(Q16*Q6,-4) -> 1210000
B12: Impairment loss, net | C12: 0 | D12: =IFERROR(VLOOKUP($B12,'IS FY21'!$A:$G,COLUMNS('IS FY21'!$A:$D),FALSE),0) -> 5886 | E12: 0 | F12: 0 | G12: =IFERROR(VLOOKUP($B12,'IS Q1-24'!$A:$J,COLUMNS('IS Q1-24'!$A:$D),FALSE),0) -> 0 | H12: =IFERROR(VLOOKUP($B12,'IS Q2-24'!$A:$J,COLUMNS('IS Q2-24'!$A:$D),FALSE),0) -> 0 | I12: =IFERROR(VLOOKUP($B12,'IS Q3-24'!$A:$J,COLUMNS('IS Q3-24'!$A:$D),FALSE),0) -> 0 | J12: 0 | K12: 0 | L12: 0 | M12: 0 | N12: 0 | O12: 0 | P12: 0 | Q12: 0
B13: Restructuring costs | C13: =IFERROR(VLOOKUP($B13,'IS FY21'!$A:$G,COLUMNS('IS FY21'!$A:$G),FALSE),0) -> 17029 | D13: =IFERROR(VLOOKUP($B13,'IS FY21'!$A:$G,COLUMNS('IS FY21'!$A:$D),FALSE),0) -> 31392 | E13: =IFERROR(VLOOKUP($B13,'IS FY23'!$A:$J,COLUMNS('IS FY23'!$A:$J),FALSE),0) -> 15805 | F13: =IFERROR(VLOOKUP($B13,'IS FY23'!$A:$J,COLUMNS('IS FY23'!$A:$D),FALSE),0) -> 7937 | G13: =IFERROR(VLOOKUP($B13,'IS Q1-24'!$A:$J,COLUMNS('IS Q1-24'!$A:$D),FALSE),0) -> 916 | H13: =IFERROR(VLOOKUP($B13,'IS Q2-24'!$A:$J,COLUMNS('IS Q2-24'!$A:$D),FALSE),0) -> 6181 | I13: =IFERROR(VLOOKUP($B13,'IS Q3-24'!$A:$J,COLUMNS('IS Q3-24'!$A:$D),FALSE),0) -> 4690 | J13: {=(AVERAGE(G13:I13,C13:F13/4))} -> 4261.1071 | K13: =AVERAGE(SUM($G13:$J13),$C13:$F13)*(1+$M$2) -> 18118.561 | L13: =K13*(1+$M$2) -> 18607.763 | M13: =L13*(1+$M$2) -> 19110.172 | N13: =M13*(1+$M$2) -> 19626.147 | O13: =N13*(1+$M$2) -> 20156.053 | P13: =O13*(1+$M$2) -> 20700.266 | Q13: =P13*(1+$M$2) -> 21259.173
B14: Gain on sale of property | C14: =IFERROR(VLOOKUP($B14,'IS FY21'!$A:$G,COLUMNS('IS FY21'!$A:$G),FALSE),0) -> 0 | D14: =IFERROR(VLOOKUP($B14,'IS FY21'!$A:$G,COLUMNS('IS FY21'!$A:$D),FALSE),0) -> 0 | E14: =IFERROR(VLOOKUP($B14,'IS FY23'!$A:$J,COLUMNS('IS FY23'!$A:$J),FALSE),0) -> -10132 | F14: 0 | G14: =IFERROR(VLOOKUP($B14,'IS Q1-24'!$A:$J,COLUMNS('IS Q1-24'!$A:$D),FALSE),0) -> 0 | H14: =IFERROR(VLOOKUP($B14,'IS Q2-24'!$A:$J,COLUMNS('IS Q2-24'!$A:$D),FALSE),0) -> 0 | I14: =IFERROR(VLOOKUP($B14,'IS Q3-24'!$A:$J,COLUMNS('IS Q3-24'!$A:$D),FALSE),0) -> 0 | J14: 0 | K14: 0 | L14: 0 | M14: 0 | N14: 0 | O14: 0 | P14: 0 | Q14: 0
B15: Income from operations | C15: =IFERROR(VLOOKUP($B15,'IS FY21'!$A:$G,COLUMNS('IS FY21'!$A:$G),FALSE),0) -> 350740 | D15: =IFERROR(VLOOKUP($B15,'IS FY21'!$A:$G,COLUMNS('IS FY21'!$A:$D),FALSE),0) -> 301769 | E15: =IFERROR(VLOOKUP($B15,'IS FY23'!$A:$J,COLUMNS('IS FY23'!$A:$J),FALSE),0) -> 468713 | F15: =IFERROR(VLOOKUP($B15,'IS FY23'!$A:$J,COLUMNS('IS FY23'!$A:$D),FALSE),0) -> 483733 | G15: =IFERROR(VLOOKUP($B15,'IS Q1-24'!$A:$J,COLUMNS('IS Q1-24'!$A:$D),FALSE),0) -> 101568 | H15: =IFERROR(VLOOKUP($B15,'IS Q2-24'!$A:$J,COLUMNS('IS Q2-24'!$A:$D),FALSE),0) -> 91195 | I15: =IFERROR(VLOOKUP($B15,'IS Q3-24'!$A:$J,COLUMNS('IS Q3-24'!$A:$D),FALSE),0) -> 106766 | J15: =J8-SUM(J11:J14) -> 100125.83 | K15: =K8-SUM(K11:K14) -> 411881.44 | L15: =L8-SUM(L11:L14) -> 431392.24 | M15: =M8-SUM(M11:M14) -> 440889.83 | N15: =N8-SUM(N11:N14) -> 440373.85 | O15: =O8-SUM(O11:O14) -> 449843.95 | P15: =P8-SUM(P11:P14) -> 439299.73 | Q15: =Q8-SUM(Q11:Q14) -> 438740.83
B16: OpEx / Revenue | C16: =C11/C6 -> 0.30558618 | D16: =D11/D6 -> 0.30662945 | E16: =E11/E6 -> 0.29357893 | F16: =F11/F6 -> 0.2871574 | G16: =G11/G6 -> 0.30465665 | H16: =H11/H6 -> 0.3113654 | I16: =I11/I6 -> 0.29508449 | J16: =J11/J6 -> 0.30020203 | K16: =AVERAGE($C$16:$J$16) -> 0.30053257 | L16: =AVERAGE($C$16:$J$16) -> 0.30053257 | M16: =AVERAGE($C$16:$J$16) -> 0.30053257 | N16: =AVERAGE($C$16:$J$16) -> 0.30053257 | O16: =AVERAGE($C$16:$J$16) -> 0.30053257 | P16: =AVERAGE($C$16:$J$16) -> 0.30053257 | Q16: =AVERAGE($C$16:$J$16) -> 0.30053257
B18: Other income (expense): | C18: =IFERROR(VLOOKUP($B18,'IS FY21'!$A:$G,COLUMNS('IS FY21'!$A:$G),FALSE),0) -> 0 | D18: =IFERROR(VLOOKUP($B18,'IS FY21'!$A:$G,COLUMNS('IS FY21'!$A:$D),FALSE),0) -> 0 | E18: =IFERROR(VLOOKUP($B18,'IS FY23'!$A:$J,COLUMNS('IS FY23'!$A:$J),FALSE),0) -> 0 | F18: =IFERROR(VLOOKUP($B18,'IS FY23'!$A:$J,COLUMNS('IS FY23'!$A:$D),FALSE),0) -> 0 | G18: =IFERROR(VLOOKUP($B18,'IS Q1-24'!$A:$J,COLUMNS('IS Q1-24'!$A:$D),FALSE),0) -> 0 | H18: =IFERROR(VLOOKUP($B18,'IS Q2-24'!$A:$J,COLUMNS('IS Q2-24'!$A:$D),FALSE),0) -> 0 | I18: =IFERROR(VLOOKUP($B18,'IS Q3-24'!$A:$J,COLUMNS('IS Q3-24'!$A:$D),FALSE),0) -> 0 | J18: 0 | K18: 0 | L18: 0 | M18: 0 | N18: 0 | O18: 0 | P18: 0 | Q18: 0
B19: Interest expense | C19: =IFERROR(VLOOKUP($B19,'IS FY21'!$A:$G,COLUMNS('IS FY21'!$A:$G),FALSE),0) -> -16673 | D19: =IFERROR(VLOOKUP($B19,'IS FY21'!$A:$G,COLUMNS('IS FY21'!$A:$D),FALSE),0) -> -14510 | E19: =IFERROR(VLOOKUP($B19,'IS FY23'!$A:$J,COLUMNS('IS FY23'!$A:$J),FALSE),0) -> -17599 | F19: =IFERROR(VLOOKUP($B19,'IS FY23'!$A:$J,COLUMNS('IS FY23'!$A:$D),FALSE),0) -> -22543 | G19: =IFERROR(VLOOKUP($B19,'IS Q1-24'!$A:$J,COLUMNS('IS Q1-24'!$A:$D),FALSE),0) -> -5320 | H19: =IFERROR(VLOOKUP($B19,'IS Q2-24'!$A:$J,COLUMNS('IS Q2-24'!$A:$D),FALSE),0) -> -6951 | I19: =IFERROR(VLOOKUP($B19,'IS Q3-24'!$A:$J,COLUMNS('IS Q3-24'!$A:$D),FALSE),0) -> -6884 | J19: =-'Balance Sheet NWC (Base)'!I25*($J$2/4) -> 0 | K19: =-'Balance Sheet NWC (Base)'!J25*($J$2) -> 0 | L19: =-'Balance Sheet NWC (Base)'!K25*($J$2) -> 0 | M19: =-'Balance Sheet NWC (Base)'!L25*($J$2) -> 0 | N19: =-'Balance Sheet NWC (Base)'!M25*($J$2) -> 0 | O19: =-'Balance Sheet NWC (Base)'!N25*($J$2) -> 0 | P19: =-'Balance Sheet NWC (Base)'!O25*($J$2) -> 0 | Q19: =-'Balance Sheet NWC (Base)'!P25*($J$2) -> 0
B20: Interest income | C20: =IFERROR(VLOOKUP($B20,'IS FY21'!$A:$G,COLUMNS('IS FY21'!$A:$G),FALSE),0) -> 333 | D20: =IFERROR(VLOOKUP($B20,'IS FY21'!$A:$G,COLUMNS('IS FY21'!$A:$D),FALSE),0) -> 66 | E20: =IFERROR(VLOOKUP($B20,'IS FY23'!$A:$J,COLUMNS('IS FY23'!$A:$J),FALSE),0) -> 150 | F20: =IFERROR(VLOOKUP($B20,'IS FY23'!$A:$J,COLUMNS('IS FY23'!$A:$D),FALSE),0) -> 1034 | G20: =IFERROR(VLOOKUP($B20,'IS Q1-24'!$A:$J,COLUMNS('IS Q1-24'!$A:$D),FALSE),0) -> 125 | H20: =IFERROR(VLOOKUP($B20,'IS Q2-24'!$A:$J,COLUMNS('IS Q2-24'!$A:$D),FALSE),0) -> 43 | I20: =IFERROR(VLOOKUP($B20,'IS Q3-24'!$A:$J,COLUMNS('IS Q3-24'!$A:$D),FALSE),0) -> 134 | J20: {=(AVERAGE(G20:I20,C20:F20/4))} -> 99.678571 | K20: =AVERAGE(SUM($G20:$J20),$C20:$F20)*(1+$M$2) -> 407.65298 | L20: =K20*(1+$M$2) -> 418.65961 | M20: =L20*(1+$M$2) -> 429.96342 | N20: =M20*(1+$M$2) -> 441.57243 | O20: =N20*(1+$M$2) -> 453.49489 | P20: =O20*(1+$M$2) -> 465.73925 | Q20: =P20*(1+$M$2) -> 478.31421
B21: Other income (expense), net | C21: =IFERROR(VLOOKUP($B21,'IS FY21'!$A:$G,COLUMNS('IS FY21'!$A:$G),FALSE),0) -> -150 | D21: =IFERROR(VLOOKUP($B21,'IS FY21'!$A:$G,COLUMNS('IS FY21'!$A:$D),FALSE),0) -> 1054 | E21: =IFERROR(VLOOKUP($B21,'IS FY23'!$A:$J,COLUMNS('IS FY23'!$A:$J),FALSE),0) -> -132 | F21: =IFERROR(VLOOKUP($B21,'IS FY23'!$A:$J,COLUMNS('IS FY23'!$A:$D),FALSE),0) -> -6068 | G21: =IFERROR(VLOOKUP($B21,'IS Q1-24'!$A:$J,COLUMNS('IS Q1-24'!$A:$D),FALSE),0) -> -5055 | H21: =IFERROR(VLOOKUP($B21,'IS Q2-24'!$A:$J,COLUMNS('IS Q2-24'!$A:$D),FALSE),0) -> -4332 | I21: =IFERROR(VLOOKUP($B21,'IS Q3-24'!$A:$J,COLUMNS('IS Q3-24'!$A:$D),FALSE),0) -> -4680 | J21: {=(AVERAGE(G21:I21,C21:F21/4))} -> -2198.7143 | K21: =AVERAGE(SUM($G21:$J21),$C21:$F21)*(1+$M$2) -> -4428.7761 | L21: =K21*(1+$M$2) -> -4548.3531 | M21: =L21*(1+$M$2) -> -4671.1586 | N21: =M21*(1+$M$2) -> -4797.2799 | O21: =N21*(1+$M$2) -> -4926.8064 | P21: =O21*(1+$M$2) -> -5059.8302 | Q21: =P21*(1+$M$2) -> -5196.4456
B22: Total other expense | C22: =IFERROR(VLOOKUP($B22,'IS FY21'!$A:$G,COLUMNS('IS FY21'!$A:$G),FALSE),0) -> -16490 | D22: =IFERROR(VLOOKUP($B22,'IS FY21'!$A:$G,COLUMNS('IS FY21'!$A:$D),FALSE),0) -> -13390 | E22: =IFERROR(VLOOKUP($B22,'IS FY23'!$A:$J,COLUMNS('IS FY23'!$A:$J),FALSE),0) -> -17581 | F22: =IFERROR(VLOOKUP($B22,'IS FY23'!$A:$J,COLUMNS('IS FY23'!$A:$D),FALSE),0) -> -27577 | G22: =IFERROR(VLOOKUP($B22,'IS Q1-24'!$A:$J,COLUMNS('IS Q1-24'!$A:$D),FALSE),0) -> -10250 | H22: =IFERROR(VLOOKUP($B22,'IS Q2-24'!$A:$J,COLUMNS('IS Q2-24'!$A:$D),FALSE),0) -> -11240 | I22: =IFERROR(VLOOKUP($B22,'IS Q3-24'!$A:$J,COLUMNS('IS Q3-24'!$A:$D),FALSE),0) -> -11430 | J22: =J19+J20+J21 -> -2099.0357 | K22: =SUM(K18:K21) -> -4021.1231 | L22: =SUM(L18:L21) -> -4129.6935 | M22: =SUM(M18:M21) -> -4241.1952 | N22: =SUM(N18:N21) -> -4355.7075 | O22: =SUM(O18:O21) -> -4473.3116 | P22: =SUM(P18:P21) -> -4594.091 | Q22: =SUM(Q18:Q21) -> -4718.1314
B23: Income before provision for income taxes | C23: =IFERROR(VLOOKUP($B23,'IS FY21'!$A:$G,COLUMNS('IS FY21'!$A:$G),FALSE),0) -> 334250 | D23: =IFERROR(VLOOKUP($B23,'IS FY21'!$A:$G,COLUMNS('IS FY21'!$A:$D),FALSE),0) -> 288379 | E23: =IFERROR(VLOOKUP($B23,'IS FY23'!$A:$J,COLUMNS('IS FY23'!$A:$J),FALSE),0) -> 451132 | F23: =IFERROR(VLOOKUP($B23,'IS FY23'!$A:$J,COLUMNS('IS FY23'!$A:$D),FALSE),0) -> 456156 | G23: =IFERROR(VLOOKUP($B23,'IS Q1-24'!$A:$J,COLUMNS('IS Q1-24'!$A:$D),FALSE),0) -> 91318 | H23: =IFERROR(VLOOKUP($B23,'IS Q2-24'!$A:$J,COLUMNS('IS Q2-24'!$A:$D),FALSE),0) -> 79955 | I23: =IFERROR(VLOOKUP($B23,'IS Q3-24'!$A:$J,COLUMNS('IS Q3-24'!$A:$D),FALSE),0) -> 95336 | J23: =J15+J22 -> 98026.789 | K23: =K15+K22 -> 407860.32 | L23: =L15+L22 -> 427262.54 | M23: =M15+M22 -> 436648.63 | N23: =N15+N22 -> 436018.15 | O23: =O15+O22 -> 445370.64 | P23: =P15+P22 -> 434705.64 | Q23: =Q15+Q22 -> 434022.7
B24: Provision for income taxes | C24: =IFERROR(VLOOKUP($B24,'IS FY21'!$A:$G,COLUMNS('IS FY21'!$A:$G),FALSE),0) -> 82492 | D24: =IFERROR(VLOOKUP($B24,'IS FY21'!$A:$G,COLUMNS('IS FY21'!$A:$D),FALSE),0) -> 70442 | E24: =IFERROR(VLOOKUP($B24,'IS FY23'!$A:$J,COLUMNS('IS FY23'!$A:$J),FALSE),0) -> 110650 | F24: =IFERROR(VLOOKUP($B24,'IS FY23'!$A:$J,COLUMNS('IS FY23'!$A:$D),FALSE),0) -> 113049 | G24: =IFERROR(VLOOKUP($B24,'IS Q1-24'!$A:$J,COLUMNS('IS Q1-24'!$A:$D),FALSE),0) -> 22190 | H24: =IFERROR(VLOOKUP($B24,'IS Q2-24'!$A:$J,COLUMNS('IS Q2-24'!$A:$D),FALSE),0) -> 18390 | I24: =IFERROR(VLOOKUP($B24,'IS Q3-24'!$A:$J,COLUMNS('IS Q3-24'!$A:$D),FALSE),0) -> 24024 | J24: =(AVERAGE(G24:I24)) -> 21534.667 | K24: =K23*K26 -> 98337.339 | L24: =L23*L26 -> 103015.32 | M24: =M23*M26 -> 105278.36 | N24: =N23*N26 -> 105126.35 | O24: =O23*O26 -> 107381.28 | P24: =P23*P26 -> 104809.89 | Q24: =Q23*Q26 -> 104645.23
B25: Net income | C25: =IFERROR(VLOOKUP($B25,'IS FY21'!$A:$G,COLUMNS('IS FY21'!$A:$G),FALSE),0) -> 251758 | D25: =IFERROR(VLOOKUP($B25,'IS FY21'!$A:$G,COLUMNS('IS FY21'!$A:$D),FALSE),0) -> 217937 | E25: =IFERROR(VLOOKUP($B25,'IS FY23'!$A:$J,COLUMNS('IS FY23'!$A:$J),FALSE),0) -> 340482 | F25: =IFERROR(VLOOKUP($B25,'IS FY23'!$A:$J,COLUMNS('IS FY23'!$A:$D),FALSE),0) -> 343107 | G25: =IFERROR(VLOOKUP($B25,'IS Q1-24'!$A:$J,COLUMNS('IS Q1-24'!$A:$D),FALSE),0) -> 69128 | H25: =IFERROR(VLOOKUP($B25,'IS Q2-24'!$A:$J,COLUMNS('IS Q2-24'!$A:$D),FALSE),0) -> 61565 | I25: =IFERROR(VLOOKUP($B25,'IS Q3-24'!$A:$J,COLUMNS('IS Q3-24'!$A:$D),FALSE),0) -> 71312 | J25: =J23-J24 -> 76492.123 | K25: =K23-K24 -> 309522.98 | L25: =L23-L24 -> 324247.22 | M25: =M23-M24 -> 331370.27 | N25: =N23-N24 -> 330891.8 | O25: =O23-O24 -> 337989.35 | P25: =P23-P24 -> 329895.75 | Q25: =Q23-Q24 -> 329377.46
B26: Provision / IBT | C26: =C24/C23 -> 0.24679731 | D26: =D24/D23 -> 0.24426883 | E26: =E24/E23 -> 0.24527189 | F26: =F24/F23 -> 0.24782969 | G26: =G24/G23 -> 0.242997 | H26: =H24/H23 -> 0.23000438 | I26: =I24/I23 -> 0.25199295 | J26: =J24/J23 -> 0.21968144 | K26: =AVERAGE($C$26:$J$26) -> 0.24110544 | L26: =AVERAGE($C$26:$J$26) -> 0.24110544 | M26: =AVERAGE($C$26:$J$26) -> 0.24110544 | N26: =AVERAGE($C$26:$J$26) -> 0.24110544 | O26: =AVERAGE($C$26:$J$26) -> 0.24110544 | P26: =AVERAGE($C$26:$J$26) -> 0.24110544 | Q26: =AVERAGE($C$26:$J$26) -> 0.24110544
B28: Less: Net income (loss) attributable to noncontrolling interest | C28: =IFERROR(VLOOKUP($B28,'IS FY21'!$A:$G,COLUMNS('IS FY21'!$A:$G),FALSE),0) -> 641 | D28: =IFERROR(VLOOKUP($B28,'IS FY21'!$A:$G,COLUMNS('IS FY21'!$A:$D),FALSE),0) -> 1030 | E28: =IFERROR(VLOOKUP($B28,'IS FY23'!$A:$J,COLUMNS('IS FY23'!$A:$J),FALSE),0) -> 696 | F28: =IFERROR(VLOOKUP($B28,'IS FY23'!$A:$J,COLUMNS('IS FY23'!$A:$D),FALSE),0) -> -126 | G28: =IFERROR(VLOOKUP($B28,'IS Q1-24'!$A:$J,COLUMNS('IS Q1-24'!$A:$D),FALSE),0) -> -222 | H28: =IFERROR(VLOOKUP($B28,'IS Q2-24'!$A:$J,COLUMNS('IS Q2-24'!$A:$D),FALSE),0) -> -282 | I28: =IFERROR(VLOOKUP($B28,'IS Q3-24'!$A:$J,COLUMNS('IS Q3-24'!$A:$D),FALSE),0) -> -393 | J28: =(AVERAGE(G28:I28)) -> -299 | K28: =AVERAGE(SUM($G28:$J28),$C28:$F28)*(1+$M$2) -> 214.643 | L28: =K28*(1+$M$2) -> 220.43836 | M28: =L28*(1+$M$2) -> 226.3902 | N28: =M28*(1+$M$2) -> 232.50273 | O28: =N28*(1+$M$2) -> 238.78031 | P28: =O28*(1+$M$2) -> 245.22737 | Q28: =P28*(1+$M$2) -> 251.84851
B29: Net income attributable to MSC Industrial | C29: =IFERROR(VLOOKUP($B29,'IS FY21'!$A:$G,COLUMNS('IS FY21'!$A:$G),FALSE),0) -> 251117 | D29: =IFERROR(VLOOKUP($B29,'IS FY21'!$A:$G,COLUMNS('IS FY21'!$A:$D),FALSE),0) -> 216907 | E29: =IFERROR(VLOOKUP($B29,'IS FY23'!$A:$J,COLUMNS('IS FY23'!$A:$J),FALSE),0) -> 339786 | F29: =IFERROR(VLOOKUP($B29,'IS FY23'!$A:$J,COLUMNS('IS FY23'!$A:$D),FALSE),0) -> 343233 | G29: =IFERROR(VLOOKUP($B29,'IS Q1-24'!$A:$J,COLUMNS('IS Q1-24'!$A:$D),FALSE),0) -> 69350 | H29: =IFERROR(VLOOKUP($B29,'IS Q2-24'!$A:$J,COLUMNS('IS Q2-24'!$A:$D),FALSE),0) -> 61847 | I29: =IFERROR(VLOOKUP($B29,'IS Q3-24'!$A:$J,COLUMNS('IS Q3-24'!$A:$D),FALSE),0) -> 71705 | J29: =J25-J28 -> 76791.123 | K29: =K25-K28 -> 309308.33 | L29: =L25-L28 -> 324026.78 | M29: =M25-M28 -> 331143.88 | N29: =N25-N28 -> 330659.3 | O29: =O25-O28 -> 337750.57 | P29: =P25-P28 -> 329650.52 | Q29: =Q25-Q28 -> 329125.62
B30: Per share data attributable to MSC Industrial: | C30: =IFERROR(VLOOKUP($B30,'IS FY21'!$A:$G,COLUMNS('IS FY21'!$A:$G),FALSE),0) -> 0 | D30: =IFERROR(VLOOKUP($B30,'IS FY21'!$A:$G,COLUMNS('IS FY21'!$A:$D),FALSE),0) -> 0 | E30: =IFERROR(VLOOKUP($B30,'IS FY23'!$A:$J,COLUMNS('IS FY23'!$A:$J),FALSE),0) -> 0 | F30: =IFERROR(VLOOKUP($B30,'IS FY23'!$A:$J,COLUMNS('IS FY23'!$A:$D),FALSE),0) -> 0 | G30: =IFERROR(VLOOKUP($B30,'IS Q1-24'!$A:$J,COLUMNS('IS Q1-24'!$A:$D),FALSE),0) -> 0 | H30: =IFERROR(VLOOKUP($B30,'IS Q2-24'!$A:$J,COLUMNS('IS Q2-24'!$A:$D),FALSE),0) -> 0 | I30: =IFERROR(VLOOKUP($B30,'IS Q3-24'!$A:$J,COLUMNS('IS Q3-24'!$A:$D),FALSE),0) -> 0 | J30: =I30 -> 0
B31: Net income per common share: | C31: =IFERROR(VLOOKUP($B31,'IS FY21'!$A:$G,COLUMNS('IS FY21'!$A:$G),FALSE),0) -> 0 | D31: =IFERROR(VLOOKUP($B31,'IS FY21'!$A:$G,COLUMNS('IS FY21'!$A:$D),FALSE),0) -> 0 | E31: =IFERROR(VLOOKUP($B31,'IS FY23'!$A:$J,COLUMNS('IS FY23'!$A:$J),FALSE),0) -> 0 | F31: =IFERROR(VLOOKUP($B31,'IS FY23'!$A:$J,COLUMNS('IS FY23'!$A:$D),FALSE),0) -> 0 | G31: =IFERROR(VLOOKUP($B31,'IS Q1-24'!$A:$J,COLUMNS('IS Q1-24'!$A:$D),FALSE),0) -> 0 | H31: =IFERROR(VLOOKUP($B31,'IS Q2-24'!$A:$J,COLUMNS('IS Q2-24'!$A:$D),FALSE),0) -> 0 | I31: =IFERROR(VLOOKUP($B31,'IS Q3-24'!$A:$J,COLUMNS('IS Q3-24'!$A:$D),FALSE),0) -> 0 | J31: =I31 -> 0
B32: Basic | C32: =IFERROR(VLOOKUP($B32,'IS FY21'!$A:$G,COLUMNS('IS FY21'!$A:$G),FALSE),0) -> 4.53 | D32: =IFERROR(VLOOKUP($B32,'IS FY21'!$A:$G,COLUMNS('IS FY21'!$A:$D),FALSE),0) -> 3.89 | E32: =IFERROR(VLOOKUP($B32,'IS FY23'!$A:$J,COLUMNS('IS FY23'!$A:$J),FALSE),0) -> 6.09 | F32: =IFERROR(VLOOKUP($B32,'IS FY23'!$A:$J,COLUMNS('IS FY23'!$A:$D),FALSE),0) -> 6.14 | G32: =IFERROR(VLOOKUP($B32,'IS Q1-24'!$A:$J,COLUMNS('IS Q1-24'!$A:$D),FALSE),0) -> 1.23 | H32: =IFERROR(VLOOKUP($B32,'IS Q2-24'!$A:$J,COLUMNS('IS Q2-24'!$A:$D),FALSE),0) -> 1.1 | I32: =IFERROR(VLOOKUP($B32,'IS Q3-24'!$A:$J,COLUMNS('IS Q3-24'!$A:$D),FALSE),0) -> 1.28 | J32: =I32 -> 1.28
B33: Diluted | C33: =IFERROR(VLOOKUP($B33,'IS FY21'!$A:$G,COLUMNS('IS FY21'!$A:$G),FALSE),0) -> 4.51 | D33: =IFERROR(VLOOKUP($B33,'IS FY21'!$A:$G,COLUMNS('IS FY21'!$A:$D),FALSE),0) -> 3.87 | E33: =IFERROR(VLOOKUP($B33,'IS FY23'!$A:$J,COLUMNS('IS FY23'!$A:$J),FALSE),0) -> 6.06 | F33: =IFERROR(VLOOKUP($B33,'IS FY23'!$A:$J,COLUMNS('IS FY23'!$A:$D),FALSE),0) -> 6.11 | G33: =IFERROR(VLOOKUP($B33,'IS Q1-24'!$A:$J,COLUMNS('IS Q1-24'!$A:$D),FALSE),0) -> 1.22 | H33: =IFERROR(VLOOKUP($B33,'IS Q2-24'!$A:$J,COLUMNS('IS Q2-24'!$A:$D),FALSE),0) -> 1.1 | I33: =IFERROR(VLOOKUP($B33,'IS Q3-24'!$A:$J,COLUMNS('IS Q3-24'!$A:$D),FALSE),0) -> 1.27 | J33: =I33 -> 1.27
B34: Weighted-average shares used in computing net income per common share: | C34: =IFERROR(VLOOKUP($B34,'IS FY21'!$A:$G,COLUMNS('IS FY21'!$A:$G),FALSE),0) -> 0 | D34: =IFERROR(VLOOKUP($B34,'IS FY21'!$A:$G,COLUMNS('IS FY21'!$A:$D),FALSE),0) -> 0 | E34: =IFERROR(VLOOKUP($B34,'IS FY23'!$A:$J,COLUMNS('IS FY23'!$A:$J),FALSE),0) -> 0 | F34: =IFERROR(VLOOKUP($B34,'IS FY23'!$A:$J,COLUMNS('IS FY23'!$A:$D),FALSE),0) -> 0 | G34: =IFERROR(VLOOKUP($B34,'IS Q1-24'!$A:$J,COLUMNS('IS Q1-24'!$A:$D),FALSE),0) -> 0 | H34: =IFERROR(VLOOKUP($B34,'IS Q2-24'!$A:$J,COLUMNS('IS Q2-24'!$A:$D),FALSE),0) -> 0 | I34: =IFERROR(VLOOKUP($B34,'IS Q3-24'!$A:$J,COLUMNS('IS Q3-24'!$A:$D),FALSE),0) -> 0 | J34: =I34 -> 0
B35: Basic Weighted Average | C35: =IFERROR(VLOOKUP($B35,'IS FY21'!$A:$G,COLUMNS('IS FY21'!$A:$G),FALSE),0) -> 55472 | D35: =IFERROR(VLOOKUP($B35,'IS FY21'!$A:$G,COLUMNS('IS FY21'!$A:$D),FALSE),0) -> 55737 | E35: =IFERROR(VLOOKUP($B35,'IS FY23'!$A:$J,COLUMNS('IS FY23'!$A:$J),FALSE),0) -> 55777 | F35: =IFERROR(VLOOKUP($B35,'IS FY23'!$A:$J,COLUMNS('IS FY23'!$A:$D),FALSE),0) -> 55918 | G35: =IFERROR(VLOOKUP($B35,'IS Q1-24'!$A:$J,COLUMNS('IS Q1-24'!$A:$D),FALSE),0) -> 56429 | H35: =IFERROR(VLOOKUP($B35,'IS Q2-24'!$A:$J,COLUMNS('IS Q2-24'!$A:$D),FALSE),0) -> 56325 | I35: =IFERROR(VLOOKUP($B35,'IS Q3-24'!$A:$J,COLUMNS('IS Q3-24'!$A:$D),FALSE),0) -> 56214 | J35: =I35/H35*I35 -> 56103.219
B36: Diluted Weighted Average | C36: =IFERROR(VLOOKUP($B36,'IS FY21'!$A:$G,COLUMNS('IS FY21'!$A:$G),FALSE),0) -> 55643 | D36: =IFERROR(VLOOKUP($B36,'IS FY21'!$A:$G,COLUMNS('IS FY21'!$A:$D),FALSE),0) -> 56093 | E36: =IFERROR(VLOOKUP($B36,'IS FY23'!$A:$J,COLUMNS('IS FY23'!$A:$J),FALSE),0) -> 56045 | F36: =IFERROR(VLOOKUP($B36,'IS FY23'!$A:$J,COLUMNS('IS FY23'!$A:$D),FALSE),0) -> 56210 | G36: =IFERROR(VLOOKUP($B36,'IS Q1-24'!$A:$J,COLUMNS('IS Q1-24'!$A:$D),FALSE),0) -> 56723 | H36: =IFERROR(VLOOKUP($B36,'IS Q2-24'!$A:$J,COLUMNS('IS Q2-24'!$A:$D),FALSE),0) -> 56467 | I36: =IFERROR(VLOOKUP($B36,'IS Q3-24'!$A:$J,COLUMNS('IS Q3-24'!$A:$D),FALSE),0) -> 56351 | J36: =I36/H36*I36 -> 56235.238
C38: =SUM(C6:C36) -> 8726523 | D38: =SUM(D6:D36) -> 8699716.7 | E38: =SUM(E6:E36) -> 10261453 | F38: =SUM(F6:F36) -> 10973935 | G38: =SUM(G6:G36) -> 2645474.4 | H38: =SUM(H6:H36) -> 2571097.2 | I38: =SUM(I6:I36) -> 2710839.5
B39: Check | C39: ='IS FY21'!G36 -> 8726522 | D39: ='IS FY21'!D36 -> 8699715.8 | E39: ='IS FY23'!J33 -> 10261452 | F39: ='IS FY23'!D33 -> 10973934 | G39: ='IS Q1-24'!D32 -> 2645473.5 | H39: ='IS Q2-24'!D32 -> 2571096.2 | I39: ='IS Q3-24'!D32 -> 2710838.5
C40: =C38-C39-C9-C16-C26 -> -3.4321257e-10 | D40: =D38-D39-D9-D16-D26 -> 2.8502517e-10 | E40: =E38-E39-E9-E16-E26 -> -1.1920669e-09 | F40: =F38-F39-F9-F16-F26 -> 8.868975e-10 | G40: =G38-G39-G9-G16-G26 -> 4.2749249e-11 | H40: =H38-H39-H9-H16-H26 -> 4.2146325e-10 | I40: =I38-I39-I9-I16-I26 -> 1.9974078e-11

Sheet Balance Sheet NWC (Base)
B2: Revenue | J2: ='3-Statement (Base)'!J9 -> 952178.75 | K2: ='3-Statement (Base)'!K9 -> 3820845.7 | L2: ='3-Statement (Base)'!L9 -> 3800977.3 | M2: ='3-Statement (Base)'!M9 -> 3978863.1 | N2: ='3-Statement (Base)'!N9 -> 4240672.3 | O2: ='3-Statement (Base)'!O9 -> 4373829.4 | P2: ='3-Statement (Base)'!P9 -> 4592520.9 | Q2: ='3-Statement (Base)'!Q9 -> 4765934.4 | R2: ='3-Statement (Base)'!R9 -> 4986845
B3: NWC % Revenue | J3: ='3-Statement (Base)'!J21 -> 0.22166298 | K3: ='3-Statement (Base)'!K21 -> 0.22095922 | L3: ='3-Statement (Base)'!L21 -> 0.21622922 | M3: ='3-Statement (Base)'!M21 -> 0.21622922 | N3: ='3-Statement (Base)'!N21 -> 0.21780589 | O3: ='3-Statement (Base)'!O21 -> 0.21675477 | P3: ='3-Statement (Base)'!P21 -> 0.21692996 | Q3: ='3-Statement (Base)'!Q21 -> 0.21716354 | R3: ='3-Statement (Base)'!R21 -> 0.21694942
C4: ='3-Statement (Base)'!C2 -> 44196 | D4: ='3-Statement (Base)'!D2 -> 44561 | E4: ='3-Statement (Base)'!E2 -> 44926 | F4: ='3-Statement (Base)'!F2 -> 45291 | G4: ='3-Statement (Base)'!G2 -> Q1-24 | H4: ='3-Statement (Base)'!H2 -> Q2-24 | I4: ='3-Statement (Base)'!I2 -> Q3-24 | J4: ='3-Statement (Base)'!J2 -> Q4-24 | ... R4: ='3-Statement (Base)'!R2 -> 48213
B5: ASSETS
B6: Current Assets:
B7: Cash and cash equivalents | C7: =IFERROR(VLOOKUP($B7,'BS FY21'!$A:$F,COLUMNS('BS FY21'!$A:$F),FALSE),0) -> 125211 | D7: =IFERROR(VLOOKUP($B7,'BS FY21'!$A:$F,COLUMNS('BS FY21'!$A:$C),FALSE),0) -> 40536 | E7: =IFERROR(VLOOKUP($B7,'BS FY23'!$A:$J,COLUMNS('BS FY23'!$A:$J),FALSE),0) -> 43537 | F7: =IFERROR(VLOOKUP($B7,'BS FY23'!$A:$J,COLUMNS('BS FY23'!$A:$D),FALSE),0) -> 50052 | G7: =IFERROR(VLOOKUP($B7,'BS Q1-24'!$A:$J,COLUMNS('BS Q1-24'!$A:$D),FALSE),0) -> 25805 | H7: =IFERROR(VLOOKUP($B7,'BS Q2-24'!$A:$J,COLUMNS('BS Q2-24'!$A:$D),FALSE),0) -> 22227 | I7: =IFERROR(VLOOKUP($B7,'BS Q3-24'!$A:$J,COLUMNS('BS Q3-24'!$A:$D),FALSE),0) -> 25928 | J7: ='3-Statement (Base)'!J68 -> 25000 | K7: ='3-Statement (Base)'!K68 -> 25000 | L7: ='3-Statement (Base)'!L68 -> 25000 | M7: ='3-Statement (Base)'!M68 -> 25000 | N7: ='3-Statement (Base)'!N68 -> 25000 | O7: ='3-Statement (Base)'!O68 -> 25000 | P7: ='3-Statement (Base)'!P68 -> 25000 | Q7: ='3-Statement (Base)'!Q68 -> 25000 | R7: ='3-Statement (Base)'!R68 -> 25000
B8: Accounts receivable | C8: =IFERROR(VLOOKUP($B8,'BS FY21'!$A:$F,COLUMNS('BS FY21'!$A:$F),FALSE),0) -> 491743 | D8: =IFERROR(VLOOKUP($B8,'BS FY21'!$A:$F,COLUMNS('BS FY21'!$A:$C),FALSE),0) -> 560373 | E8: =IFERROR(VLOOKUP($B8,'BS FY23'!$A:$J,COLUMNS('BS FY23'!$A:$J),FALSE),0) -> 687608 | F8: =IFERROR(VLOOKUP($B8,'BS FY23'!$A:$J,COLUMNS('BS FY23'!$A:$D),FALSE),0) -> 435421 | G8: =IFERROR(VLOOKUP($B8,'BS Q1-24'!$A:$J,COLUMNS('BS Q1-24'!$A:$D),FALSE),0) -> 414280 | H8: =IFERROR(VLOOKUP($B8,'BS Q2-24'!$A:$J,COLUMNS('BS Q2-24'!$A:$D),FALSE),0) -> 428699 | I8: =IFERROR(VLOOKUP($B8,'BS Q3-24'!$A:$J,COLUMNS('BS Q3-24'!$A:$D),FALSE),0) -> 419810 | J8: =I8/I$49*J$49 -> 437700.67 | K8: =J8/J$49*K$49 -> 437700.67 | L8: =K8/K$49*L$49 -> 426103.63 | M8: =L8/L$49*M$49 -> 446045.28 | N8: =M8/M$49*N$49 -> 478861.48 | O8: =N8/N$49*O$49 -> 491514.22 | P8: =O8/O$49*P$49 -> 516507.05 | Q8: =P8/P$49*Q$49 -> 536587.5 | R8: =Q8/Q$49*R$49 -> 560905.83
B9: Inventories | C9: =IFERROR(VLOOKUP($B9,'BS FY21'!$A:$F,COLUMNS('BS FY21'!$A:$F),FALSE),0) -> 543106 | D9: =IFERROR(VLOOKUP($B9,'BS FY21'!$A:$F,COLUMNS('BS FY21'!$A:$C),FALSE),0) -> 624169 | E9: =IFERROR(VLOOKUP($B9,'BS FY23'!$A:$J,COLUMNS('BS FY23'!$A:$J),FALSE),0) -> 715625 | F9: =IFERROR(VLOOKUP($B9,'BS FY23'!$A:$J,COLUMNS('BS FY23'!$A:$D),FALSE),0) -> 726521 | G9: =IFERROR(VLOOKUP($B9,'BS Q1-24'!$A:$J,COLUMNS('BS Q1-24'!$A:$D),FALSE),0) -> 709362 | H9: =IFERROR(VLOOKUP($B9,'BS Q2-24'!$A:$J,COLUMNS('BS Q2-24'!$A:$D),FALSE),0) -> 685373 | I9: =IFERROR(VLOOKUP($B9,'BS Q3-24'!$A:$J,COLUMNS('BS Q3-24'!$A:$D),FALSE),0) -> 665638 | J9: =I9/I$49*J$49 -> 694004.91 | K9: =J9/J$49*K$49 -> 694004.91 | L9: =K9/K$49*L$49 -> 675616.99 | M9: =L9/L$49*M$49 -> 707235.87 | N9: =M9/M$49*N$49 -> 759268.23 | O9: =N9/N$49*O$49 -> 779330.04 | P9: =O9/O$49*P$49 -> 818957.9 | Q9: =P9/P$49*Q$49 -> 850796.87 | R9: =Q9/Q$49*R$49 -> 889355.27
B10: Prepaid expenses and other current assets | C10: =IFERROR(VLOOKUP($B10,'BS FY21'!$A:$F,COLUMNS('BS FY21'!$A:$F),FALSE),0) -> 77710 | D10: =IFERROR(VLOOKUP($B10,'BS FY21'!$A:$F,COLUMNS('BS FY21'!$A:$C),FALSE),0) -> 89167 | E10: =IFERROR(VLOOKUP($B10,'BS FY23'!$A:$J,COLUMNS('BS FY23'!$A:$J),FALSE),0) -> 96853 | F10: =IFERROR(VLOOKUP($B10,'BS FY23'!$A:$J,COLUMNS('BS FY23'!$A:$D),FALSE),0) -> 105519 | G10: =IFERROR(VLOOKUP($B10,'BS Q1-24'!$A:$J,COLUMNS('BS Q1-24'!$A:$D),FALSE),0) -> 121519 | H10: =IFERROR(VLOOKUP($B10,'BS Q2-24'!$A:$J,COLUMNS('BS Q2-24'!$A:$D),FALSE),0) -> 128614 | I10: =IFERROR(VLOOKUP($B10,'BS Q3-24'!$A:$J,COLUMNS('BS Q3-24'!$A:$D),FALSE),0) -> 101472 | J10: =I10/I$49*J$49 -> 105796.34 | K10: =J10/J$49*K$49 -> 105796.34 | L10: =K10/K$49*L$49 -> 102993.23 | M10: =L10/L$49*M$49 -> 107813.31 | N10: =M10/M$49*N$49 -> 115745.29 | O10: =N10/N$49*O$49 -> 118803.58 | P10: =O10/O$49*P$49 -> 124844.58 | Q10: =P10/P$49*Q$49 -> 129698.21 | R10: =Q10/Q$49*R$49 -> 135576.18
B11: Total current assets | C11: =IFERROR(VLOOKUP($B11,'BS FY21'!$A:$F,COLUMNS('BS FY21'!$A:$F),FALSE),0) -> 1237770 | D11: =IFERROR(VLOOKUP($B11,'BS FY21'!$A:$F,COLUMNS('BS FY21'!$A:$C),FALSE),0) -> 1314245 | E11: =IFERROR(VLOOKUP($B11,'BS FY23'!$A:$J,COLUMNS('BS FY23'!$A:$J),FALSE),0) -> 1543623 | F11: =IFERROR(VLOOKUP($B11,'BS FY23'!$A:$J,COLUMNS('BS FY23'!$A:$D),FALSE),0) -> 1317513 | G11: =IFERROR(VLOOKUP($B11,'BS Q1-24'!$A:$J,COLUMNS('BS Q1-24'!$A:$D),FALSE),0) -> 1270966 | H11: =IFERROR(VLOOKUP($B11,'BS Q2-24'!$A:$J,COLUMNS('BS Q2-24'!$A:$D),FALSE),0) -> 1264913 | I11: =IFERROR(VLOOKUP($B11,'BS Q3-24'!$A:$J,COLUMNS('BS Q3-24'!$A:$D),FALSE),0) -> 1212848 | J11: =((I11-I7)/I49)*J49+J7 -> 1262501.9 | K11: =((J11-J7)/J49)*K49+K7 -> 1262501.9 | L11: =((K11-K7)/K49)*L49+L7 -> 1229713.9 | M11: =((L11-L7)/L49)*M49+M7 -> 1286094.5 | N11: =((M11-M7)/M49)*N49+N7 -> 1378875 | O11: =((N11-N7)/N49)*O49+O7 -> 1414647.8 | P11: =((O11-O7)/O49)*P49+P7 -> 1485309.5 | Q11: =((P11-P7)/P49)*Q49+Q7 -> 1542082.6 | R11: =((Q11-Q7)/Q49)*R49+R7 -> 1610837.3
B12: Property, plant and equipment, net | C12: =IFERROR(VLOOKUP($B12,'BS FY21'!$A:$F,COLUMNS('BS FY21'!$A:$F),FALSE),0) -> 301979 | D12: =IFERROR(VLOOKUP($B12,'BS FY21'!$A:$F,COLUMNS('BS FY21'!$A:$C),FALSE),0) -> 298416 | E12: =IFERROR(VLOOKUP($B12,'BS FY23'!$A:$J,COLUMNS('BS FY23'!$A:$J),FALSE),0) -> 286666 | F12: =IFERROR(VLOOKUP($B12,'BS FY23'!$A:$J,COLUMNS('BS FY23'!$A:$D),FALSE),0) -> 319660 | G12: =IFERROR(VLOOKUP($B12,'BS Q1-24'!$A:$J,COLUMNS('BS Q1-24'!$A:$D),FALSE),0) -> 322091 | H12: =IFERROR(VLOOKUP($B12,'BS Q2-24'!$A:$J,COLUMNS('BS Q2-24'!$A:$D),FALSE),0) -> 330765 | I12: =IFERROR(VLOOKUP($B12,'BS Q3-24'!$A:$J,COLUMNS('BS Q3-24'!$A:$D),FALSE),0) -> 344787
B13: Goodwill | C13: =IFERROR(VLOOKUP($B13,'BS FY21'!$A:$F,COLUMNS('BS FY21'!$A:$F),FALSE),0) -> 677579 | D13: =IFERROR(VLOOKUP($B13,'BS FY21'!$A:$F,COLUMNS('BS FY21'!$A:$C),FALSE),0) -> 692704 | E13: =IFERROR(VLOOKUP($B13,'BS FY23'!$A:$J,COLUMNS('BS FY23'!$A:$J),FALSE),0) -> 710130 | F13: =IFERROR(VLOOKUP($B13,'BS FY23'!$A:$J,COLUMNS('BS FY23'!$A:$D),FALSE),0) -> 718174 | G13: =IFERROR(VLOOKUP($B13,'BS Q1-24'!$A:$J,COLUMNS('BS Q1-24'!$A:$D),FALSE),0) -> 718318 | H13: =IFERROR(VLOOKUP($B13,'BS Q2-24'!$A:$J,COLUMNS('BS Q2-24'!$A:$D),FALSE),0) -> 722101 | I13: =IFERROR(VLOOKUP($B13,'BS Q3-24'!$A:$J,COLUMNS('BS Q3-24'!$A:$D),FALSE),0) -> 721932
B14: Identifiable intangibles, net | C14: =IFERROR(VLOOKUP($B14,'BS FY21'!$A:$F,COLUMNS('BS FY21'!$A:$F),FALSE),0) -> 104873 | D14: =IFERROR(VLOOKUP($B14,'BS FY21'!$A:$F,COLUMNS('BS FY21'!$A:$C),FALSE),0) -> 101854 | E14: =IFERROR(VLOOKUP($B14,'BS FY23'!$A:$J,COLUMNS('BS FY23'!$A:$J),FALSE),0) -> 114328 | F14: =IFERROR(VLOOKUP($B14,'BS FY23'!$A:$J,COLUMNS('BS FY23'!$A:$D),FALSE),0) -> 110641 | G14: =IFERROR(VLOOKUP($B14,'BS Q1-24'!$A:$J,COLUMNS('BS Q1-24'!$A:$D),FALSE),0) -> 106890 | H14: =IFERROR(VLOOKUP($B14,'BS Q2-24'!$A:$J,COLUMNS('BS Q2-24'!$A:$D),FALSE),0) -> 106833 | I14: =IFERROR(VLOOKUP($B14,'BS Q3-24'!$A:$J,COLUMNS('BS Q3-24'!$A:$D),FALSE),0) -> 102854
B15: Operating lease assets | C15: =IFERROR(VLOOKUP($B15,'BS FY21'!$A:$F,COLUMNS('BS FY21'!$A:$F),FALSE),0) -> 56173 | D15: =IFERROR(VLOOKUP($B15,'BS FY21'!$A:$F,COLUMNS('BS FY21'!$A:$C),FALSE),0) -> 49011 | E15: =IFERROR(VLOOKUP($B15,'BS FY23'!$A:$J,COLUMNS('BS FY23'!$A:$J),FALSE),0) -> 64780 | F15: =IFERROR(VLOOKUP($B15,'BS FY23'!$A:$J,COLUMNS('BS FY23'!$A:$D),FALSE),0) -> 65909 | G15: =IFERROR(VLOOKUP($B15,'BS Q1-24'!$A:$J,COLUMNS('BS Q1-24'!$A:$D),FALSE),0) -> 61076 | H15: =IFERROR(VLOOKUP($B15,'BS Q2-24'!$A:$J,COLUMNS('BS Q2-24'!$A:$D),FALSE),0) -> 61943 | I15: =IFERROR(VLOOKUP($B15,'BS Q3-24'!$A:$J,COLUMNS('BS Q3-24'!$A:$D),FALSE),0) -> 60878
B16: Other assets | C16: =IFERROR(VLOOKUP($B16,'BS FY21'!$A:$F,COLUMNS('BS FY21'!$A:$F),FALSE),0) -> 4056 | D16: =IFERROR(VLOOKUP($B16,'BS FY21'!$A:$F,COLUMNS('BS FY21'!$A:$C),FALSE),0) -> 5885 | E16: =IFERROR(VLOOKUP($B16,'BS FY23'!$A:$J,COLUMNS('BS FY23'!$A:$J),FALSE),0) -> 9887 | F16: =IFERROR(VLOOKUP($B16,'BS FY23'!$A:$J,COLUMNS('BS FY23'!$A:$D),FALSE),0) -> 12237 | G16: =IFERROR(VLOOKUP($B16,'BS Q1-24'!$A:$J,COLUMNS('BS Q1-24'!$A:$D),FALSE),0) -> 14383 | H16: =IFERROR(VLOOKUP($B16,'BS Q2-24'!$A:$J,COLUMNS('BS Q2-24'!$A:$D),FALSE),0) -> 14839 | I16: =IFERROR(VLOOKUP($B16,'BS Q3-24'!$A:$J,COLUMNS('BS Q3-24'!$A:$D),FALSE),0) -> 24495
B17: Total assets | C17: =IFERROR(VLOOKUP($B17,'BS FY21'!$A:$F,COLUMNS('BS FY21'!$A:$F),FALSE),0) -> 2382430 | D17: =IFERROR(VLOOKUP($B17,'BS FY21'!$A:$F,COLUMNS('BS FY21'!$A:$C),FALSE),0) -> 2462115 | E17: =IFERROR(VLOOKUP($B17,'BS FY23'!$A:$J,COLUMNS('BS FY23'!$A:$J),FALSE),0) -> 2729414 | F17: =IFERROR(VLOOKUP($B17,'BS FY23'!$A:$J,COLUMNS('BS FY23'!$A:$D),FALSE),0) -> 2544134 | G17: =IFERROR(VLOOKUP($B17,'BS Q1-24'!$A:$J,COLUMNS('BS Q1-24'!$A:$D),FALSE),0) -> 2493724 | H17: =IFERROR(VLOOKUP($B17,'BS Q2-24'!$A:$J,COLUMNS('BS Q2-24'!$A:$D),FALSE),0) -> 2501394 | I17: =IFERROR(VLOOKUP($B17,'BS Q3-24'!$A:$J,COLUMNS('BS Q3-24'!$A:$D),FALSE),0) -> 2467794
B18: LIABILITIES AND SHAREHOLDERS’ EQUITY | C18: =IFERROR(VLOOKUP($B18,'BS FY21'!$A:$F,COLUMNS('BS FY21'!$A:$F),FALSE),0) -> 0 | D18: =IFERROR(VLOOKUP($B18,'BS FY21'!$A:$F,COLUMNS('BS FY21'!$A:$C),FALSE),0) -> 0 | E18: =IFERROR(VLOOKUP($B18,'BS FY23'!$A:$J,COLUMNS('BS FY23'!$A:$J),FALSE),0) -> 0 | F18: =IFERROR(VLOOKUP($B18,'BS FY23'!$A:$J,COLUMNS('BS FY23'!$A:$D),FALSE),0) -> 0 | G18: =IFERROR(VLOOKUP($B18,'BS Q1-24'!$A:$J,COLUMNS('BS Q1-24'!$A:$D),FALSE),0) -> 0 | H18: =IFERROR(VLOOKUP($B18,'BS Q2-24'!$A:$J,COLUMNS('BS Q2-24'!$A:$D),FALSE),0) -> 0 | I18: =IFERROR(VLOOKUP($B18,'BS Q3-24'!$A:$J,COLUMNS('BS Q3-24'!$A:$D),FALSE),0) -> 0
B19: Current Liabilities: | C19: =IFERROR(VLOOKUP($B19,'BS FY21'!$A:$F,COLUMNS('BS FY21'!$A:$F),FALSE),0) -> 0 | D19: =IFERROR(VLOOKUP($B19,'BS FY21'!$A:$F,COLUMNS('BS FY21'!$A:$C),FALSE),0) -> 0 | E19: =IFERROR(VLOOKUP($B19,'BS FY23'!$A:$J,COLUMNS('BS FY23'!$A:$J),FALSE),0) -> 0 | F19: =IFERROR(VLOOKUP($B19,'BS FY23'!$A:$J,COLUMNS('BS FY23'!$A:$D),FALSE),0) -> 0 | G19: =IFERROR(VLOOKUP($B19,'BS Q1-24'!$A:$J,COLUMNS('BS Q1-24'!$A:$D),FALSE),0) -> 0 | H19: =IFERROR(VLOOKUP($B19,'BS Q2-24'!$A:$J,COLUMNS('BS Q2-24'!$A:$D),FALSE),0) -> 0 | I19: =IFERROR(VLOOKUP($B19,'BS Q3-24'!$A:$J,COLUMNS('BS Q3-24'!$A:$D),FALSE),0) -> 0
A20: Total Debt | B20: Current portion of debt including obligations under finance leases | C20: =IFERROR(VLOOKUP($B20,'BS FY21'!$A:$F,COLUMNS('BS FY21'!$A:$F),FALSE),0) -> 122248 | D20: =IFERROR(VLOOKUP($B20,'BS FY21'!$A:$F,COLUMNS('BS FY21'!$A:$C),FALSE),0) -> 202433 | E20: =IFERROR(VLOOKUP($B20,'BS FY23'!$A:$J,COLUMNS('BS FY23'!$A:$J),FALSE),0) -> 325680 | F20: =IFERROR(VLOOKUP($B20,'BS FY23'!$A:$J,COLUMNS('BS FY23'!$A:$D),FALSE),0) -> 229935 | G20: =IFERROR(VLOOKUP($B20,'BS Q1-24'!$A:$J,COLUMNS('BS Q1-24'!$A:$D),FALSE),0) -> 244048 | H20: =IFERROR(VLOOKUP($B20,'BS Q2-24'!$A:$J,COLUMNS('BS Q2-24'!$A:$D),FALSE),0) -> 257829 | I20: =IFERROR(VLOOKUP($B20,'BS Q3-24'!$A:$J,COLUMNS('BS Q3-24'!$A:$D),FALSE),0) -> 206335 | J20: =I20 -> 206335 | K20: =J20 -> 206335 | L20: =K20 -> 206335 | M20: =L20 -> 206335 | N20: =M20 -> 206335 | O20: =N20 -> 206335 | P20: =O20 -> 206335 | Q20: =P20 -> 206335 | R20: =Q20 -> 206335
B21: Current portion of operating lease liabilities | C21: =IFERROR(VLOOKUP($B21,'BS FY21'!$A:$F,COLUMNS('BS FY21'!$A:$F),FALSE),0) -> 21815 | D21: =IFERROR(VLOOKUP($B21,'BS FY21'!$A:$F,COLUMNS('BS FY21'!$A:$C),FALSE),0) -> 13927 | E21: =IFERROR(VLOOKUP($B21,'BS FY23'!$A:$J,COLUMNS('BS FY23'!$A:$J),FALSE),0) -> 18560 | F21: =IFERROR(VLOOKUP($B21,'BS FY23'!$A:$J,COLUMNS('BS FY23'!$A:$D),FALSE),0) -> 21168 | G21: =IFERROR(VLOOKUP($B21,'BS Q1-24'!$A:$J,COLUMNS('BS Q1-24'!$A:$D),FALSE),0) -> 20694 | H21: =IFERROR(VLOOKUP($B21,'BS Q2-24'!$A:$J,COLUMNS('BS Q2-24'!$A:$D),FALSE),0) -> 21686 | I21: =IFERROR(VLOOKUP($B21,'BS Q3-24'!$A:$J,COLUMNS('BS Q3-24'!$A:$D),FALSE),0) -> 22235 | J21: =I21/I$49*J$49 -> 23182.569 | K21: =J21/J$49*K$49 -> 23182.569 | L21: =K21/K$49*L$49 -> 22568.339 | M21: =L21/L$49*M$49 -> 23624.537 | N21: =M21/M$49*N$49 -> 25362.628 | O21: =N21/N$49*O$49 -> 26032.774 | P21: =O21/O$49*P$49 -> 27356.505 | Q21: =P21/P$49*Q$49 -> 28420.055 | R21: =Q21/Q$49*R$49 -> 29708.061
B22: Accounts payable | C22: =IFERROR(VLOOKUP($B22,'BS FY21'!$A:$F,COLUMNS('BS FY21'!$A:$F),FALSE),0) -> 125775 | D22: =IFERROR(VLOOKUP($B22,'BS FY21'!$A:$F,COLUMNS('BS FY21'!$A:$C),FALSE),0) -> 186330 | E22: =IFERROR(VLOOKUP($B22,'BS FY23'!$A:$J,COLUMNS('BS FY23'!$A:$J),FALSE),0) -> 217378 | F22: =IFERROR(VLOOKUP($B22,'BS FY23'!$A:$J,COLUMNS('BS FY23'!$A:$D),FALSE),0) -> 226299 | G22: =IFERROR(VLOOKUP($B22,'BS Q1-24'!$A:$J,COLUMNS('BS Q1-24'!$A:$D),FALSE),0) -> 188976 | H22: =IFERROR(VLOOKUP($B22,'BS Q2-24'!$A:$J,COLUMNS('BS Q2-24'!$A:$D),FALSE),0) -> 208111 | I22: =IFERROR(VLOOKUP($B22,'BS Q3-24'!$A:$J,COLUMNS('BS Q3-24'!$A:$D),FALSE),0) -> 205644 | J22: =I22/I$49*J$49 -> 214407.75 | K22: =J22/J$49*K$49 -> 214407.75 | L22: =K22/K$49*L$49 -> 208726.94 | M22: =L22/L$49*M$49 -> 218495.36 | N22: =M22/M$49*N$49 -> 234570.38 | O22: =N22/N$49*O$49 -> 240768.33 | P22: =O22/O$49*P$49 -> 253011.06 | Q22: =P22/P$49*Q$49 -> 262847.48 | R22: =Q22/Q$49*R$49 -> 274759.82
B23: Accrued expenses and other current liabilities | C23: =IFERROR(VLOOKUP($B23,'BS FY21'!$A:$F,COLUMNS('BS FY21'!$A:$F),FALSE),0) -> 138895 | D23: =IFERROR(VLOOKUP($B23,'BS FY21'!$A:$F,COLUMNS('BS FY21'!$A:$C),FALSE),0) -> 159238 | E23: =IFERROR(VLOOKUP($B23,'BS FY23'!$A:$J,COLUMNS('BS FY23'!$A:$J),FALSE),0) -> 164326 | F23: =IFERROR(VLOOKUP($B23,'BS FY23'!$A:$J,COLUMNS('BS FY23'!$A:$D),FALSE),0) -> 172034 | G23: =IFERROR(VLOOKUP($B23,'BS Q1-24'!$A:$J,COLUMNS('BS Q1-24'!$A:$D),FALSE),0) -> 174140 | H23: =IFERROR(VLOOKUP($B23,'BS Q2-24'!$A:$J,COLUMNS('BS Q2-24'!$A:$D),FALSE),0) -> 142804 | I23: =IFERROR(VLOOKUP($B23,'BS Q3-24'!$A:$J,COLUMNS('BS Q3-24'!$A:$D),FALSE),0) -> 149298 | J23: =I23/I$49*J$49 -> 155660.5 | K23: =J23/J$49*K$49 -> 155660.5 | L23: =K23/K$49*L$49 -> 151536.22 | M23: =L23/L$49*M$49 -> 158628.11 | N23: =M23/M$49*N$49 -> 170298.61 | O23: =N23/N$49*O$49 -> 174798.34 | P23: =O23/O$49*P$49 -> 183686.59 | Q23: =P23/P$49*Q$49 -> 190827.85 | R23: =Q23/Q$49*R$49 -> 199476.24
B24: Total current liabilities | C24: =IFERROR(VLOOKUP($B24,'BS FY21'!$A:$F,COLUMNS('BS FY21'!$A:$F),FALSE),0) -> 408733 | D24: =IFERROR(VLOOKUP($B24,'BS FY21'!$A:$F,COLUMNS('BS FY21'!$A:$C),FALSE),0) -> 561928 | E24: =IFERROR(VLOOKUP($B24,'BS FY23'!$A:$J,COLUMNS('BS FY23'!$A:$J),FALSE),0) -> 725944 | F24: =IFERROR(VLOOKUP($B24,'BS FY23'!$A:$J,COLUMNS('BS FY23'!$A:$D),FALSE),0) -> 649436 | G24: =IFERROR(VLOOKUP($B24,'BS Q1-24'!$A:$J,COLUMNS('BS Q1-24'!$A:$D),FALSE),0) -> 627858 | H24: =IFERROR(VLOOKUP($B24,'BS Q2-24'!$A:$J,COLUMNS('BS Q2-24'!$A:$D),FALSE),0) -> 630430 | I24: =IFERROR(VLOOKUP($B24,'BS Q3-24'!$A:$J,COLUMNS('BS Q3-24'!$A:$D),FALSE),0) -> 583512 | J24: =(I24-I20)/I49*J49+J20 -> 599585.82 | K24: =(J24-J20)/J49*K49+K20 -> 599585.82 | L24: =(K24-K20)/K49*L49+L20 -> 589166.5 | M24: =(L24-L20)/L49*M49+M20 -> 607083.01 | N24: =(M24-M20)/M49*N49+N20 -> 636566.62 | O24: =(N24-N20)/N49*O49+O20 -> 647934.44 | P24: =(O24-O20)/O49*P49+P20 -> 670389.16 | Q24: =(P24-P20)/P49*Q49+Q20 -> 688430.39 | R24: =(Q24-Q20)/Q49*R49+R20 -> 710279.11
A25: Total Debt | B25: Long-term debt including obligations under finance leases | C25: =IFERROR(VLOOKUP($B25,'BS FY21'!$A:$F,COLUMNS('BS FY21'!$A:$F),FALSE),0) -> 497018 | D25: =IFERROR(VLOOKUP($B25,'BS FY21'!$A:$F,COLUMNS('BS FY21'!$A:$C),FALSE),0) -> 583616 | E25: =IFERROR(VLOOKUP($B25,'BS FY23'!$A:$J,COLUMNS('BS FY23'!$A:$J),FALSE),0) -> 468912 | F25: =IFERROR(VLOOKUP($B25,'BS FY23'!$A:$J,COLUMNS('BS FY23'!$A:$D),FALSE),0) -> 224391 | G25: =IFERROR(VLOOKUP($B25,'BS Q1-24'!$A:$J,COLUMNS('BS Q1-24'!$A:$D),FALSE),0) -> 294430 | H25: =IFERROR(VLOOKUP($B25,'BS Q2-24'!$A:$J,COLUMNS('BS Q2-24'!$A:$D),FALSE),0) -> 294474 | I25: =IFERROR(VLOOKUP($B25,'BS Q3-24'!$A:$J,COLUMNS('BS Q3-24'!$A:$D),FALSE),0) -> 299812
B26: Noncurrent operating lease liabilities | C26: =IFERROR(VLOOKUP($B26,'BS FY21'!$A:$F,COLUMNS('BS FY21'!$A:$F),FALSE),0) -> 34379 | D26: =IFERROR(VLOOKUP($B26,'BS FY21'!$A:$F,COLUMNS('BS FY21'!$A:$C),FALSE),0) -> 36429 | E26: =IFERROR(VLOOKUP($B26,'BS FY23'!$A:$J,COLUMNS('BS FY23'!$A:$J),FALSE),0) -> 47616 | F26: =IFERROR(VLOOKUP($B26,'BS FY23'!$A:$J,COLUMNS('BS FY23'!$A:$D),FALSE),0) -> 45924 | G26: =IFERROR(VLOOKUP($B26,'BS Q1-24'!$A:$J,COLUMNS('BS Q1-24'!$A:$D),FALSE),0) -> 41410 | H26: =IFERROR(VLOOKUP($B26,'BS Q2-24'!$A:$J,COLUMNS('BS Q2-24'!$A:$D),FALSE),0) -> 41230 | I26: =IFERROR(VLOOKUP($B26,'BS Q3-24'!$A:$J,COLUMNS('BS Q3-24'!$A:$D),FALSE),0) -> 39532
B27: Deferred income taxes and tax uncertainties | C27: =IFERROR(VLOOKUP($B27,'BS FY21'!$A:$F,COLUMNS('BS FY21'!$A:$F),FALSE),0) -> 121727 | D27: =IFERROR(VLOOKUP($B27,'BS FY21'!$A:$F,COLUMNS('BS FY21'!$A:$C),FALSE),0) -> 108827 | E27: =IFERROR(VLOOKUP($B27,'BS FY23'!$A:$J,COLUMNS('BS FY23'!$A:$J),FALSE),0) -> 124659 | F27: =IFERROR(VLOOKUP($B27,'BS FY23'!$A:$J,COLUMNS('BS FY23'!$A:$D),FALSE),0) -> 131801 | G27: =IFERROR(VLOOKUP($B27,'BS Q1-24'!$A:$J,COLUMNS('BS Q1-24'!$A:$D),FALSE),0) -> 131801 | H27: =IFERROR(VLOOKUP($B27,'BS Q2-24'!$A:$J,COLUMNS('BS Q2-24'!$A:$D),FALSE),0) -> 131761 | I27: =IFERROR(VLOOKUP($B27,'BS Q3-24'!$A:$J,COLUMNS('BS Q3-24'!$A:$D),FALSE),0) -> 130729
B28: Other noncurrent liabilities | C28: 0 | D28: =IFERROR(VLOOKUP($B28,'BS FY21'!$A:$F,COLUMNS('BS FY21'!$A:$C),FALSE),0) -> 9443 | E28: =IFERROR(VLOOKUP($B28,'BS FY23'!$A:$J,COLUMNS('BS FY23'!$A:$J),FALSE),0) -> 0 | F28: =IFERROR(VLOOKUP($B28,'BS FY23'!$A:$J,COLUMNS('BS FY23'!$A:$D),FALSE),0) -> 0 | G28: =IFERROR(VLOOKUP($B28,'BS Q1-24'!$A:$J,COLUMNS('BS Q1-24'!$A:$D),FALSE),0) -> 0 | H28: =IFERROR(VLOOKUP($B28,'BS Q2-24'!$A:$J,COLUMNS('BS Q2-24'!$A:$D),FALSE),0) -> 0 | I28: =IFERROR(VLOOKUP($B28,'BS Q3-24'!$A:$J,COLUMNS('BS Q3-24'!$A:$D),FALSE),0) -> 0
B29: Total liabilities | C29: =IFERROR(VLOOKUP($B29,'BS FY21'!$A:$F,COLUMNS('BS FY21'!$A:$F),FALSE),0) -> 1061857 | D29: =IFERROR(VLOOKUP($B29,'BS FY21'!$A:$F,COLUMNS('BS FY21'!$A:$C),FALSE),0) -> 1300243 | E29: =IFERROR(VLOOKUP($B29,'BS FY23'!$A:$J,COLUMNS('BS FY23'!$A:$J),FALSE),0) -> 1367131 | F29: =IFERROR(VLOOKUP($B29,'BS FY23'!$A:$J,COLUMNS('BS FY23'!$A:$D),FALSE),0) -> 1051552 | G29: =IFERROR(VLOOKUP($B29,'BS Q1-24'!$A:$J,COLUMNS('BS Q1-24'!$A:$D),FALSE),0) -> 1095499 | H29: =IFERROR(VLOOKUP($B29,'BS Q2-24'!$A:$J,COLUMNS('BS Q2-24'!$A:$D),FALSE),0) -> 1097895 | I29: =IFERROR(VLOOKUP($B29,'BS Q3-24'!$A:$J,COLUMNS('BS Q3-24'!$A:$D),FALSE),0) -> 1053585
B30: Commitments and Contingencies | C30: =IFERROR(VLOOKUP($B30,'BS FY21'!$A:$F,COLUMNS('BS FY21'!$A:$F),FALSE),0) -> 0 | D30: =IFERROR(VLOOKUP($B30,'BS FY21'!$A:$F,COLUMNS('BS FY21'!$A:$C),FALSE),0) -> 0 | E30: =IFERROR(VLOOKUP($B30,'BS FY23'!$A:$J,COLUMNS('BS FY23'!$A:$J),FALSE),0) -> 0 | F30: =IFERROR(VLOOKUP($B30,'BS FY23'!$A:$J,COLUMNS('BS FY23'!$A:$D),FALSE),0) -> 0 | G30: =IFERROR(VLOOKUP($B30,'BS Q1-24'!$A:$J,COLUMNS('BS Q1-24'!$A:$D),FALSE),0) -> 0 | H30: =IFERROR(VLOOKUP($B30,'BS Q2-24'!$A:$J,COLUMNS('BS Q2-24'!$A:$D),FALSE),0) -> 0 | I30: =IFERROR(VLOOKUP($B30,'BS Q3-24'!$A:$J,COLUMNS('BS Q3-24'!$A:$D),FALSE),0) -> 0
B31: Shareholders’ Equity: | C31: =IFERROR(VLOOKUP($B31,'BS FY21'!$A:$F,COLUMNS('BS FY21'!$A:$F),FALSE),0) -> 0 | D31: =IFERROR(VLOOKUP($B31,'BS FY21'!$A:$F,COLUMNS('BS FY21'!$A:$C),FALSE),0) -> 0 | E31: =IFERROR(VLOOKUP($B31,'BS FY23'!$A:$J,COLUMNS('BS FY23'!$A:$J),FALSE),0) -> 0 | F31: =IFERROR(VLOOKUP($B31,'BS FY23'!$A:$J,COLUMNS('BS FY23'!$A:$D),FALSE),0) -> 0 | G31: =IFERROR(VLOOKUP($B31,'BS Q1-24'!$A:$J,COLUMNS('BS Q1-24'!$A:$D),FALSE),0) -> 0 | H31: =IFERROR(VLOOKUP($B31,'BS Q2-24'!$A:$J,COLUMNS('BS Q2-24'!$A:$D),FALSE),0) -> 0 | I31: =IFERROR(VLOOKUP($B31,'BS Q3-24'!$A:$J,COLUMNS('BS Q3-24'!$A:$D),FALSE),0) -> 0
B32: MSC Industrial Shareholders’ Equity: | C32: =IFERROR(VLOOKUP($B32,'BS FY21'!$A:$F,COLUMNS('BS FY21'!$A:$F),FALSE),0) -> 0 | D32: =IFERROR(VLOOKUP($B32,'BS FY21'!$A:$F,COLUMNS('BS FY21'!$A:$C),FALSE),0) -> 0 | E32: =IFERROR(VLOOKUP($B32,'BS FY23'!$A:$J,COLUMNS('BS FY23'!$A:$J),FALSE),0) -> 0 | F32: =IFERROR(VLOOKUP($B32,'BS FY23'!$A:$J,COLUMNS('BS FY23'!$A:$D),FALSE),0) -> 0 | G32: =IFERROR(VLOOKUP($B32,'BS Q1-24'!$A:$J,COLUMNS('BS Q1-24'!$A:$D),FALSE),0) -> 0 | H32: =IFERROR(VLOOKUP($B32,'BS Q2-24'!$A:$J,COLUMNS('BS Q2-24'!$A:$D),FALSE),0) -> 0 | I32: =IFERROR(VLOOKUP($B32,'BS Q3-24'!$A:$J,COLUMNS('BS Q3-24'!$A:$D),FALSE),0) -> 0
B33: Preferred Stock | C33: 0 | D33: 0 | E33: 0 | F33: 0 | G33: 0 | H33: 0 | I33: 0
B34: Class A Common Stock | C34: =IFERROR(VLOOKUP($B34,'BS FY21'!$A:$F,COLUMNS('BS FY21'!$A:$F),FALSE),0) -> 47 | D34: =IFERROR(VLOOKUP($B34,'BS FY21'!$A:$F,COLUMNS('BS FY21'!$A:$C),FALSE),0) -> 48 | E34: =IFERROR(VLOOKUP($B34,'BS FY23'!$A:$J,COLUMNS('BS FY23'!$A:$J),FALSE),0) -> 48 | F34: =IFERROR(VLOOKUP($B34,'BS FY23'!$A:$J,COLUMNS('BS FY23'!$A:$D),FALSE),0) -> 48 | G34: =IFERROR(VLOOKUP($B34,'BS Q1-24'!$A:$J,COLUMNS('BS Q1-24'!$A:$D),FALSE),0) -> 58 | H34: =IFERROR(VLOOKUP($B34,'BS Q2-24'!$A:$J,COLUMNS('BS Q2-24'!$A:$D),FALSE),0) -> 58 | I34: =IFERROR(VLOOKUP($B34,'BS Q3-24'!$A:$J,COLUMNS('BS Q3-24'!$A:$D),FALSE),0) -> 57
B35: Class B Common Stock | C35: =IFERROR(VLOOKUP($B35,'BS FY21'!$A:$F,COLUMNS('BS FY21'!$A:$F),FALSE),0) -> 10 | D35: =IFERROR(VLOOKUP($B35,'BS FY21'!$A:$F,COLUMNS('BS FY21'!$A:$C),FALSE),0) -> 9 | E35: =IFERROR(VLOOKUP($B35,'BS FY23'!$A:$J,COLUMNS('BS FY23'!$A:$J),FALSE),0) -> 9 | F35: =IFERROR(VLOOKUP($B35,'BS FY23'!$A:$J,COLUMNS('BS FY23'!$A:$D),FALSE),0) -> 9 | G35: 0 | H35: 0 | I35: 0
B36: Additional paid-in capital | C36: =IFERROR(VLOOKUP($B36,'BS FY21'!$A:$F,COLUMNS('BS FY21'!$A:$F),FALSE),0) -> 690739 | D36: =IFERROR(VLOOKUP($B36,'BS FY21'!$A:$F,COLUMNS('BS FY21'!$A:$C),FALSE),0) -> 740867 | E36: =IFERROR(VLOOKUP($B36,'BS FY23'!$A:$J,COLUMNS('BS FY23'!$A:$J),FALSE),0) -> 798408 | F36: =IFERROR(VLOOKUP($B36,'BS FY23'!$A:$J,COLUMNS('BS FY23'!$A:$D),FALSE),0) -> 849502 | G36: =IFERROR(VLOOKUP($B36,'BS Q1-24'!$A:$J,COLUMNS('BS Q1-24'!$A:$D),FALSE),0) -> 1052729 | H36: =IFERROR(VLOOKUP($B36,'BS Q2-24'!$A:$J,COLUMNS('BS Q2-24'!$A:$D),FALSE),0) -> 1059405 | I36: =IFERROR(VLOOKUP($B36,'BS Q3-24'!$A:$J,COLUMNS('BS Q3-24'!$A:$D),FALSE),0) -> 1063738
B37: Retained earnings | C37: =IFERROR(VLOOKUP($B37,'BS FY21'!$A:$F,COLUMNS('BS FY21'!$A:$F),FALSE),0) -> 749515 | D37: =IFERROR(VLOOKUP($B37,'BS FY21'!$A:$F,COLUMNS('BS FY21'!$A:$C),FALSE),0) -> 532315 | E37: =IFERROR(VLOOKUP($B37,'BS FY23'!$A:$J,COLUMNS('BS FY23'!$A:$J),FALSE),0) -> 681292 | F37: =IFERROR(VLOOKUP($B37,'BS FY23'!$A:$J,COLUMNS('BS FY23'!$A:$D),FALSE),0) -> 755007 | G37: =IFERROR(VLOOKUP($B37,'BS Q1-24'!$A:$J,COLUMNS('BS Q1-24'!$A:$D),FALSE),0) -> 464962 | H37: =IFERROR(VLOOKUP($B37,'BS Q2-24'!$A:$J,COLUMNS('BS Q2-24'!$A:$D),FALSE),0) -> 463874 | I37: =IFERROR(VLOOKUP($B37,'BS Q3-24'!$A:$J,COLUMNS('BS Q3-24'!$A:$D),FALSE),0) -> 470085
B38: Accumulated other comprehensive loss | C38: =IFERROR(VLOOKUP($B38,'BS FY21'!$A:$F,COLUMNS('BS FY21'!$A:$F),FALSE),0) -> -21418 | D38: =IFERROR(VLOOKUP($B38,'BS FY21'!$A:$F,COLUMNS('BS FY21'!$A:$C),FALSE),0) -> -17984 | E38: =IFERROR(VLOOKUP($B38,'BS FY23'!$A:$J,COLUMNS('BS FY23'!$A:$J),FALSE),0) -> -23121 | F38: =IFERROR(VLOOKUP($B38,'BS FY23'!$A:$J,COLUMNS('BS FY23'!$A:$D),FALSE),0) -> -17725 | G38: =IFERROR(VLOOKUP($B38,'BS Q1-24'!$A:$J,COLUMNS('BS Q1-24'!$A:$D),FALSE),0) -> -17277 | H38: =IFERROR(VLOOKUP($B38,'BS Q2-24'!$A:$J,COLUMNS('BS Q2-24'!$A:$D),FALSE),0) -> -17340 | I38: =IFERROR(VLOOKUP($B38,'BS Q3-24'!$A:$J,COLUMNS('BS Q3-24'!$A:$D),FALSE),0) -> -17553
B39: Class A treasury stock | C39: =IFERROR(VLOOKUP($B39,'BS FY21'!$A:$F,COLUMNS('BS FY21'!$A:$F),FALSE),0) -> -103948 | D39: =IFERROR(VLOOKUP($B39,'BS FY21'!$A:$F,COLUMNS('BS FY21'!$A:$C),FALSE),0) -> -104384 | E39: =IFERROR(VLOOKUP($B39,'BS FY23'!$A:$J,COLUMNS('BS FY23'!$A:$J),FALSE),0) -> -106202 | F39: =IFERROR(VLOOKUP($B39,'BS FY23'!$A:$J,COLUMNS('BS FY23'!$A:$D),FALSE),0) -> -107677 | G39: =IFERROR(VLOOKUP($B39,'BS Q1-24'!$A:$J,COLUMNS('BS Q1-24'!$A:$D),FALSE),0) -> -115399 | H39: =IFERROR(VLOOKUP($B39,'BS Q2-24'!$A:$J,COLUMNS('BS Q2-24'!$A:$D),FALSE),0) -> -115488 | I39: =IFERROR(VLOOKUP($B39,'BS Q3-24'!$A:$J,COLUMNS('BS Q3-24'!$A:$D),FALSE),0) -> -114711
B40: Total MSC Industrial shareholders’ equity | C40: =IFERROR(VLOOKUP($B40,'BS FY21'!$A:$F,COLUMNS('BS FY21'!$A:$F),FALSE),0) -> 1314945 | D40: =IFERROR(VLOOKUP($B40,'BS FY21'!$A:$F,COLUMNS('BS FY21'!$A:$C),FALSE),0) -> 1150871 | E40: =IFERROR(VLOOKUP($B40,'BS FY23'!$A:$J,COLUMNS('BS FY23'!$A:$J),FALSE),0) -> 1350434 | F40: =IFERROR(VLOOKUP($B40,'BS FY23'!$A:$J,COLUMNS('BS FY23'!$A:$D),FALSE),0) -> 1479164 | G40: =IFERROR(VLOOKUP($B40,'BS Q1-24'!$A:$J,COLUMNS('BS Q1-24'!$A:$D),FALSE),0) -> 1385073 | H40: =IFERROR(VLOOKUP($B40,'BS Q2-24'!$A:$J,COLUMNS('BS Q2-24'!$A:$D),FALSE),0) -> 1390509 | I40: =IFERROR(VLOOKUP($B40,'BS Q3-24'!$A:$J,COLUMNS('BS Q3-24'!$A:$D),FALSE),0) -> 1401616
B41: Noncontrolling interest | C41: =IFERROR(VLOOKUP($B41,'BS FY21'!$A:$F,COLUMNS('BS FY21'!$A:$F),FALSE),0) -> 5628 | D41: =IFERROR(VLOOKUP($B41,'BS FY21'!$A:$F,COLUMNS('BS FY21'!$A:$C),FALSE),0) -> 11001 | E41: =IFERROR(VLOOKUP($B41,'BS FY23'!$A:$J,COLUMNS('BS FY23'!$A:$J),FALSE),0) -> 11849 | F41: =IFERROR(VLOOKUP($B41,'BS FY23'!$A:$J,COLUMNS('BS FY23'!$A:$D),FALSE),0) -> 13418 | G41: =IFERROR(VLOOKUP($B41,'BS Q1-24'!$A:$J,COLUMNS('BS Q1-24'!$A:$D),FALSE),0) -> 13152 | H41: =IFERROR(VLOOKUP($B41,'BS Q2-24'!$A:$J,COLUMNS('BS Q2-24'!$A:$D),FALSE),0) -> 12990 | I41: =IFERROR(VLOOKUP($B41,'BS Q3-24'!$A:$J,COLUMNS('BS Q3-24'!$A:$D),FALSE),0) -> 12593
B42: Total shareholders' equity | C42: =IFERROR(VLOOKUP($B42,'BS FY21'!$A:$F,COLUMNS('BS FY21'!$A:$F),FALSE),0) -> 1320573 | D42: =IFERROR(VLOOKUP($B42,'BS FY21'!$A:$F,COLUMNS('BS FY21'!$A:$C),FALSE),0) -> 1161872 | E42: =IFERROR(VLOOKUP($B42,'BS FY23'!$A:$J,COLUMNS('BS FY23'!$A:$J),FALSE),0) -> 1362283 | F42: =IFERROR(VLOOKUP($B42,'BS FY23'!$A:$J,COLUMNS('BS FY23'!$A:$D),FALSE),0) -> 1492582 | G42: =IFERROR(VLOOKUP($B42,'BS Q1-24'!$A:$J,COLUMNS('BS Q1-24'!$A:$D),FALSE),0) -> 1398225 | H42: =IFERROR(VLOOKUP($B42,'BS Q2-24'!$A:$J,COLUMNS('BS Q2-24'!$A:$D),FALSE),0) -> 1403499 | I42: =IFERROR(VLOOKUP($B42,'BS Q3-24'!$A:$J,COLUMNS('BS Q3-24'!$A:$D),FALSE),0) -> 1414209
B43: Total liabilities and shareholders’ equity | C43: =IFERROR(VLOOKUP($B43,'BS FY21'!$A:$F,COLUMNS('BS FY21'!$A:$F),FALSE),0) -> 2382430 | D43: =IFERROR(VLOOKUP($B43,'BS FY21'!$A:$F,COLUMNS('BS FY21'!$A:$C),FALSE),0) -> 2462115 | E43: =IFERROR(VLOOKUP($B43,'BS FY23'!$A:$J,COLUMNS('BS FY23'!$A:$J),FALSE),0) -> 2729414 | F43: =IFERROR(VLOOKUP($B43,'BS FY23'!$A:$J,COLUMNS('BS FY23'!$A:$D),FALSE),0) -> 2544134 | G43: =IFERROR(VLOOKUP($B43,'BS Q1-24'!$A:$J,COLUMNS('BS Q1-24'!$A:$D),FALSE),0) -> 2493724 | H43: =IFERROR(VLOOKUP($B43,'BS Q2-24'!$A:$J,COLUMNS('BS Q2-24'!$A:$D),FALSE),0) -> 2501394 | I43: =IFERROR(VLOOKUP($B43,'BS Q3-24'!$A:$J,COLUMNS('BS Q3-24'!$A:$D),FALSE),0) -> 2467794
C44: =C43-C17 -> 0 | D44: =D43-D17 -> 0 | E44: =E43-E17 -> 0 | F44: =F43-F17 -> 0 | G44: =G43-G17 -> 0 | H44: =H43-H17 -> 0 | I44: =I43-I17 -> 0
C45: =SUM(C7:C43) -> 14873598 | D45: =SUM(D7:D43) -> 15337619 | E45: =SUM(E7:E43) -> 17267071 | F45: =SUM(F7:F43) -> 16166783 | G45: =SUM(G7:G43) -> 15752517 | H45: =SUM(H7:H43) -> 15792822 | I45: =SUM(I7:I43) -> 15536946
B46: Check | C46: ='BS FY21'!F49 -> 14873598 | D46: ='BS FY21'!C49 -> 15337619 | E46: ='BS FY23'!J45 -> 17267071 | F46: ='BS FY23'!D45 -> 16166783 | G46: ='BS Q1-24'!D46 -> 15752517 | H46: ='BS Q2-24'!D46 -> 15792822 | I46: ='BS Q3-24'!D46 -> 15536946
C47: =C45-C46 -> 0 | D47: =D45-D46 -> 0 | E47: =E45-E46 -> 0 | F47: =F45-F46 -> 0 | G47: =G45-G46 -> 0 | H47: =H45-H46 -> 0 | I47: =I45-I46 -> 0
C49: =C11-C7-C24+C20 -> 826074 | D49: =D11-D7-D24+D20 -> 914214 | E49: =E11-E7-E24+E20 -> 1099822 | F49: =F11-F7-F24+F20 -> 847960 | G49: =G11-G7-G24+G20 -> 861351 | H49: =H11-H7-H24+H20 -> 870085 | I49: =I11-I7-I24+I20 -> 809743 | J49: =J3*J2*4 -> 844251.1 | K49: =K3*K2 -> 844251.1 | L49: =L3*L2 -> 821882.36 | M49: =M3*M2 -> 860346.46 | N49: =N3*N2 -> 923643.38 | O49: =O3*O2 -> 948048.4 | P49: =P3*P2 -> 996255.37 | Q49: =Q3*Q2 -> 1034987.2 | R49: =R3*R2 -> 1081893.2
B50: Check | C50: =C11-C24-C49-C7+C20 -> 0 | D50: =D11-D24-D49-D7+D20 -> 0 | E50: =E11-E24-E49-E7+E20 -> 0 | F50: =F11-F24-F49-F7+F20 -> 0 | G50: =G11-G24-G49-G7+G20 -> 0 | H50: =H11-H24-H49-H7+H20 -> 0 | I50: =I11-I24-I49-I7+I20 -> 0 | J50: =J11-J24-J49-J7+J20 -> 0 | ... R50: =R11-R24-R49-R7+R20 -> 3.4924597e-10

Sheet Balance Sheet NWC (Downside)
B2: Revenue | J2: ='3-Statement (Base)'!J9 -> 952178.75 | K2: ='3-Statement (Base)'!K9 -> 3820845.7 | L2: ='3-Statement (Base)'!L9 -> 3800977.3 | M2: ='3-Statement (Base)'!M9 -> 3978863.1 | N2: ='3-Statement (Base)'!N9 -> 4240672.3 | O2: ='3-Statement (Base)'!O9 -> 4373829.4 | P2: ='3-Statement (Base)'!P9 -> 4592520.9 | Q2: ='3-Statement (Base)'!Q9 -> 4765934.4 | R2: ='3-Statement (Base)'!R9 -> 4986845
B3: NWC % Revenue | J3: ='3-Statement (Downside)'!J24 -> 0.22166298 | K3: ='3-Statement (Downside)'!K24 -> 0.22095922 | L3: ='3-Statement (Downside)'!L24 -> 0.24022922 | M3: ='3-Statement (Downside)'!M24 -> 0.23422922 | N3: ='3-Statement (Downside)'!N24 -> 0.22380589 | O3: ='3-Statement (Downside)'!O24 -> 0.21975477 | P3: ='3-Statement (Downside)'!P24 -> 0.21692996 | Q3: ='3-Statement (Downside)'!Q24 -> 0.21716354 | R3: ='3-Statement (Downside)'!R24 -> 0.21694942
C4: ='3-Statement (Base)'!C2 -> 44196 | D4: ='3-Statement (Base)'!D2 -> 44561 | E4: ='3-Statement (Base)'!E2 -> 44926 | F4: ='3-Statement (Base)'!F2 -> 45291 | G4: ='3-Statement (Base)'!G2 -> Q1-24 | H4: ='3-Statement (Base)'!H2 -> Q2-24 | I4: ='3-Statement (Base)'!I2 -> Q3-24 | J4: ='3-Statement (Base)'!J2 -> Q4-24 | ... R4: ='3-Statement (Base)'!R2 -> 48213
B5: ASSETS
B6: Current Assets:
B7: Cash and cash equivalents | C7: =IFERROR(VLOOKUP($B7,'BS FY21'!$A:$F,COLUMNS('BS FY21'!$A:$F),FALSE),0) -> 125211 | D7: =IFERROR(VLOOKUP($B7,'BS FY21'!$A:$F,COLUMNS('BS FY21'!$A:$C),FALSE),0) -> 40536 | E7: =IFERROR(VLOOKUP($B7,'BS FY23'!$A:$J,COLUMNS('BS FY23'!$A:$J),FALSE),0) -> 43537 | F7: =IFERROR(VLOOKUP($B7,'BS FY23'!$A:$J,COLUMNS('BS FY23'!$A:$D),FALSE),0) -> 50052 | G7: =IFERROR(VLOOKUP($B7,'BS Q1-24'!$A:$J,COLUMNS('BS Q1-24'!$A:$D),FALSE),0) -> 25805 | H7: =IFERROR(VLOOKUP($B7,'BS Q2-24'!$A:$J,COLUMNS('BS Q2-24'!$A:$D),FALSE),0) -> 22227 | I7: =IFERROR(VLOOKUP($B7,'BS Q3-24'!$A:$J,COLUMNS('BS Q3-24'!$A:$D),FALSE),0) -> 25928 | J7: ='3-Statement (Downside)'!J73 -> 25000 | K7: ='3-Statement (Downside)'!K73 -> 25000 | L7: ='3-Statement (Downside)'!L73 -> 25000 | M7: ='3-Statement (Downside)'!M73 -> 25000 | N7: ='3-Statement (Downside)'!N73 -> 25000 | O7: ='3-Statement (Downside)'!O73 -> 25000 | P7: ='3-Statement (Downside)'!P73 -> 25000 | Q7: ='3-Statement (Downside)'!Q73 -> 25000 | R7: ='3-Statement (Downside)'!R73 -> 25000
B8: Accounts receivable | C8: =IFERROR(VLOOKUP($B8,'BS FY21'!$A:$F,COLUMNS('BS FY21'!$A:$F),FALSE),0) -> 491743 | D8: =IFERROR(VLOOKUP($B8,'BS FY21'!$A:$F,COLUMNS('BS FY21'!$A:$C),FALSE),0) -> 560373 | E8: =IFERROR(VLOOKUP($B8,'BS FY23'!$A:$J,COLUMNS('BS FY23'!$A:$J),FALSE),0) -> 687608 | F8: =IFERROR(VLOOKUP($B8,'BS FY23'!$A:$J,COLUMNS('BS FY23'!$A:$D),FALSE),0) -> 435421 | G8: =IFERROR(VLOOKUP($B8,'BS Q1-24'!$A:$J,COLUMNS('BS Q1-24'!$A:$D),FALSE),0) -> 414280 | H8: =IFERROR(VLOOKUP($B8,'BS Q2-24'!$A:$J,COLUMNS('BS Q2-24'!$A:$D),FALSE),0) -> 428699 | I8: =IFERROR(VLOOKUP($B8,'BS Q3-24'!$A:$J,COLUMNS('BS Q3-24'!$A:$D),FALSE),0) -> 419810 | J8: =I8/I$49*J$49 -> 437700.67 | K8: =J8/J$49*K$49 -> 437700.67 | L8: =K8/K$49*L$49 -> 473398.29 | M8: =L8/L$49*M$49 -> 483176.32 | N8: =M8/M$49*N$49 -> 492052.9 | O8: =N8/N$49*O$49 -> 498317.04 | P8: =O8/O$49*P$49 -> 516507.05 | Q8: =P8/P$49*Q$49 -> 536587.5 | R8: =Q8/Q$49*R$49 -> 560905.83
B9: Inventories | C9: =IFERROR(VLOOKUP($B9,'BS FY21'!$A:$F,COLUMNS('BS FY21'!$A:$F),FALSE),0) -> 543106 | D9: =IFERROR(VLOOKUP($B9,'BS FY21'!$A:$F,COLUMNS('BS FY21'!$A:$C),FALSE),0) -> 624169 | E9: =IFERROR(VLOOKUP($B9,'BS FY23'!$A:$J,COLUMNS('BS FY23'!$A:$J),FALSE),0) -> 715625 | F9: =IFERROR(VLOOKUP($B9,'BS FY23'!$A:$J,COLUMNS('BS FY23'!$A:$D),FALSE),0) -> 726521 | G9: =IFERROR(VLOOKUP($B9,'BS Q1-24'!$A:$J,COLUMNS('BS Q1-24'!$A:$D),FALSE),0) -> 709362 | H9: =IFERROR(VLOOKUP($B9,'BS Q2-24'!$A:$J,COLUMNS('BS Q2-24'!$A:$D),FALSE),0) -> 685373 | I9: =IFERROR(VLOOKUP($B9,'BS Q3-24'!$A:$J,COLUMNS('BS Q3-24'!$A:$D),FALSE),0) -> 665638 | J9: =I9/I$49*J$49 -> 694004.91 | K9: =J9/J$49*K$49 -> 694004.91 | L9: =K9/K$49*L$49 -> 750605.97 | M9: =L9/L$49*M$49 -> 766109.72 | N9: =M9/M$49*N$49 -> 780184.15 | O9: =N9/N$49*O$49 -> 790116.38 | P9: =O9/O$49*P$49 -> 818957.9 | Q9: =P9/P$49*Q$49 -> 850796.87 | R9: =Q9/Q$49*R$49 -> 889355.27
B10: Prepaid expenses and other current assets | C10: =IFERROR(VLOOKUP($B10,'BS FY21'!$A:$F,COLUMNS('BS FY21'!$A:$F),FALSE),0) -> 77710 | D10: =IFERROR(VLOOKUP($B10,'BS FY21'!$A:$F,COLUMNS('BS FY21'!$A:$C),FALSE),0) -> 89167 | E10: =IFERROR(VLOOKUP($B10,'BS FY23'!$A:$J,COLUMNS('BS FY23'!$A:$J),FALSE),0) -> 96853 | F10: =IFERROR(VLOOKUP($B10,'BS FY23'!$A:$J,COLUMNS('BS FY23'!$A:$D),FALSE),0) -> 105519 | G10: =IFERROR(VLOOKUP($B10,'BS Q1-24'!$A:$J,COLUMNS('BS Q1-24'!$A:$D),FALSE),0) -> 121519 | H10: =IFERROR(VLOOKUP($B10,'BS Q2-24'!$A:$J,COLUMNS('BS Q2-24'!$A:$D),FALSE),0) -> 128614 | I10: =IFERROR(VLOOKUP($B10,'BS Q3-24'!$A:$J,COLUMNS('BS Q3-24'!$A:$D),FALSE),0) -> 101472 | J10: =I10/I$49*J$49 -> 105796.34 | K10: =J10/J$49*K$49 -> 105796.34 | L10: =K10/K$49*L$49 -> 114424.79 | M10: =L10/L$49*M$49 -> 116788.23 | N10: =M10/M$49*N$49 -> 118933.78 | O10: =N10/N$49*O$49 -> 120447.88 | P10: =O10/O$49*P$49 -> 124844.58 | Q10: =P10/P$49*Q$49 -> 129698.21 | R10: =Q10/Q$49*R$49 -> 135576.18
